Workbook

Sheet Summary
A1: Place-based data inventory · refined set · summary
A2: Counts are live formulas over the Verification tab (every kept dataset), except the funnel (fixed counts; sources named).
A4: Tier × theme | B4: Gold | C4: Silver | D4: Bronze | E4: Browser needed | F4: Failed | G4: Total
B5: =COUNTIFS(Verification!$D$2:$D$667,$A5,Verification!$B$2:$B$667,"Gold") | C5: =COUNTIFS(Verification!$D$2:$D$667,$A5,Verification!$B$2:$B$667,"Silver") | D5: =COUNTIFS(Verification!$D$2:$D$667,$A5,Verification!$B$2:$B$667,"Bronze") | E5: =COUNTIFS(Verification!$D$2:$D$667,$A5,Verification!$B$2:$B$667,"Browser needed") | F5: =COUNTIFS(Verification!$D$2:$D$667,$A5,Verification!$B$2:$B$667,"Failed") | G5: =SUM(B5:F5)
A6: air quality | B6: =COUNTIFS(Verification!$D$2:$D$667,$A6,Verification!$B$2:$B$667,"Gold") | C6: =COUNTIFS(Verification!$D$2:$D$667,$A6,Verification!$B$2:$B$667,"Silver") | D6: =COUNTIFS(Verification!$D$2:$D$667,$A6,Verification!$B$2:$B$667,"Bronze") | E6: =COUNTIFS(Verification!$D$2:$D$667,$A6,Verification!$B$2:$B$667,"Browser needed") | F6: =COUNTIFS(Verification!$D$2:$D$667,$A6,Verification!$B$2:$B$667,"Failed") | G6: =SUM(B6:F6)
A7: boundaries | B7: =COUNTIFS(Verification!$D$2:$D$667,$A7,Verification!$B$2:$B$667,"Gold") | C7: =COUNTIFS(Verification!$D$2:$D$667,$A7,Verification!$B$2:$B$667,"Silver") | D7: =COUNTIFS(Verification!$D$2:$D$667,$A7,Verification!$B$2:$B$667,"Bronze") | E7: =COUNTIFS(Verification!$D$2:$D$667,$A7,Verification!$B$2:$B$667,"Browser needed") | F7: =COUNTIFS(Verification!$D$2:$D$667,$A7,Verification!$B$2:$B$667,"Failed") | G7: =SUM(B7:F7)
A8: built_environment | B8: =COUNTIFS(Verification!$D$2:$D$667,$A8,Verification!$B$2:$B$667,"Gold") | C8: =COUNTIFS(Verification!$D$2:$D$667,$A8,Verification!$B$2:$B$667,"Silver") | D8: =COUNTIFS(Verification!$D$2:$D$667,$A8,Verification!$B$2:$B$667,"Bronze") | E8: =COUNTIFS(Verification!$D$2:$D$667,$A8,Verification!$B$2:$B$667,"Browser needed") | F8: =COUNTIFS(Verification!$D$2:$D$667,$A8,Verification!$B$2:$B$667,"Failed") | G8: =SUM(B8:F8)
A9: climate_hazard | B9: =COUNTIFS(Verification!$D$2:$D$667,$A9,Verification!$B$2:$B$667,"Gold") | C9: =COUNTIFS(Verification!$D$2:$D$667,$A9,Verification!$B$2:$B$667,"Silver") | D9: =COUNTIFS(Verification!$D$2:$D$667,$A9,Verification!$B$2:$B$667,"Bronze") | E9: =COUNTIFS(Verification!$D$2:$D$667,$A9,Verification!$B$2:$B$667,"Browser needed") | F9: =COUNTIFS(Verification!$D$2:$D$667,$A9,Verification!$B$2:$B$667,"Failed") | G9: =SUM(B9:F9)
A10: demographics | B10: =COUNTIFS(Verification!$D$2:$D$667,$A10,Verification!$B$2:$B$667,"Gold") | C10: =COUNTIFS(Verification!$D$2:$D$667,$A10,Verification!$B$2:$B$667,"Silver") | D10: =COUNTIFS(Verification!$D$2:$D$667,$A10,Verification!$B$2:$B$667,"Bronze") | E10: =COUNTIFS(Verification!$D$2:$D$667,$A10,Verification!$B$2:$B$667,"Browser needed") | F10: =COUNTIFS(Verification!$D$2:$D$667,$A10,Verification!$B$2:$B$667,"Failed") | G10: =SUM(B10:F10)
A11: environment | B11: =COUNTIFS(Verification!$D$2:$D$667,$A11,Verification!$B$2:$B$667,"Gold") | C11: =COUNTIFS(Verification!$D$2:$D$667,$A11,Verification!$B$2:$B$667,"Silver") | D11: =COUNTIFS(Verification!$D$2:$D$667,$A11,Verification!$B$2:$B$667,"Bronze") | E11: =COUNTIFS(Verification!$D$2:$D$667,$A11,Verification!$B$2:$B$667,"Browser needed") | F11: =COUNTIFS(Verification!$D$2:$D$667,$A11,Verification!$B$2:$B$667,"Failed") | G11: =SUM(B11:F11)
A12: food_access | B12: =COUNTIFS(Verification!$D$2:$D$667,$A12,Verification!$B$2:$B$667,"Gold") | C12: =COUNTIFS(Verification!$D$2:$D$667,$A12,Verification!$B$2:$B$667,"Silver") | D12: =COUNTIFS(Verification!$D$2:$D$667,$A12,Verification!$B$2:$B$667,"Bronze") | E12: =COUNTIFS(Verification!$D$2:$D$667,$A12,Verification!$B$2:$B$667,"Browser needed") | F12: =COUNTIFS(Verification!$D$2:$D$667,$A12,Verification!$B$2:$B$667,"Failed") | G12: =SUM(B12:F12)
A13: health surveys | B13: =COUNTIFS(Verification!$D$2:$D$667,$A13,Verification!$B$2:$B$667,"Gold") | C13: =COUNTIFS(Verification!$D$2:$D$667,$A13,Verification!$B$2:$B$667,"Silver") | D13: =COUNTIFS(Verification!$D$2:$D$667,$A13,Verification!$B$2:$B$667,"Bronze") | E13: =COUNTIFS(Verification!$D$2:$D$667,$A13,Verification!$B$2:$B$667,"Browser needed") | F13: =COUNTIFS(Verification!$D$2:$D$667,$A13,Verification!$B$2:$B$667,"Failed") | G13: =SUM(B13:F13)
A14: health_outcome | B14: =COUNTIFS(Verification!$D$2:$D$667,$A14,Verification!$B$2:$B$667,"Gold") | C14: =COUNTIFS(Verification!$D$2:$D$667,$A14,Verification!$B$2:$B$667,"Silver") | D14: =COUNTIFS(Verification!$D$2:$D$667,$A14,Verification!$B$2:$B$667,"Bronze") | E14: =COUNTIFS(Verification!$D$2:$D$667,$A14,Verification!$B$2:$B$667,"Browser needed") | F14: =COUNTIFS(Verification!$D$2:$D$667,$A14,Verification!$B$2:$B$667,"Failed") | G14: =SUM(B14:F14)
A15: other | B15: =COUNTIFS(Verification!$D$2:$D$667,$A15,Verification!$B$2:$B$667,"Gold") | C15: =COUNTIFS(Verification!$D$2:$D$667,$A15,Verification!$B$2:$B$667,"Silver") | D15: =COUNTIFS(Verification!$D$2:$D$667,$A15,Verification!$B$2:$B$667,"Bronze") | E15: =COUNTIFS(Verification!$D$2:$D$667,$A15,Verification!$B$2:$B$667,"Browser needed") | F15: =COUNTIFS(Verification!$D$2:$D$667,$A15,Verification!$B$2:$B$667,"Failed") | G15: =SUM(B15:F15)
A16: sdoh | B16: =COUNTIFS(Verification!$D$2:$D$667,$A16,Verification!$B$2:$B$667,"Gold") | C16: =COUNTIFS(Verification!$D$2:$D$667,$A16,Verification!$B$2:$B$667,"Silver") | D16: =COUNTIFS(Verification!$D$2:$D$667,$A16,Verification!$B$2:$B$667,"Bronze") | E16: =COUNTIFS(Verification!$D$2:$D$667,$A16,Verification!$B$2:$B$667,"Browser needed") | F16: =COUNTIFS(Verification!$D$2:$D$667,$A16,Verification!$B$2:$B$667,"Failed") | G16: =SUM(B16:F16)
A17: socioeconomic | B17: =COUNTIFS(Verification!$D$2:$D$667,$A17,Verification!$B$2:$B$667,"Gold") | C17: =COUNTIFS(Verification!$D$2:$D$667,$A17,Verification!$B$2:$B$667,"Silver") | D17: =COUNTIFS(Verification!$D$2:$D$667,$A17,Verification!$B$2:$B$667,"Bronze") | E17: =COUNTIFS(Verification!$D$2:$D$667,$A17,Verification!$B$2:$B$667,"Browser needed") | F17: =COUNTIFS(Verification!$D$2:$D$667,$A17,Verification!$B$2:$B$667,"Failed") | G17: =SUM(B17:F17)
... A20: water quality | B20: =COUNTIFS(Verification!$D$2:$D$667,$A20,Verification!$B$2:$B$667,"Gold") | C20: =COUNTIFS(Verification!$D$2:$D$667,$A20,Verification!$B$2:$B$667,"Silver") | D20: =COUNTIFS(Verification!$D$2:$D$667,$A20,Verification!$B$2:$B$667,"Bronze") | E20: =COUNTIFS(Verification!$D$2:$D$667,$A20,Verification!$B$2:$B$667,"Browser needed") | F20: =COUNTIFS(Verification!$D$2:$D$667,$A20,Verification!$B$2:$B$667,"Failed") | G20: =SUM(B20:F20)
A21: Total | B21: =SUM(B5:B20) | C21: =SUM(C5:C20) | D21: =SUM(D5:D20) | E21: =SUM(E5:E20) | F21: =SUM(F5:F20) | G21: =SUM(G5:G20)
A23: URL health | B23: Datasets
A24: healthy | B24: =COUNTIF(Verification!$E$2:$E$667,A24)
A25: degraded | B25: =COUNTIF(Verification!$E$2:$E$667,A25)
A26: moved | B26: =COUNTIF(Verification!$E$2:$E$667,A26)
A27: blocked | B27: =COUNTIF(Verification!$E$2:$E$667,A27)
A28: dead | B28: =COUNTIF(Verification!$E$2:$E$667,A28)
A29: n.a. | B29: =COUNTIF(Verification!$E$2:$E$667,A29)
A31: License class (content checks) | B31: Datasets
A32: open | B32: =COUNTIF(Verification!$F$2:$F$667,A32)
A33: attribution | B33: =COUNTIF(Verification!$F$2:$F$667,A33)
A34: non-commercial | B34: =COUNTIF(Verification!$F$2:$F$667,A34)
A35: registration | B35: =COUNTIF(Verification!$F$2:$F$667,A35)
A36: restricted | B36: =COUNTIF(Verification!$F$2:$F$667,A36)
A37: unknown | B37: =COUNTIF(Verification!$F$2:$F$667,A37)
A38: not checked | B38: =COUNTIF(Verification!$F$2:$F$667,A38)
A40: Finest unit | B40: Datasets
A41: point | B41: =COUNTIF(Verification!$G$2:$G$667,A41)
A42: unknown | B42: =COUNTIF(Verification!$G$2:$G$667,A42)
A43: tract | B43: =COUNTIF(Verification!$G$2:$G$667,A43)
A44: county | B44: =COUNTIF(Verification!$G$2:$G$667,A44)
A45: postcode_small_area | B45: =COUNTIF(Verification!$G$2:$G$667,A45)
A46: country | B46: =COUNTIF(Verification!$G$2:$G$667,A46)
A47: grid_1km | B47: =COUNTIF(Verification!$G$2:$G$667,A47)
A48: polygon | B48: =COUNTIF(Verification!$G$2:$G$667,A48)
A49: state | B49: =COUNTIF(Verification!$G$2:$G$667,A49)
A50: grid_30m | B50: =COUNTIF(Verification!$G$2:$G$667,A50)
A51: block_group | B51: =COUNTIF(Verification!$G$2:$G$667,A51)
A52: block | B52: =COUNTIF(Verification!$G$2:$G$667,A52)
... A58: line | B58: =COUNTIF(Verification!$G$2:$G$667,A58)
A59: (blank) | B59: =COUNTBLANK(Verification!$G$2:$G$667)
A60: grid_0.25deg | B60: =COUNTIF(Verification!$G$2:$G$667,A60)
A61: points | B61: =COUNTIF(Verification!$G$2:$G$667,A61)
A62: grid_10m | B62: =COUNTIF(Verification!$G$2:$G$667,A62)
A63: grid_0.01deg | B63: =COUNTIF(Verification!$G$2:$G$667,A63)
A64: grid_0.5deg | B64: =COUNTIF(Verification!$G$2:$G$667,A64)
A65: zip | B65: =COUNTIF(Verification!$G$2:$G$667,A65)
A66: zcta_zip | B66: =COUNTIF(Verification!$G$2:$G$667,A66)
A67: points (OSM) | B67: =COUNTIF(Verification!$G$2:$G$667,A67)
A68: raster | B68: =COUNTIF(Verification!$G$2:$G$667,A68)
A69: state (50 states + DC code; no local) | B69: =COUNTIF(Verification!$G$2:$G$667,A69)
A70: grid_300m | B70: =COUNTIF(Verification!$G$2:$G$667,A70)
A71: grid_0.1deg | B71: =COUNTIF(Verification!$G$2:$G$667,A71)
... A204: facility (centre); coordinates not confirmed | B204: =COUNTIF(Verification!$G$2:$G$667,A204)
A206: Gaia fit × health relevance | B206: Health 3 | C206: Health 2 | D206: Health 1 | E206: Health 0 | F206: Unknown | G206: Total
A207: Joins today | B207: =COUNTIFS(Verification!$H$2:$H$667,$A207,Verification!$I$2:$I$667,3) | C207: =COUNTIFS(Verification!$H$2:$H$667,$A207,Verification!$I$2:$I$667,2) | D207: =COUNTIFS(Verification!$H$2:$H$667,$A207,Verification!$I$2:$I$667,1) | E207: =COUNTIFS(Verification!$H$2:$H$667,$A207,Verification!$I$2:$I$667,0) | F207: =COUNTIFS(Verification!$H$2:$H$667,$A207,Verification!$I$2:$I$667,"unknown") | G207: =COUNTIF(Verification!$H$2:$H$667,$A207)
A208: Needs a count/distance step | B208: =COUNTIFS(Verification!$H$2:$H$667,$A208,Verification!$I$2:$I$667,3) | C208: =COUNTIFS(Verification!$H$2:$H$667,$A208,Verification!$I$2:$I$667,2) | D208: =COUNTIFS(Verification!$H$2:$H$667,$A208,Verification!$I$2:$I$667,1) | E208: =COUNTIFS(Verification!$H$2:$H$667,$A208,Verification!$I$2:$I$667,0) | F208: =COUNTIFS(Verification!$H$2:$H$667,$A208,Verification!$I$2:$I$667,"unknown") | G208: =COUNTIF(Verification!$H$2:$H$667,$A208)
A209: Needs raster support | B209: =COUNTIFS(Verification!$H$2:$H$667,$A209,Verification!$I$2:$I$667,3) | C209: =COUNTIFS(Verification!$H$2:$H$667,$A209,Verification!$I$2:$I$667,2) | D209: =COUNTIFS(Verification!$H$2:$H$667,$A209,Verification!$I$2:$I$667,1) | E209: =COUNTIFS(Verification!$H$2:$H$667,$A209,Verification!$I$2:$I$667,0) | F209: =COUNTIFS(Verification!$H$2:$H$667,$A209,Verification!$I$2:$I$667,"unknown") | G209: =COUNTIF(Verification!$H$2:$H$667,$A209)
A210: Not linkable as listed | B210: =COUNTIFS(Verification!$H$2:$H$667,$A210,Verification!$I$2:$I$667,3) | C210: =COUNTIFS(Verification!$H$2:$H$667,$A210,Verification!$I$2:$I$667,2) | D210: =COUNTIFS(Verification!$H$2:$H$667,$A210,Verification!$I$2:$I$667,1) | E210: =COUNTIFS(Verification!$H$2:$H$667,$A210,Verification!$I$2:$I$667,0) | F210: =COUNTIFS(Verification!$H$2:$H$667,$A210,Verification!$I$2:$I$667,"unknown") | G210: =COUNTIF(Verification!$H$2:$H$667,$A210)
A211: Unknown | B211: =COUNTIFS(Verification!$H$2:$H$667,$A211,Verification!$I$2:$I$667,3) | C211: =COUNTIFS(Verification!$H$2:$H$667,$A211,Verification!$I$2:$I$667,2) | D211: =COUNTIFS(Verification!$H$2:$H$667,$A211,Verification!$I$2:$I$667,1) | E211: =COUNTIFS(Verification!$H$2:$H$667,$A211,Verification!$I$2:$I$667,0) | F211: =COUNTIFS(Verification!$H$2:$H$667,$A211,Verification!$I$2:$I$667,"unknown") | G211: =COUNTIF(Verification!$H$2:$H$667,$A211)
A213: Already in gaiaCatalog | B213: Datasets
A214: Kept datasets with a gaiaCatalog folder | B214: =COUNTIF(Verification!$J$2:$J$667,"?*")
A215: …of which Gold or Silver | B215: =COUNTIFS(Verification!$J$2:$J$667,"?*",Verification!$B$2:$B$667,"Gold")+COUNTIFS(Verification!$J$2:$J$667,"?*",Verification!$B$2:$B$667,"Silver")
A216: Public access: registration or restricted | B216: =COUNTIF(Verification!$M$2:$M$667,"registration")+COUNTIF(Verification!$M$2:$M$667,"restricted")
A218: Coverage of assessment | B218: Datasets | C218: Of which Gold/Silver
A219: Read by part B (content checks, 22 or 28 Oct) | B219: 396 | C219: 296
A220: Sent to part B but blocked at the content step | B220: 91 | C220: 10
A221: Not read: browser queue (site blocks scripts or certificate problem) | B221: 61 | C221: 0
A222: Not read: link dead or withdrawn (Failed) | B222: 34 | C222: 0
A223: Not read: no URL | B223: 1 | C223: 0
A224: Checked in a browser by a person (sample, 28 Oct) | B224: 41 | C224: 28
A225: Not read: other | B225: 63 | C225: 21
A226: Total kept | B226: 666
A228: How the list was built (fixed counts) | B228: Rows | C228: Source
A229: Harvested: agent web sweeps + catalog-API listings | B229: 3337 | C229: harvest-2026-10-20-summary.md
A230: After removing duplicates | B230: 3160 | C230: harvest-2026-10-20-dedupe-report.md
A231: Curated rows, or a catalog lead with a stated spatial unit | B231: 1018 | C231: next-pass-2026-10-20-report.md; place-data-inventory-2026-10-21.xlsx
A232: Kept after trimming | B232: 570 | C232: trim-2026-10-22-report.md
A233: Mirrors / successors of withdrawn tools added | B233: 4 | C233: refine-report-2026-10-23.md
A234: Dropped as duplicates (28 Oct) | B234: 0 | C234: dupe-review-2026-10-28.csv
A235: Trimmed after a browser check (28 Oct) | B235: 3 | C235: browser-sample-2026-10-28.md
A236: Read for content (part B, 22 and 28 Oct) | B236: 487 | C236: close-report-2026-10-28.md
A237: Verified (Gold + Silver) | B237: =B21+C21 | C237: Summary, tier totals
A238: Blue numbers are fixed counts from the files named in column C (docs/discovery, 20–28 October 2026).
A240: Round 2 pilot (not in the counts above) | B240: Datasets
A241: Bronze | B241: =COUNTIF('Round 2 pilot'!$B$2:$B$25,A241)
A242: Browser needed | B242: =COUNTIF('Round 2 pilot'!$B$2:$B$25,A242)
A243: Gold / Silver / Failed (part B not run) | B243: =COUNTIF('Round 2 pilot'!$B$2:$B$25,"Gold")+COUNTIF('Round 2 pilot'!$B$2:$B$25,"Silver")+COUNTIF('Round 2 pilot'!$B$2:$B$25,"Failed")
A244: Total new round 2 rows | B244: =SUM(B241:B243)
A245: URL health: healthy | B245: =COUNTIF('Round 2 pilot'!$C$2:$C$25,"healthy")
A246: URL health: degraded | B246: =COUNTIF('Round 2 pilot'!$C$2:$C$25,"degraded")
A247: URL health: blocked | B247: =COUNTIF('Round 2 pilot'!$C$2:$C$25,"blocked")

Sheet About
A1: Place-based data inventory: refined set
A2: Date | B2: 29 October 2026 · OHDSI GIS Working Group · built 20–29 October 2026 (round 1 closed 28 October; on 29 October: working-group requests, the US federal licence rule, geometry classification, and file verification of the request datasets)
A3: What this is | B3: 666 public, place-based datasets that could be linked to where patients live (571 from round 1, then added on 29 October for working-group requests, file verification, category backfill and the priority-sources spike), each with a verification tier; the Round 2 pilot sheet holds 24 more. 345 are verified (Gold or Silver): years, spatial unit and access were read from the publisher's page, with the page URL kept as evidence. 15 are file-verified: a real file was downloaded and its columns, place key, geometry and years read (column verification_level). For US federal datasets the licence pass comes from the working group's rule (US federal works are public domain under 17 U.S.C. 105 unless a page says otherwise); their license_class is public_domain_us_federal.
A4: How it was built | B4: 1 Harvest: AI-assisted web sweeps plus scripted catalog-API listings (data.gov, HDX, Earthdata CMR, EU and national portals): 3,337 listings. 2 De-duplication: 3,160. 3 Split: 594 curated rows kept apart from 2,576 catalog leads; leads whose title names a spatial unit were added: 1,018. 4 Score: health relevance (0–3) and Gaia fit (joins today / needs a count or distance step / needs raster support / not linkable) from each listing. 5 Trim: 570 kept (relevant, data from 2000 on, not a one-off event, not hyper-local, not a portal). 6 URL health (21–22 Oct): scripted checks of every landing and access URL. 7 Content checks (22 and 28 Oct): an agent read the landing page and one documentation page of each live dataset (shortlist and step-3 groups on 22 Oct; the remaining live rows on 28 Oct). 8 Mirrors: four community mirrors or successors of withdrawn federal tools were added. 9 Duplicates (28 Oct): every flagged group among the kept rows was decided (see the Duplicates resolved tab).
A5: What 'verified' means | B5: Each check is pass / warn / fail / n.a. / not checked, with a detail and (for content checks) an evidence URL. Link checks: link live (2xx), redirect (same domain), TLS, soft-404 (page names the dataset), withdrawn (no retirement notice), access URL, format match, machine-readable metadata, persistent id, Wayback snapshot. Content checks: licence (+ class: open / attribution / non-commercial / registration / restricted), years (+ latest year), recency (pass 2020+, warn 2000–2019, fail before 2000 or discontinued), update cadence, version, finest unit, coverage, access route, join key, Gaia-loadable format. Workspace checks: in gaiaCatalog, recipe health from the deployment logs.
A6: Tiers | B6: Gold: link, page, withdrawn, licence, unit, years and access all pass; recency pass or warn. Silver: link passes and no fail among licence, unit, years, recency. Bronze: link live but content not read or incomplete. Browser needed: the site blocks scripts or has a certificate problem; it needs a real browser (a person or a browser agent). Failed: link dead, page generic, publisher says withdrawn, or data before 2000.
A7: Score | B7: 0–100, weighted: link 20, soft-404 10, withdrawn 10, licence 15, unit 15, years 7.5, recency 7.5, access 10, join key 10, machine metadata 5; pass = 1, warn = 0.5, fail = 0; normalised over the checks that apply.
A8: Assumptions | B8: Links were checked automatically on 21–22 October 2026; pages were read on 22 and 28 October, the working-group targets on 29 October, and the request datasets' files opened on 29 October (no other downloads). A 'fail' on licence means no licence statement was found on the pages read, not that the data are restricted; US federal rows pass by rule. A row keyed to one specific geometry dataset that is not yet found is capped at Silver. Relevance and Gaia-fit are rule-based from each listing; geometry classes are partly inferred (column geo_class_basis). Recency cut-off is 2000. Sites that block scripts were not worked around.
A9: Tabs | B9: Summary (live formulas over the Verification tab, plus the coverage of the assessment) · Refined set (Gold and Silver) · Verification (every kept row, colour-coded checks) · Browser queue · Duplicates resolved · Trimmed (what was left out and why) · Round 2 pilot (24 new health-facility registries, link-checked only).
A10: Files | B10: In docs/discovery of the Gaia workspace: inventory-combined-2026-10-29-fv.csv (every column; 604 rows incl. the round 2 pilot), inventory.csv (the Gold and Silver), landscape/landscape-report-2026-10-29.md, fileverify/fileverify-report-2026-10-29.md, exploration-1.5-report-2026-10-29.md, iterations/README.md (how it was built), TODO.md (what's next).
A11: Round 2 pilot | B11: 24 new health-facility registries (sweep 1 of 5; the other sweeps were not run). They were link-checked (part A) but not read for content (part B), so none is above Bronze. They are NOT in the Summary counts above (571 round 1 rows); see the foot of the Summary and the Round 2 pilot sheet. One more candidate (HRSA health-center sites) was already in the inventory and stays a single round 1 row.

Sheet Verification
A1: Dataset | B1: Tier | C1: Score | D1: Theme | E1: URL health | F1: License class | G1: Finest unit | H1: Gaia fit | I1: Health relevance (0-3) | J1: In gaiaCatalog | K1: Source | L1: Latest year | M1: Public access | N1: Verified on | O1: ✓ link live | P1: ✓ redirect | Q1: ✓ tls | R1: ✓ soft404 | S1: ✓ withdrawn | T1: ✓ access url | U1: ✓ format match | V1: ✓ machine metadata | W1: ✓ persistent id | X1: ✓ archived | Y1: ✓ license | Z1: ✓ temporal | AA1: ✓ recency | AB1: ✓ cadence | AC1: ✓ version | AD1: ✓ unit | AE1: ✓ coverage | AF1: ✓ access | AG1: ✓ join key | AH1: ✓ format gaia | AI1: ✓ in gaia | AJ1: ✓ recipe health | AK1: Blockers | AL1: Landing page | AM1: id
A2: Cartografia digitalizada de secciones censales | B2: Gold | C2: 98 | D2: boundaries | E2: healthy | F2: open | G2: polygon (seccion censal; small statistical area) | H2: Joins today | I2: 1 | K2: Curated | L2: 2025 | M2: open | N2: 2026-10-28 | O2: pass | P2: pass | Q2: pass | R2: pass | S2: pass | T2: n.a. | U2: n.a. | V2: warn | W2: warn | X2: pass | Y2: pass | Z2: pass | AA2: pass | AB2: warn | AC2: pass | AD2: pass | AE2: pass | AF2: pass | AG2: pass | AH2: pass | AI2: n.a. | AJ2: n.a. | AK2: machine_metadata(warn);persistent_id(warn);cadence(warn) | AL2: https://www.ine.es/ss/Satellite?L=es_ES&c=Page&cid=1259952026632&p=1259952026632&pagename=ProductosYServicios%2FPYSLayout | AM2: es_ine_secciones_censales
A3: Demografiska statistikomraden (DeSO) | B3: Gold | C3: 98 | D3: boundaries | E3: healthy | F3: open | G3: polygon (DeSO small statistical area; county and municipality as attributes) | H3: Joins today | I3: 1 | K3: Curated | L3: 2025 | M3: open | N3: 2026-10-28 | O3: pass | P3: pass | Q3: pass | R3: pass | S3: pass | T3: pass | U3: pass | V3: warn | W3: warn | X3: pass | Y3: pass | Z3: pass | AA3: pass | AB3: warn | AC3: pass | AD3: pass | AE3: pass | AF3: pass | AG3: pass | AH3: pass | AI3: n.a. | AJ3: n.a. | AK3: machine_metadata(warn);persistent_id(warn);cadence(warn) | AL3: https://www.scb.se/en/services/open-data-api/open-geodata/open-data-for-deso--demographic-statistical-areas/ | AM3: se_scb_deso
A4: Global Administrative Unit Layers (GAUL) | B4: Gold | C4: 93 | D4: boundaries | E4: healthy | F4: open | G4: admin2 | H4: Joins today | I4: 1 | K4: Curated | L4: 2024 | M4: open | N4: 2026-10-28 | O4: pass | P4: pass | Q4: pass | R4: pass | S4: pass | T4: pass | U4: warn | V4: warn | W4: warn | X4: pass | Y4: pass | Z4: pass | AA4: pass | AB4: pass | AC4: pass | AD4: pass | AE4: pass | AF4: pass | AG4: warn | AH4: pass | AI4: n.a. | AJ4: n.a. | AK4: format_match(warn);machine_metadata(warn);persistent_id(warn);join_key(warn) | AL4: https://www.fao.org/hih-geospatial-platform/news/detail/now-available--the-global-administrative-unit-layers-(gaul)-dataset---2024-edition/en | AM4: global_fao_gaul
A5: Postal codes point dataset and postal code to NUTS correspondence (Tercet) | B5: Gold | C5: 98 | D5: boundaries | E5: degraded | F5: open | G5: point | H5: Needs a count/distance step | I5: 1 | K5: Curated | L5: 2024 | M5: open | N5: 2026-10-28 | O5: pass | P5: pass | Q5: pass | R5: pass | S5: pass | T5: fail | U5: n.a. | V5: warn | W5: warn | X5: pass | Y5: pass | Z5: pass | AA5: pass | AB5: warn | AC5: pass | AD5: pass | AE5: pass | AF5: pass | AG5: pass | AH5: pass | AI5: n.a. | AJ5: n.a. | AK5: access_url;machine_metadata(warn);persistent_id(warn);cadence(warn) | AL5: https://ec.europa.eu/eurostat/web/gisco/geodata/administrative-units/postal-codes | AM5: eu_eurostat_gisco_postal_codes
A6: National Walkability Index | B6: Gold | C6: 95 | D6: built_environment | E6: healthy | F6: open | G6: block_group | H6: Joins today | I6: 3 | K6: Curated | L6: 2021 | M6: open | N6: 2026-10-22 | O6: pass | P6: pass | Q6: pass | R6: pass | S6: pass | T6: pass | U6: pass | V6: pass | W6: warn | X6: pass | Y6: pass | Z6: pass | AA6: pass | AB6: not_checked | AC6: warn | AD6: pass | AE6: pass | AF6: pass | AG6: warn | AH6: warn | AI6: n.a. | AJ6: n.a. | AK6: persistent_id(warn);version(warn);join_key(warn);format_gaia(warn) | AL6: https://catalog.data.gov/dataset/walkability-index | AM6: us_epa_national_walkability_index
A7: European Settlement Map (ESM) 2015 R2019 (2 m / 10 m built-up) | B7: Gold | C7: 92 | D7: built_environment | E7: degraded | F7: attribution | G7: grid_2m | H7: Needs raster support | I7: 2 | K7: Curated | L7: 2015 | M7: open | N7: 2026-10-28 | O7: pass | P7: pass | Q7: pass | R7: pass | S7: pass | T7: fail | U7: n.a. | V7: fail | W7: pass | X7: pass | Y7: pass | Z7: pass | AA7: warn | AB7: not_checked | AC7: pass | AD7: pass | AE7: warn | AF7: pass | AG7: pass | AH7: not_checked | AI7: n.a. | AJ7: n.a. | AK7: access_url;machine_metadata;recency(warn);coverage(warn) | AL7: https://human-settlement.emergency.copernicus.eu/datasets.php | AM7: eu_jrc_european_settlement_map
A8: Florida Managed Areas (FLMA) / state and national parks (FNAI GIS data) | B8: Gold | C8: 95 | D8: built_environment | E8: degraded | F8: attribution | G8: polygon | H8: Joins today | I8: 2 | J8: fl_2026_flma;mdc_2026_flma | K8: Curated | L8: 2026 | M8: open | N8: 2026-10-22 | O8: pass | P8: pass | Q8: pass | R8: pass | S8: pass | T8: n.a. | U8: n.a. | V8: fail | W8: warn | X8: pass | Y8: pass | Z8: pass | AA8: pass | AB8: pass | AC8: pass | AD8: pass | AE8: pass | AF8: pass | AG8: pass | AH8: pass | AI8: pass | AJ8: not_checked | AK8: machine_metadata;persistent_id(warn) | AL8: https://www.fnai.org/publications/gis-data | AM8: us_fnai_florida_managed_areas
A9: GHSL GHS-BUILT-S built-up surface grid (R2023A); related GHS-BUILT-V volume, GHS-BUILT-H height, GHS-BUILT-C characteristics, GHS-AGE | B9: Gold | C9: 95 | D9: built_environment | E9: degraded | F9: open | G9: grid_10m | H9: Needs raster support | I9: 2 | K9: Curated | L9: 2030 | M9: open | N9: 2026-10-28 | O9: pass | P9: pass | Q9: pass | R9: pass | S9: pass | T9: pass | U9: warn | V9: fail | W9: pass | X9: pass | Y9: pass | Z9: pass | AA9: pass | AB9: warn | AC9: pass | AD9: pass | AE9: pass | AF9: pass | AG9: pass | AH9: not_checked | AI9: n.a. | AJ9: n.a. | AK9: machine_metadata;format_match(warn);cadence(warn) | AL9: https://human-settlement.emergency.copernicus.eu/datasets.php | AM9: global_jrc_ghsl_ghs_built_s
A10: GHSL GHS-DUC Degree of Urbanisation Classification of administrative units (GADM 4.1), R2023A; GHS-WUP-DUC R2025A | B10: Gold | C10: 91 | D10: built_environment | E10: degraded | F10: open | G10: GADM 4.1 administrative units, levels 0-5 (GHS-DUC); grid_1km (GHS-WUP-DUC) | H10: Needs raster support | I10: 2 | K10: Curated | L10: 2030 | M10: open | N10: 2026-10-28 | O10: pass | P10: pass | Q10: pass | R10: pass | S10: pass | T10: pass | U10: warn | V10: fail | W10: pass | X10: pass | Y10: pass | Z10: pass | AA10: pass | AB10: warn | AC10: pass | AD10: pass | AE10: pass | AF10: pass | AG10: warn | AH10: not_checked | AI10: n.a. | AJ10: n.a. | AK10: machine_metadata;format_match(warn);cadence(warn);join_key(warn) | AL10: https://human-settlement.emergency.copernicus.eu/datasets.php | AM10: global_jrc_ghsl_ghs_duc
A11: GHSL GHS-SMOD Degree of Urbanisation settlement model grid (R2023A) and GHS-WUP-DEGURBA (R2025A) | B11: Gold | C11: 95 | D11: built_environment | E11: degraded | F11: open | G11: grid_1km | H11: Needs raster support | I11: 2 | K11: Curated | L11: 2030 | M11: open | N11: 2026-10-28 | O11: pass | P11: pass | Q11: pass | R11: pass | S11: pass | T11: pass | U11: warn | V11: fail | W11: pass | X11: pass | Y11: pass | Z11: pass | AA11: pass | AB11: warn | AC11: pass | AD11: pass | AE11: pass | AF11: pass | AG11: pass | AH11: not_checked | AI11: n.a. | AJ11: n.a. | AK11: machine_metadata;format_match(warn);cadence(warn) | AL11: https://human-settlement.emergency.copernicus.eu/datasets.php | AM11: global_jrc_ghsl_ghs_smod
A12: Microsoft GlobalMLBuildingFootprints: worldwide building footprints derived from satellite imagery (with height estimates) | B12: Gold | C12: 98 | D12: built_environment | E12: degraded | F12: open | G12: polygon | H12: Joins today | I12: 2 | K12: Curated | L12: 2026 | M12: open | N12: 2026-10-22 | O12: pass | P12: pass | Q12: pass | R12: pass | S12: pass | T12: fail | U12: n.a. | V12: warn | W12: warn | X12: pass | Y12: pass | Z12: pass | AA12: pass | AB12: warn | AC12: warn | AD12: pass | AE12: pass | AF12: pass | AG12: pass | AH12: pass | AI12: n.a. | AJ12: n.a. | AK12: access_url;machine_metadata(warn);persistent_id(warn);cadence(warn);version(warn) | AL12: https://github.com/microsoft/GlobalMLBuildingFootprints | AM12: global_microsoft_building_footprints
A13: Open Buildings | B13: Gold | C13: 98 | D13: built_environment | E13: healthy | F13: open | G13: polygon (v3 footprints); grid_4m effective resolution, rasters provided at 50 cm (Temporal) | H13: Needs raster support | I13: 2 | K13: Curated | L13: 2023 | M13: open | N13: 2026-10-28 | O13: pass | P13: pass | Q13: pass | R13: pass | S13: pass | T13: pass | U13: warn | V13: warn | W13: warn | X13: pass | Y13: pass | Z13: pass | AA13: pass | AB13: warn | AC13: pass | AD13: pass | AE13: pass | AF13: pass | AG13: pass | AH13: pass | AI13: n.a. | AJ13: n.a. | AK13: format_match(warn);machine_metadata(warn);persistent_id(warn);cadence(warn) | AL13: https://sites.research.google/gr/open-buildings/ | AM13: global_google_open_buildings
A14: World Settlement Footprint (WSF) 2019; related WSF 2015, WSF Evolution (1985-2015), WSF 3D | B14: Gold | C14: 92 | D14: built_environment | E14: degraded | F14: open | G14: grid_10m | H14: Needs raster support | I14: 2 | K14: Curated | L14: 2019 | M14: open | N14: 2026-10-28 | O14: pass | P14: pass | Q14: pass | R14: pass | S14: pass | T14: fail | U14: n.a. | V14: fail | W14: pass | X14: pass | Y14: pass | Z14: pass | AA14: warn | AB14: not_checked | AC14: warn | AD14: pass | AE14: pass | AF14: pass | AG14: pass | AH14: pass | AI14: n.a. | AJ14: n.a. | AK14: access_url;machine_metadata;recency(warn);version(warn) | AL14: https://geoservice.dlr.de/web/datasets/wsf_2019 | AM14: global_dlr_wsf_2019
A15: gridMET (METDATA) | B15: Gold | C15: 98 | D15: climate_hazard | E15: healthy | F15: open | G15: grid_4km | H15: Needs raster support | I15: 3 | K15: Curated | L15: 2026 | M15: open | N15: 2026-10-22 | O15: pass | P15: pass | Q15: pass | R15: pass | S15: pass | T15: pass | U15: warn | V15: warn | W15: warn | X15: pass | Y15: pass | Z15: pass | AA15: pass | AB15: pass | AC15: warn | AD15: pass | AE15: pass | AF15: pass | AG15: pass | AH15: pass | AI15: n.a. | AJ15: n.a. | AK15: format_match(warn);machine_metadata(warn);persistent_id(warn);version(warn) | AL15: https://www.climatologylab.org/gridmet.html | AM15: us_climatologylab_gridmet
A16: Wildfire Risk to Communities | B16: Gold | C16: 93 | D16: climate_hazard | E16: healthy | F16: open | G16: grid_30m | H16: Needs raster support | I16: 2 | K16: Curated | L16: 2024 | M16: open | N16: 2026-10-28 | O16: pass | P16: pass | Q16: pass | R16: pass | S16: pass | T16: pass | U16: pass | V16: warn | W16: pass | X16: pass | Y16: pass | Z16: pass | AA16: pass | AB16: warn | AC16: pass | AD16: pass | AE16: pass | AF16: pass | AG16: warn | AH16: warn | AI16: n.a. | AJ16: n.a. | AK16: machine_metadata(warn);cadence(warn);join_key(warn);format_gaia(warn) | AL16: https://wildfirerisk.org/download/ | AM16: us_usfs_wildfire_risk_to_communities
A17: Zensus 2022 Gitterdaten (grid data 100 m / 1 km / 10 km) | B17: Gold | C17: 93 | D17: demographics | E17: healthy | F17: attribution | G17: grid_100m | H17: Needs raster support | I17: 3 | K17: Curated | L17: 2022 | M17: open | N17: 2026-10-22 | O17: pass | P17: pass | Q17: pass | R17: pass | S17: pass | T17: pass | U17: warn | V17: warn | W17: warn | X17: pass | Y17: pass | Z17: pass | AA17: pass | AB17: pass | AC17: not_checked | AD17: pass | AE17: pass | AF17: pass | AG17: warn | AH17: pass | AI17: n.a. | AJ17: n.a. | AK17: format_match(warn);machine_metadata(warn);persistent_id(warn);join_key(warn) | AL17: https://www.destatis.de/zensus2022 | AM17: de_destatis_zensus2022_grid
A18: American Community Survey 5-Year Data | B18: Gold | C18: 93 | D18: demographics | E18: healthy | F18: attribution | G18: block_group | H18: Joins today | I18: 2 | J18: fl_2021_acs_5yr_tract_fsr;mdc_2019_acs_5yr_tract_dvmt;mdc_2020_2024_acs_5yr_trends_tract_dvmt;mdc_2020_acs_5yr_tract_dvmt;mdc_2021_acs_5yr_tract_dvmt;mdc_2022_acs_5yr_tract_dvmt;mdc_2023_acs_5yr_tract_dvmt;mdc_2024_acs_5yr_tract_dvmt | K18: Curated | L18: 2024 | M18: unknown | N18: 2026-10-22 | O18: pass | P18: pass | Q18: pass | R18: pass | S18: pass | T18: pass | U18: pass | V18: warn | W18: warn | X18: pass | Y18: pass | Z18: pass | AA18: pass | AB18: pass | AC18: pass | AD18: pass | AE18: pass | AF18: pass | AG18: warn | AH18: warn | AI18: pass | AJ18: not_checked | AK18: machine_metadata(warn);persistent_id(warn);join_key(warn);format_gaia(warn) | AL18: https://www.census.gov/data/developers/data-sets/acs-5year.html | AM18: us_census_acs_5year
A19: Censo de Poblacion y Vivienda (Censo 2017; Censo 2024) | B19: Gold | C19: 98 | D19: demographics | E19: healthy | F19: open | G19: block (manzana) | H19: Joins today | I19: 2 | K19: Curated | L19: 2024 | M19: unknown | N19: 2026-10-22 | O19: pass | P19: pass | Q19: pass | R19: pass | S19: pass | T19: pass | U19: warn | V19: warn | W19: warn | X19: pass | Y19: pass | Z19: pass | AA19: pass | AB19: warn | AC19: pass | AD19: pass | AE19: warn | AF19: pass | AG19: not_checked | AH19: warn | AI19: n.a. | AJ19: n.a. | AK19: format_match(warn);machine_metadata(warn);persistent_id(warn);cadence(warn);coverage(warn);format_gaia(warn) | AL19: https://www.ine.gob.cl/estadisticas/sociales/censos-de-poblacion-y-vivienda/censo-de-poblacion-y-vivienda | AM19: cl_ine_censo
A20: Kaart van 100 meter bij 100 meter met statistieken | B20: Gold | C20: 98 | D20: demographics | E20: healthy | F20: attribution | G20: grid_100m | H20: Needs raster support | I20: 2 | K20: Curated | L20: 2025 | M20: open | N20: 2026-10-28 | O20: pass | P20: pass | Q20: pass | R20: pass | S20: pass | T20: n.a. | U20: n.a. | V20: warn | W20: warn | X20: pass | Y20: pass | Z20: pass | AA20: pass | AB20: pass | AC20: pass | AD20: pass | AE20: pass | AF20: pass | AG20: pass | AH20: pass | AI20: n.a. | AJ20: n.a. | AK20: machine_metadata(warn);persistent_id(warn) | AL20: https://www.cbs.nl/nl-nl/dossier/nederland-regionaal/geografische-data/kaart-van-100-meter-bij-100-meter-met-statistieken | AM20: nl_cbs_100m_grid
A21: Recensement de la population - Base infracommunale (IRIS) | B21: Gold | C21: 95 | D21: demographics | E21: degraded | F21: open | G21: IRIS (small statistical area, ~2000 inhabitants; commune level where commune not split into IRIS) | H21: Joins today | I21: 2 | K21: Curated | L21: 2023 | M21: open | N21: 2026-10-22 | O21: pass | P21: pass | Q21: pass | R21: pass | S21: pass | T21: warn | U21: n.a. | V21: fail | W21: warn | X21: pass | Y21: pass | Z21: pass | AA21: pass | AB21: not_checked | AC21: pass | AD21: pass | AE21: pass | AF21: pass | AG21: pass | AH21: pass | AI21: n.a. | AJ21: n.a. | AK21: machine_metadata;access_url(warn);persistent_id(warn) | AL21: https://www.insee.fr/fr/statistiques/9061333 | AM21: fr_insee_iris_rp
A22: 3D Hydrography Program (3DHP) hydrography data (successor to the NHD) | B22: Gold | C22: 98 | D22: environment | E22: healthy | F22: open | G22: line | H22: Needs a count/distance step | I22: 3 | K22: Mirror | L22: 2026 | M22: open | N22: 2026-10-28 | O22: pass | P22: pass | Q22: pass | R22: pass | S22: pass | T22: pass | U22: warn | V22: warn | W22: warn | X22: pass | Y22: pass | Z22: pass | AA22: pass | AB22: pass | AC22: warn | AD22: pass | AE22: pass | AF22: pass | AG22: pass | AH22: warn | AI22: n.a. | AJ22: n.a. | AK22: format_match(warn);machine_metadata(warn);persistent_id(warn);version(warn);format_gaia(warn) | AL22: https://www.usgs.gov/3d-hydrography-program | AM22: us_usgs_3dhp
A23: Air Quality e-Reporting (Air Quality download service) | B23: Gold | C23: 91 | D23: environment | E23: degraded | F23: attribution | G23: point | H23: Needs a count/distance step | I23: 3 | K23: Curated | L23: 2026 | M23: open | N23: 2026-10-22 | O23: pass | P23: pass | Q23: pass | R23: pass | S23: pass | T23: pass | U23: pass | V23: fail | W23: warn | X23: pass | Y23: pass | Z23: pass | AA23: pass | AB23: not_checked | AC23: warn | AD23: pass | AE23: warn | AF23: pass | AG23: warn | AH23: warn | AI23: n.a. | AJ23: n.a. | AK23: machine_metadata;persistent_id(warn);version(warn);coverage(warn);join_key(warn);format_gaia(warn) | AL23: https://www.eea.europa.eu/en/datahub/datahubitem-view/778ef9f5-6293-4846-badd-56a29c70880d | AM23: eu_eea_air_quality_ereporting
A24: ChinaHighAirPollutants (CHAP) | B24: Gold | C24: 91 | D24: environment | E24: degraded | F24: open | G24: grid_1km | H24: Needs raster support | I24: 3 | K24: Curated | L24: 2026 | M24: open | N24: 2026-10-22 | O24: pass | P24: pass | Q24: pass | R24: pass | S24: pass | T24: pass | U24: warn | V24: fail | W24: pass | X24: pass | Y24: pass | Z24: pass | AA24: pass | AB24: warn | AC24: pass | AD24: pass | AE24: pass | AF24: pass | AG24: warn | AH24: pass | AI24: n.a. | AJ24: n.a. | AK24: machine_metadata;format_match(warn);cadence(warn);join_key(warn) | AL24: https://weijing-rs.github.io/product.html | AM24: cn_wei_chap
A25: Daily Census Tract-Level PM2.5 Concentrations (2001-2005; 2006-2010; 2011-2015; 2016) | B25: Gold | C25: 92 | D25: environment | E25: healthy | F25: open | G25: tract | H25: Joins today | I25: 3 | J25: us_2014_2019_monthly_pm25_by_tract_cdc | K25: Curated | L25: 2015 | M25: open | N25: 2026-10-22 | O25: pass | P25: pass | Q25: pass | R25: pass | S25: pass | T25: pass | U25: warn | V25: pass | W25: warn | X25: pass | Y25: pass | Z25: pass | AA25: warn | AB25: not_checked | AC25: warn | AD25: pass | AE25: not_checked | AF25: pass | AG25: warn | AH25: warn | AI25: pass | AJ25: not_checked | AK25: format_match(warn);persistent_id(warn);recency(warn);version(warn);join_key(warn);format_gaia(warn) | AL25: https://catalog.data.gov/dataset/daily-census-tract-level-pm2-5-concentrations-2011-2015 | AM25: us_cdc_daily_tract_pm25
A26: ESA CCI Soil Moisture (active, passive, combined) v09.2 | B26: Gold | C26: 98 | D26: environment | E26: degraded | F26: attribution | G26: grid_0.25deg | H26: Needs raster support | I26: 3 | K26: Curated | L26: 2024 | M26: open | N26: 2026-10-22 | O26: pass | P26: pass | Q26: pass | R26: pass | S26: pass | T26: fail | U26: n.a. | V26: warn | W26: pass | X26: pass | Y26: pass | Z26: pass | AA26: pass | AB26: pass | AC26: pass | AD26: pass | AE26: pass | AF26: pass | AG26: pass | AH26: pass | AI26: n.a. | AJ26: n.a. | AK26: access_url;machine_metadata(warn) | AL26: https://climate.esa.int/en/projects/soil-moisture/ | AM26: global_esa_cci_soil_moisture
A27: ESA Climate Change Initiative Land Cover (CCI-LC) annual global maps 300 m, 1992-2020 (v2.0.7, v2.1.1) and C3S continuation | B27: Gold | C27: 98 | D27: environment | E27: degraded | F27: attribution | G27: grid_300m | H27: Needs raster support | I27: 3 | K27: Curated | L27: 2020 | M27: open | N27: 2026-10-22 | O27: pass | P27: pass | Q27: pass | R27: pass | S27: pass | T27: fail | U27: n.a. | V27: warn | W27: pass | X27: pass | Y27: pass | Z27: pass | AA27: pass | AB27: warn | AC27: pass | AD27: pass | AE27: pass | AF27: pass | AG27: pass | AH27: not_checked | AI27: n.a. | AJ27: n.a. | AK27: access_url;machine_metadata(warn);cadence(warn) | AL27: https://climate.esa.int/en/projects/land-cover/ | AM27: global_esa_cci_land_cover
A28: SatPM2.5 (Satellite-derived PM2.5) global estimates V6.GL.02.04 and V5.GL.05.02 | B28: Gold | C28: 95 | D28: environment | E28: degraded | F28: open | G28: grid_0.01deg | H28: Needs raster support | I28: 3 | K28: Curated | L28: 2023 | M28: open | N28: 2026-10-22 | O28: pass | P28: pass | Q28: pass | R28: pass | S28: pass | T28: pass | U28: warn | V28: fail | W28: pass | X28: pass | Y28: pass | Z28: pass | AA28: pass | AB28: warn | AC28: pass | AD28: pass | AE28: pass | AF28: pass | AG28: pass | AH28: pass | AI28: n.a. | AJ28: n.a. | AK28: machine_metadata;format_match(warn);cadence(warn) | AL28: https://sites.wustl.edu/acag/datasets/surface-pm2-5/ | AM28: global_acag_pm25
A29: Health facilities in Thailand 2020 | B29: Gold | C29: 100 | D29: health_outcome | E29: healthy | F29: attribution | G29: point | H29: Needs a count/distance step | I29: 3 | K29: Catalog lead | L29: 2020 | M29: open | N29: 2026-10-22 | O29: pass | P29: pass | Q29: pass | R29: pass | S29: pass | T29: pass | U29: pass | V29: pass | W29: warn | X29: fail | Y29: pass | Z29: pass | AA29: pass | AB29: not_checked | AC29: warn | AD29: pass | AE29: fail | AF29: pass | AG29: pass | AH29: pass | AI29: n.a. | AJ29: n.a. | AK29: archived;coverage;persistent_id(warn);version(warn) | AL29: https://data.opendevelopmentmekong.net/dataset/health-facilities-in-thailand-2020 | AM29: mekong_odm_health_facilities_in_thailand_2020
A30: U.S. Small-area Life Expectancy Estimates Project (USALEEP) | B30: Gold | C30: 94 | D30: health_outcome | E30: healthy | F30: open | G30: tract | H30: Joins today | I30: 3 | K30: Curated | L30: 2015 | M30: unknown | N30: 2026-10-22 | O30: pass | P30: pass | Q30: pass | R30: pass | S30: pass | T30: pass | U30: warn | V30: warn | W30: warn | X30: pass | Y30: pass | Z30: pass | AA30: warn | AB30: warn | AC30: warn | AD30: pass | AE30: warn | AF30: pass | AG30: pass | AH30: pass | AI30: n.a. | AJ30: n.a. | AK30: format_match(warn);machine_metadata(warn);persistent_id(warn);recency(warn);cadence(warn);version(warn);coverage(warn) | AL30: https://www.cdc.gov/nchs/nvss/usaleep/usaleep.html | AM30: us_cdc_usaleep
A31: Rural Urban Classification | B31: Gold | C31: 93 | D31: other | E31: healthy | F31: open | G31: output_area (OA; 188,880 OAs of c. 100-625 people) | H31: Joins today | I31: 2 | K31: Curated | L31: 2021 | M31: open | N31: 2026-10-22 | O31: pass | P31: pass | Q31: pass | R31: pass | S31: pass | T31: pass | U31: warn | V31: warn | W31: warn | X31: pass | Y31: pass | Z31: pass | AA31: pass | AB31: warn | AC31: pass | AD31: pass | AE31: fail | AF31: pass | AG31: warn | AH31: warn | AI31: n.a. | AJ31: n.a. | AK31: coverage;format_match(warn);machine_metadata(warn);persistent_id(warn);cadence(warn);join_key(warn);format_gaia(warn) | AL31: https://www.gov.uk/government/collections/rural-urban-classification | AM31: gb_defra_ons_rural_urban_classification
A32: Area Health Resources Files (AHRF) | B32: Gold | C32: 91 | D32: sdoh | E32: degraded | F32: open | G32: county | H32: Joins today | I32: 3 | K32: Curated | L32: 2025 | M32: open | N32: 2026-10-22 | O32: pass | P32: pass | Q32: pass | R32: pass | S32: pass | T32: pass | U32: warn | V32: fail | W32: warn | X32: pass | Y32: pass | Z32: pass | AA32: pass | AB32: pass | AC32: pass | AD32: pass | AE32: pass | AF32: pass | AG32: warn | AH32: pass | AI32: n.a. | AJ32: n.a. | AK32: machine_metadata;format_match(warn);persistent_id(warn);join_key(warn) | AL32: https://data.hrsa.gov/topics/health-workforce/ahrf | AM32: us_hrsa_ahrf
A33: Comprehensive Housing Affordability Strategy (CHAS) data | B33: Gold | C33: 92 | D33: sdoh | E33: healthy | F33: unknown | G33: block group (091), tract (080) | H33: Joins today | I33: 3 | K33: Curated | L33: 2022 | M33: open | N33: 2026-10-28 | O33: pass | P33: pass | Q33: pass | R33: pass | S33: pass | T33: pass | U33: pass | V33: not_checked | W33: not_checked | X33: pass | Y33: warn | Z33: pass | AA33: pass | AB33: not_checked | AC33: not_checked | AD33: pass | AE33: not_checked | AF33: pass | AG33: not_checked | AH33: pass | AI33: n.a. | AJ33: n.a. | AK33: license(warn) | AL33: https://www.huduser.gov/portal/datasets/cp.html | AM33: us_hud_chas
A34: NATA / AirToxScreen replication dataset 1996-2019 (tract and county risk tables) | B34: Gold | C34: 95 | D34: toxics | E34: healthy | F34: open | G34: tract | H34: Joins today | I34: 3 | K34: Curated | L34: 2020 | M34: open | N34: 2026-10-22 | O34: pass | P34: pass | Q34: pass | R34: pass | S34: pass | T34: pass | U34: n.a. | V34: pass | W34: pass | X34: fail | Y34: pass | Z34: pass | AA34: pass | AB34: warn | AC34: pass | AD34: pass | AE34: warn | AF34: pass | AG34: warn | AH34: warn | AI34: n.a. | AJ34: n.a. | AK34: archived;cadence(warn);coverage(warn);join_key(warn);format_gaia(warn) | AL34: https://zenodo-rdm.web.cern.ch/records/17187663 | AM34: us_zenodo_nata_replication_1996_2019
A35: 2021 Census Boundary Files | B35: Silver | C35: 93 | D35: boundaries | E35: healthy | F35: open | G35: block | H35: Joins today | I35: 1 | K35: Curated | L35: 2021 | M35: open | N35: 2026-10-28 | O35: pass | P35: pass | Q35: pass | R35: pass | S35: pass | T35: warn | U35: n.a. | V35: pass | W35: warn | X35: fail | Y35: pass | Z35: pass | AA35: pass | AB35: pass | AC35: warn | AD35: warn | AE35: warn | AF35: pass | AG35: pass | AH35: pass | AI35: n.a. | AJ35: n.a. | AK35: archived;access_url(warn);persistent_id(warn);version(warn);unit(warn);coverage(warn) | AL35: https://open.canada.ca/data/dataset/ef70dc3b-1069-4037-9bce-61f47e628a1d | AM35: ca_statcan_census_boundary_files_2021
A36: Australian Statistical Geography Standard (ASGS) Edition 3 digital boundary files | B36: Silver | C36: 91 | D36: boundaries | E36: healthy | F36: open | G36: block | H36: Joins today | I36: 1 | K36: Curated | L36: 2025 | M36: open | N36: 2026-10-28 | O36: pass | P36: pass | Q36: pass | R36: pass | S36: pass | T36: n.a. | U36: n.a. | V36: warn | W36: warn | X36: pass | Y36: pass | Z36: pass | AA36: pass | AB36: pass | AC36: pass | AD36: warn | AE36: pass | AF36: pass | AG36: pass | AH36: pass | AI36: n.a. | AJ36: n.a. | AK36: machine_metadata(warn);persistent_id(warn);unit(warn) | AL36: https://www.abs.gov.au/statistics/standards/australian-statistical-geography-standard-asgs-edition-3/jul2021-jun2026/access-and-downloads/digital-boundary-files | AM36: au_abs_asgs_boundaries
A37: Boundary-Line | B37: Silver | C37: 92 | D37: boundaries | E37: healthy | F37: unknown | G37: postcode_small_area | H37: Joins today | I37: 1 | K37: Curated | L37: 2026 | M37: open | N37: 2026-10-28 | O37: pass | P37: pass | Q37: pass | R37: pass | S37: pass | T37: pass | U37: warn | V37: warn | W37: warn | X37: pass | Y37: not_checked | Z37: warn | AA37: pass | AB37: pass | AC37: not_checked | AD37: not_checked | AE37: pass | AF37: pass | AG37: pass | AH37: pass | AI37: n.a. | AJ37: n.a. | AK37: format_match(warn);machine_metadata(warn);persistent_id(warn);temporal(warn) | AL37: https://www.ordnancesurvey.co.uk/products/boundary-line | AM37: gb_os_boundary_line
... A40: GeoNames geographical database | B40: Silver | C40: 92 | D40: boundaries | E40: degraded | F40: open | G40: point | H40: Needs a count/distance step | I40: 1 | K40: Curated | L40: 2026 | M40: open | N40: 2026-10-28 | O40: pass | P40: pass | Q40: pass | R40: pass | S40: pass | T40: pass | U40: pass | V40: fail | W40: warn | X40: pass | Y40: pass | Z40: warn | AA40: pass | AB40: pass | AC40: not_checked | AD40: pass | AE40: pass | AF40: pass | AG40: pass | AH40: pass | AI40: n.a. | AJ40: n.a. | AK40: machine_metadata;persistent_id(warn);temporal(warn) | AL40: https://www.geonames.org/export/ | AM40: global_geonames
A41: GeoNames postal codes | B41: Silver | C41: 95 | D41: boundaries | E41: degraded | F41: open | G41: point | H41: Needs a count/distance step | I41: 1 | K41: Curated | L41: current | M41: open | N41: 2026-10-28 | O41: pass | P41: pass | Q41: pass | R41: pass | S41: pass | T41: pass | U41: warn | V41: fail | W41: warn | X41: pass | Y41: pass | Z41: not_checked | AA41: not_checked | AB41: warn | AC41: not_checked | AD41: pass | AE41: pass | AF41: pass | AG41: pass | AH41: pass | AI41: n.a. | AJ41: n.a. | AK41: machine_metadata;format_match(warn);persistent_id(warn);cadence(warn) | AL41: https://www.geonames.org/export/ | AM41: global_geonames_postal_codes
A42: Local administrative units (LAU) - GISCO geodata | B42: Silver | C42: 84 | D42: boundaries | E42: healthy | F42: non-commercial | G42: admin3 | H42: Joins today | I42: 1 | K42: Curated | L42: 2024 | M42: open | N42: 2026-10-28 | O42: pass | P42: pass | Q42: pass | R42: pass | S42: pass | T42: pass | U42: warn | V42: warn | W42: warn | X42: pass | Y42: warn | Z42: pass | AA42: pass | AB42: pass | AC42: warn | AD42: warn | AE42: not_checked | AF42: pass | AG42: pass | AH42: pass | AI42: n.a. | AJ42: n.a. | AK42: format_match(warn);machine_metadata(warn);persistent_id(warn);license(warn);version(warn);unit(warn) | AL42: https://ec.europa.eu/eurostat/web/gisco/geodata/statistical-units/local-administrative-units | AM42: eu_eurostat_gisco_lau
A43: OpenAddresses | B43: Silver | C43: 97 | D43: boundaries | E43: healthy | F43: attribution | G43: address | H43: Needs a count/distance step | I43: 1 | K43: Curated | M43: open | N43: 2026-10-28 | O43: pass | P43: pass | Q43: pass | R43: pass | S43: pass | T43: pass | U43: warn | V43: warn | W43: warn | X43: pass | Y43: pass | Z43: not_checked | AA43: not_checked | AB43: not_checked | AC43: not_checked | AD43: pass | AE43: pass | AF43: not_checked | AG43: pass | AH43: not_checked | AI43: n.a. | AJ43: n.a. | AK43: format_match(warn);machine_metadata(warn);persistent_id(warn) | AL43: https://openaddresses.io/ | AM43: global_openaddresses
A44: Radios censales (cartografia censal) - Censo 2022 / 2010 | B44: Silver | C44: 89 | D44: boundaries | E44: degraded | F44: open | G44: polygon (radio censal, census enumeration area) | H44: Joins today | I44: 1 | K44: Curated | L44: 2022 | M44: open | N44: 2026-10-28 | O44: pass | P44: pass | Q44: pass | R44: pass | S44: pass | T44: pass | U44: warn | V44: fail | W44: warn | X44: pass | Y44: pass | Z44: pass | AA44: pass | AB44: pass | AC44: pass | AD44: warn | AE44: warn | AF44: pass | AG44: pass | AH44: pass | AI44: n.a. | AJ44: n.a. | AK44: machine_metadata;format_match(warn);persistent_id(warn);unit(warn);coverage(warn) | AL44: https://www.indec.gob.ar/indec/web/Institucional-Indec-Codgeo | AM44: ar_indec_radios_censales
A45: Second Administrative Level Boundaries (SALB) | B45: Silver | C45: 71 | D45: boundaries | E45: degraded | F45: unknown | G45: admin2 | H45: Unknown | I45: 1 | K45: Curated | M45: unknown | N45: 2026-10-28 | O45: pass | P45: pass | Q45: pass | R45: pass | S45: pass | T45: n.a. | U45: n.a. | V45: fail | W45: warn | X45: pass | Y45: warn | Z45: not_checked | AA45: not_checked | AB45: not_checked | AC45: not_checked | AD45: warn | AE45: warn | AF45: warn | AG45: not_checked | AH45: warn | AI45: n.a. | AJ45: n.a. | AK45: machine_metadata;persistent_id(warn);license(warn);unit(warn);coverage(warn);access(warn);format_gaia(warn) | AL45: https://salb.un.org/en | AM45: global_un_salb
A46: Stats NZ Geographic Data Service (boundaries) | B46: Silver | C46: 81 | D46: boundaries | E46: degraded | F46: open | G46: polygon (SA2; plus grid_250m population grid); meshblock/SA1 layers not seen | H46: Joins today | I46: 1 | K46: Curated | L46: 2026 | M46: unknown | N46: 2026-10-28 | O46: pass | P46: pass | Q46: pass | R46: pass | S46: pass | T46: pass | U46: pass | V46: fail | W46: warn | X46: pass | Y46: pass | Z46: warn | AA46: pass | AB46: pass | AC46: pass | AD46: warn | AE46: pass | AF46: warn | AG46: pass | AH46: warn | AI46: n.a. | AJ46: n.a. | AK46: machine_metadata;persistent_id(warn);temporal(warn);unit(warn);access(warn);format_gaia(warn) | AL46: https://datafinder.stats.govt.nz/ | AM46: nz_statsnz_geographic_data_service
A47: Tanzania 2022 Population and Housing Census boundaries (regions, districts; Magu District) | B47: Silver | C47: 74 | D47: boundaries | E47: degraded | F47: registration | G47: admin2 (region and district confirmed; ward, village/mtaa and EA levels described as planned in text carried over from the 2012 release) | H47: Unknown | I47: 1 | J47: tz_2022_nbs;tz_2022_nbs_magu_district | K47: Curated | L47: 2022 | M47: unknown | N47: 2026-10-28 | O47: pass | P47: pass | Q47: pass | R47: pass | S47: pass | T47: n.a. | U47: n.a. | V47: fail | W47: warn | X47: fail | Y47: warn | Z47: warn | AA47: pass | AB47: not_checked | AC47: warn | AD47: warn | AE47: pass | AF47: warn | AG47: pass | AH47: warn | AI47: pass | AJ47: not_checked | AK47: machine_metadata;archived;persistent_id(warn);license(warn);temporal(warn);version(warn);unit(warn);access(warn);format_gaia(warn) | AL47: https://microdata.nbs.go.tz/index.php/catalog/49/related-materials | AM47: tz_nbs_2022_census_boundaries
A48: Who's On First | B48: Silver | C48: 87 | D48: boundaries | E48: degraded | F48: attribution | G48: point | H48: Joins today | I48: 1 | K48: Curated | M48: open | N48: 2026-10-28 | O48: pass | P48: pass | Q48: pass | R48: pass | S48: pass | T48: pass | U48: warn | V48: fail | W48: warn | X48: pass | Y48: pass | Z48: not_checked | AA48: not_checked | AB48: not_checked | AC48: not_checked | AD48: warn | AE48: pass | AF48: pass | AG48: pass | AH48: pass | AI48: n.a. | AJ48: n.a. | AK48: machine_metadata;format_match(warn);persistent_id(warn);unit(warn) | AL48: https://whosonfirst.org/ | AM48: global_whos_on_first
A49: Overture Maps Foundation data releases | B49: Silver | C49: 93 | D49: built_environment | E49: healthy | F49: open | G49: point | H49: Needs a count/distance step | I49: 3 | K49: Curated | L49: 2026 | M49: open | N49: 2026-10-22 | O49: pass | P49: pass | Q49: pass | R49: pass | S49: pass | T49: pass | U49: warn | V49: warn | W49: warn | X49: pass | Y49: pass | Z49: warn | AA49: pass | AB49: not_checked | AC49: warn | AD49: not_checked | AE49: not_checked | AF49: pass | AG49: pass | AH49: pass | AI49: n.a. | AJ49: n.a. | AK49: format_match(warn);machine_metadata(warn);persistent_id(warn);temporal(warn);version(warn) | AL49: https://docs.overturemaps.org/getting-data/ | AM49: global_overture_maps
A50: Smart Location Database (SLD) | B50: Silver | C50: 96 | D50: built_environment | E50: healthy | F50: open | G50: block_group | H50: Joins today | I50: 3 | K50: Curated | L50: 2021 | M50: open | N50: 2026-10-22 | O50: pass | P50: pass | Q50: pass | R50: pass | S50: pass | T50: pass | U50: pass | V50: pass | W50: warn | X50: pass | Y50: pass | Z50: warn | AA50: pass | AB50: not_checked | AC50: pass | AD50: pass | AE50: pass | AF50: pass | AG50: not_checked | AH50: warn | AI50: n.a. | AJ50: n.a. | AK50: persistent_id(warn);temporal(warn);format_gaia(warn) | AL50: https://catalog.data.gov/dataset/smart-location-database | AM50: us_epa_smart_location_database
A51: Annual National Land Cover Database (Annual NLCD) | B51: Silver | C51: 89 | D51: built_environment | E51: degraded | F51: open | G51: grid_30m | H51: Needs raster support | I51: 2 | J51: mdc_2021_nlcd_impervious_surfaces;mdc_2021_nlcd_land_cover | K51: Curated | L51: 2025 | M51: open | N51: 2026-10-28 | O51: pass | P51: pass | Q51: pass | R51: pass | S51: pass | T51: pass | U51: pass | V51: fail | W51: warn | X51: pass | Y51: pass | Z51: pass | AA51: pass | AB51: warn | AC51: pass | AD51: not_checked | AE51: pass | AF51: pass | AG51: warn | AH51: warn | AI51: pass | AJ51: not_checked | AK51: machine_metadata;persistent_id(warn);cadence(warn);join_key(warn);format_gaia(warn) | AL51: https://www.mrlc.gov/data | AM51: us_usgs_nlcd_annual
A52: Derived map of global electricity transmission and distribution lines (Global Electrification Database) | B52: Silver | C52: 92 | D52: built_environment | E52: healthy | F52: open | G52: line | H52: Needs raster support | I52: 2 | K52: Curated | M52: open | N52: 2026-10-28 | O52: pass | P52: pass | Q52: pass | R52: pass | S52: pass | T52: n.a. | U52: n.a. | V52: pass | W52: warn | X52: fail | Y52: pass | Z52: not_checked | AA52: not_checked | AB52: not_checked | AC52: warn | AD52: warn | AE52: pass | AF52: pass | AG52: pass | AH52: pass | AI52: n.a. | AJ52: n.a. | AK52: archived;persistent_id(warn);version(warn);unit(warn) | AL52: https://datacatalog.worldbank.org/search/dataset/0038055/Global-Electrification-Database-from-Tracking-SDG7-The-Energy-Progress-Report | AM52: global_worldbank_global_electrification_grid_map
A53: Florida US Highways | B53: Silver | C53: 80 | D53: built_environment | E53: degraded | F53: unknown | G53: line | H53: Unknown | I53: 2 | K53: Curated | L53: 2026 | M53: open | N53: 2026-10-28 | O53: pass | P53: pass | Q53: pass | R53: warn | S53: not_checked | T53: n.a. | U53: n.a. | V53: pass | W53: warn | X53: pass | Y53: warn | Z53: pass | AA53: pass | AB53: pass | AC53: warn | AD53: warn | AE53: pass | AF53: pass | AG53: pass | AH53: pass | AI53: n.a. | AJ53: n.a. | AK53: soft404(warn);persistent_id(warn);license(warn);version(warn);unit(warn) | AL53: https://gis-fdot.opendata.arcgis.com/datasets/fdot::us-routes-tda/about | AM53: us_fl_us_highways
A54: Global Man-made Impervious Surface (GMIS) Dataset From Landsat, v1 (2010) | B54: Silver | C54: 96 | D54: built_environment | E54: healthy | F54: open | G54: grid_30m | H54: Needs raster support | I54: 2 | K54: Curated | L54: 2010 | M54: registration | N54: 2026-10-28 | O54: pass | P54: pass | Q54: pass | R54: pass | S54: pass | T54: pass | U54: warn | V54: pass | W54: pass | X54: pass | Y54: pass | Z54: pass | AA54: warn | AB54: pass | AC54: pass | AD54: pass | AE54: pass | AF54: not_checked | AG54: pass | AH54: pass | AI54: n.a. | AJ54: n.a. | AK54: format_match(warn);recency(warn) | AL54: https://www.earthdata.nasa.gov/data/catalog/sedac-ciesin-sedac-ulandsat-gmis-v1-1.0 | AM54: global_sedac_gmis_v1
A55: Global Roads Open Access Data Set, Version 1 (gROADSv1) | B55: Silver | C55: 96 | D55: built_environment | E55: healthy | F55: open | G55: line | H55: Needs a count/distance step | I55: 2 | K55: Curated | L55: 2010 | M55: registration | N55: 2026-10-28 | O55: pass | P55: pass | Q55: pass | R55: pass | S55: pass | T55: pass | U55: warn | V55: pass | W55: pass | X55: pass | Y55: pass | Z55: pass | AA55: warn | AB55: warn | AC55: pass | AD55: not_checked | AE55: pass | AF55: not_checked | AG55: pass | AH55: pass | AI55: n.a. | AJ55: n.a. | AK55: format_match(warn);recency(warn);cadence(warn) | AL55: https://www.earthdata.nasa.gov/data/catalog/sedac-ciesin-sedac-groads-v1-1.0 | AM55: global_sedac_groads_v1
A56: High Resolution Layer Imperviousness (Imperviousness Density, Imperviousness Change, Built-up) | B56: Silver | C56: 94 | D56: built_environment | E56: degraded | F56: unknown | G56: grid_10m | H56: Needs raster support | I56: 2 | K56: Curated | L56: 2018 | M56: registration | N56: 2026-10-28 | O56: pass | P56: pass | Q56: pass | R56: pass | S56: pass | T56: fail | U56: n.a. | V56: warn | W56: warn | X56: pass | Y56: not_checked | Z56: not_checked | AA56: not_checked | AB56: not_checked | AC56: not_checked | AD56: not_checked | AE56: warn | AF56: not_checked | AG56: not_checked | AH56: not_checked | AI56: n.a. | AJ56: n.a. | AK56: access_url;machine_metadata(warn);persistent_id(warn);coverage(warn) | AL56: https://land.copernicus.eu/en/products/high-resolution-layer-imperviousness | AM56: eu_copernicus_hrl_imperviousness
A57: National Agriculture Imagery Program (NAIP) | B57: Silver | C57: 93 | D57: built_environment | E57: healthy | F57: open | G57: grid_0.3m (30-100 cm imagery) | H57: Needs raster support | I57: 2 | K57: Curated | L57: 2023 | M57: open | N57: 2026-10-28 | O57: pass | P57: pass | Q57: pass | R57: pass | S57: pass | T57: pass | U57: warn | V57: pass | W57: warn | X57: pass | Y57: pass | Z57: pass | AA57: pass | AB57: pass | AC57: not_checked | AD57: warn | AE57: pass | AF57: pass | AG57: pass | AH57: pass | AI57: n.a. | AJ57: n.a. | AK57: format_match(warn);persistent_id(warn);unit(warn) | AL57: https://catalog.data.gov/dataset/national-agriculture-imagery-program-naip | AM57: us_usda_naip
A58: NRC List of Power Reactor Units (operating commercial reactors) | B58: Silver | C58: 76 | D58: built_environment | E58: degraded | F58: open | G58: point (approximate; text location such as '6 miles WNW of Russellville, AR'; no coordinates) | H58: Needs a count/distance step | I58: 2 | K58: Curated | L58: 2026 | M58: unknown | N58: 2026-10-28 | O58: pass | P58: pass | Q58: pass | R58: pass | S58: pass | T58: pass | U58: pass | V58: fail | W58: warn | X58: pass | Y58: pass | Z58: warn | AA58: pass | AB58: not_checked | AC58: warn | AD58: warn | AE58: pass | AF58: pass | AG58: fail | AH58: fail | AI58: n.a. | AJ58: n.a. | AK58: machine_metadata;join_key;format_gaia;persistent_id(warn);temporal(warn);version(warn);unit(warn) | AL58: https://www.nrc.gov/reactors/operating/list-power-reactor-units.html | AM58: us_nrc_power_reactor_units
A59: OpenStreetMap | B59: Silver | C59: 96 | D59: built_environment | E59: healthy | F59: open | G59: point | H59: Needs a count/distance step | I59: 2 | J59: hh_glaciares_osm;hh_red_vial_osm;hh_rios_arroyos_osm;hh_rutas_pie_osm;tt_ferry_routes;tt_populated_places;tt_regions;tt_roads;tz_populated_places_osm;tz_regions_osm | K59: Curated | M59: open | N59: 2026-10-28 | O59: pass | P59: pass | Q59: pass | R59: pass | S59: pass | T59: n.a. | U59: n.a. | V59: warn | W59: warn | X59: pass | Y59: pass | Z59: not_checked | AA59: not_checked | AB59: not_checked | AC59: not_checked | AD59: not_checked | AE59: pass | AF59: not_checked | AG59: not_checked | AH59: not_checked | AI59: pass | AJ59: not_checked | AK59: machine_metadata(warn);persistent_id(warn) | AL59: https://www.openstreetmap.org/ | AM59: global_openstreetmap
A60: OpenStreetMap US extracts (Geofabrik) | B60: Silver | C60: 97 | D60: built_environment | E60: healthy | F60: open | G60: point | H60: Needs a count/distance step | I60: 2 | K60: Curated | L60: 2026 | M60: open | N60: 2026-10-28 | O60: pass | P60: pass | Q60: pass | R60: pass | S60: pass | T60: pass | U60: warn | V60: warn | W60: warn | X60: pass | Y60: pass | Z60: pass | AA60: pass | AB60: warn | AC60: warn | AD60: not_checked | AE60: pass | AF60: pass | AG60: pass | AH60: pass | AI60: n.a. | AJ60: n.a. | AK60: format_match(warn);machine_metadata(warn);persistent_id(warn);cadence(warn);version(warn) | AL60: https://download.geofabrik.de/north-america/us.html | AM60: global_geofabrik_osm_extracts
A61: Transitland | B61: Silver | C61: 83 | D61: built_environment | E61: healthy | F61: non-commercial | G61: point | H61: Needs a count/distance step | I61: 2 | K61: Curated | L61: 2026 | M61: registration | N61: 2026-10-28 | O61: pass | P61: pass | Q61: pass | R61: pass | S61: pass | T61: pass | U61: pass | V61: warn | W61: warn | X61: pass | Y61: warn | Z61: warn | AA61: pass | AB61: warn | AC61: pass | AD61: pass | AE61: pass | AF61: warn | AG61: pass | AH61: pass | AI61: n.a. | AJ61: n.a. | AK61: machine_metadata(warn);persistent_id(warn);license(warn);temporal(warn);cadence(warn);access(warn) | AL61: https://www.transit.land/ | AM61: global_interline_transitland
A62: Treepedia Green View Index (GVI) | B62: Silver | C62: 92 | D62: built_environment | E62: healthy | F62: open | G62: point | H62: Needs raster support | I62: 2 | K62: Curated | M62: open | N62: 2026-10-28 | O62: pass | P62: pass | Q62: pass | R62: pass | S62: pass | T62: pass | U62: warn | V62: warn | W62: warn | X62: pass | Y62: pass | Z62: not_checked | AA62: not_checked | AB62: not_checked | AC62: not_checked | AD62: pass | AE62: warn | AF62: warn | AG62: pass | AH62: pass | AI62: n.a. | AJ62: n.a. | AK62: format_match(warn);machine_metadata(warn);persistent_id(warn);coverage(warn);access(warn) | AL62: https://github.com/mittrees/Treepedia_Public | AM62: global_mit_treepedia_gvi
A63: Canadian Climate Normals | B63: Silver | C63: 84 | D63: climate_hazard | E63: degraded | F63: non-commercial | G63: point | H63: Needs a count/distance step | I63: 3 | K63: Curated | L63: 2020 | M63: open | N63: 2026-10-22 | O63: pass | P63: pass | Q63: pass | R63: pass | S63: pass | T63: n.a. | U63: n.a. | V63: fail | W63: warn | X63: pass | Y63: warn | Z63: pass | AA63: pass | AB63: pass | AC63: pass | AD63: pass | AE63: pass | AF63: pass | AG63: warn | AH63: pass | AI63: n.a. | AJ63: n.a. | AK63: machine_metadata;persistent_id(warn);license(warn);join_key(warn) | AL63: https://climate.weather.gc.ca/climate_normals/index_e.html | AM63: ca_eccc_climate_normals
A64: CERRA sub-daily regional reanalysis data for Europe on single levels from 1984 to present | B64: Silver | C64: 100 | D64: climate_hazard | E64: healthy | F64: open | G64: grid_5.5km | H64: Needs raster support | I64: 3 | K64: Curated | L64: 2026 | M64: registration | N64: 2026-10-22 | O64: pass | P64: pass | Q64: pass | R64: pass | S64: pass | T64: pass | U64: warn | V64: pass | W64: pass | X64: pass | Y64: pass | Z64: pass | AA64: pass | AB64: pass | AC64: warn | AD64: pass | AE64: pass | AF64: not_checked | AG64: pass | AH64: fail | AI64: n.a. | AJ64: n.a. | AK64: format_gaia;format_match(warn);version(warn) | AL64: https://cds.climate.copernicus.eu/datasets/reanalysis-cerra-single-levels?tab=overview | AM64: eu_copernicus_cerra
A65: CMIP6 climate projections (Climate Data Store catalogue entry) | B65: Silver | C65: 91 | D65: climate_hazard | E65: healthy | F65: unknown | G65: grid_250km | H65: Needs raster support | I65: 3 | K65: Curated | L65: 2026 | M65: registration | N65: 2026-10-22 | O65: pass | P65: pass | Q65: pass | R65: pass | S65: pass | T65: pass | U65: warn | V65: pass | W65: pass | X65: pass | Y65: warn | Z65: pass | AA65: pass | AB65: warn | AC65: warn | AD65: not_checked | AE65: pass | AF65: not_checked | AG65: pass | AH65: pass | AI65: n.a. | AJ65: n.a. | AK65: format_match(warn);license(warn);cadence(warn);version(warn) | AL65: https://cds.climate.copernicus.eu/datasets/projections-cmip6?tab=overview | AM65: global_copernicus_cmip6_cds
A66: E-OBS daily gridded meteorological data for Europe from 1950 to present derived from in-situ observations | B66: Silver | C66: 93 | D66: climate_hazard | E66: healthy | F66: non-commercial | G66: grid_0.1deg | H66: Needs raster support | I66: 3 | K66: Curated | L66: 2026 | M66: open | N66: 2026-10-22 | O66: pass | P66: pass | Q66: pass | R66: pass | S66: pass | T66: pass | U66: warn | V66: pass | W66: pass | X66: pass | Y66: warn | Z66: pass | AA66: pass | AB66: pass | AC66: pass | AD66: pass | AE66: pass | AF66: pass | AG66: pass | AH66: pass | AI66: n.a. | AJ66: n.a. | AK66: format_match(warn);license(warn) | AL66: https://cds.climate.copernicus.eu/datasets/insitu-gridded-observations-europe?tab=overview | AM66: eu_copernicus_eobs
A67: ERA5 hourly data on single levels from 1940 to present | B67: Silver | C67: 100 | D67: climate_hazard | E67: healthy | F67: open | G67: grid_0.25deg | H67: Needs raster support | I67: 3 | K67: Curated | L67: 2026 | M67: registration | N67: 2026-10-22 | O67: pass | P67: pass | Q67: pass | R67: pass | S67: pass | T67: pass | U67: warn | V67: pass | W67: pass | X67: pass | Y67: pass | Z67: pass | AA67: pass | AB67: pass | AC67: pass | AD67: pass | AE67: pass | AF67: not_checked | AG67: pass | AH67: warn | AI67: n.a. | AJ67: n.a. | AK67: format_match(warn);format_gaia(warn) | AL67: https://cds.climate.copernicus.eu/datasets/reanalysis-era5-single-levels?tab=overview | AM67: global_copernicus_era5_single_levels
A68: ERA5-Land hourly data from 1950 to present | B68: Silver | C68: 100 | D68: climate_hazard | E68: healthy | F68: open | G68: grid_0.1deg | H68: Needs raster support | I68: 3 | J68: hh_dem_copernicus;tz_1984_copernicus_avg_temp | K68: Curated | L68: 2026 | M68: registration | N68: 2026-10-22 | O68: pass | P68: pass | Q68: pass | R68: pass | S68: pass | T68: n.a. | U68: n.a. | V68: pass | W68: pass | X68: pass | Y68: pass | Z68: pass | AA68: pass | AB68: pass | AC68: not_checked | AD68: pass | AE68: pass | AF68: not_checked | AG68: pass | AH68: warn | AI68: pass | AJ68: not_checked | AK68: format_gaia(warn) | AL68: https://cds.climate.copernicus.eu/datasets/reanalysis-era5-land | AM68: global_copernicus_era5_land
A69: ISIMIP (Inter-Sectoral Impact Model Intercomparison Project) simulation rounds ISIMIP2a/2b/3a/3b input and output data | B69: Silver | C69: 79 | D69: climate_hazard | E69: healthy | F69: unknown | G69: grid_0.25deg (15arcmin experiment labels; 60arcmin for most global sectors) | H69: Needs raster support | I69: 3 | K69: Curated | L69: current | M69: open | N69: 2026-10-22 | O69: pass | P69: pass | Q69: pass | R69: pass | S69: pass | T69: pass | U69: warn | V69: warn | W69: warn | X69: pass | Y69: warn | Z69: not_checked | AA69: not_checked | AB69: warn | AC69: pass | AD69: warn | AE69: pass | AF69: pass | AG69: not_checked | AH69: not_checked | AI69: n.a. | AJ69: n.a. | AK69: format_match(warn);machine_metadata(warn);persistent_id(warn);license(warn);cadence(warn);unit(warn) | AL69: https://www.isimip.org/outputdata/ | AM69: global_isimip_output_data
A70: Lancet Countdown on Health and Climate Change data explorer | B70: Silver | C70: 82 | D70: climate_hazard | E70: healthy | F70: non-commercial | G70: country | H70: Joins today | I70: 3 | K70: Curated | L70: 2024 | M70: open | N70: 2026-10-22 | O70: pass | P70: pass | Q70: pass | R70: pass | S70: pass | T70: n.a. | U70: n.a. | V70: warn | W70: warn | X70: pass | Y70: warn | Z70: pass | AA70: pass | AB70: pass | AC70: pass | AD70: warn | AE70: pass | AF70: pass | AG70: not_checked | AH70: warn | AI70: n.a. | AJ70: n.a. | AK70: machine_metadata(warn);persistent_id(warn);license(warn);unit(warn);format_gaia(warn) | AL70: https://lancetcountdown.org/explore-our-data/ | AM70: global_lancet_countdown_indicators
A71: Miami-Dade derived raster layers (surface temperature, average LST 2013-2022, NDVI, distance to water, distance to parks) | B71: Silver | C71: 85 | D71: climate_hazard | E71: degraded | F71: attribution | G71: grid_30m | H71: Needs raster support | I71: 3 | J71: mdc_2013_2022_lst_30m;mdc_2021_hylo | K71: Curated | L71: 2022 | M71: open | N71: 2026-10-22 | O71: pass | P71: pass | Q71: pass | R71: warn | S71: not_checked | T71: n.a. | U71: n.a. | V71: fail | W71: warn | X71: pass | Y71: pass | Z71: pass | AA71: pass | AB71: warn | AC71: warn | AD71: pass | AE71: pass | AF71: pass | AG71: warn | AH71: pass | AI71: pass | AJ71: not_checked | AK71: machine_metadata;soft404(warn);persistent_id(warn);cadence(warn);version(warn);join_key(warn) | AL71: https://scholarship.miami.edu/esploro/outputs/991032051519802976 | AM71: us_um_gdsc_mdc_derived_layers
A72: National Risk Index (NRI) | B72: Silver | C72: 93 | D72: climate_hazard | E72: healthy | F72: open | G72: tract | H72: Joins today | I72: 3 | K72: Curated | L72: 2025 | M72: open | N72: 2026-10-22 | O72: pass | P72: pass | Q72: pass | R72: pass | S72: pass | T72: pass | U72: pass | V72: warn | W72: warn | X72: pass | Y72: pass | Z72: warn | AA72: pass | AB72: not_checked | AC72: pass | AD72: pass | AE72: not_checked | AF72: not_checked | AG72: not_checked | AH72: not_checked | AI72: n.a. | AJ72: n.a. | AK72: machine_metadata(warn);persistent_id(warn);temporal(warn) | AL72: https://hazards.fema.gov/nri/ | AM72: us_fema_national_risk_index
A73: Natural Disaster Hotspots: Global Multihazard Frequency and Distribution / Mortality Risks / Proportional Economic Loss (CHRR, v1.0) | B73: Silver | C73: 91 | D73: climate_hazard | E73: healthy | F73: open | G73: grid_2.5arcmin (0.0417 x 0.0417 decimal degrees) | H73: Needs raster support | I73: 3 | K73: Curated | L73: 2000 | M73: registration | N73: 2026-10-22 | O73: pass | P73: pass | Q73: pass | R73: pass | S73: pass | T73: pass | U73: warn | V73: pass | W73: pass | X73: pass | Y73: pass | Z73: pass | AA73: warn | AB73: warn | AC73: pass | AD73: pass | AE73: pass | AF73: not_checked | AG73: warn | AH73: warn | AI73: n.a. | AJ73: n.a. | AK73: format_match(warn);recency(warn);cadence(warn);join_key(warn);format_gaia(warn) | AL73: https://www.earthdata.nasa.gov/data/catalog/sedac-ciesin-chrr-ndh-multi-hfd-1.0 | AM73: global_sedac_ndh_multihazard
A74: ThinkHazard! multi-hazard classification by administrative unit | B74: Silver | C74: 88 | D74: climate_hazard | E74: degraded | F74: attribution | G74: admin2 | H74: Joins today | I74: 3 | K74: Curated | L74: 2020 | M74: open | N74: 2026-10-22 | O74: pass | P74: pass | Q74: pass | R74: pass | S74: pass | T74: fail | U74: n.a. | V74: fail | W74: warn | X74: pass | Y74: pass | Z74: warn | AA74: pass | AB74: pass | AC74: warn | AD74: pass | AE74: pass | AF74: pass | AG74: warn | AH74: warn | AI74: n.a. | AJ74: n.a. | AK74: access_url;machine_metadata;persistent_id(warn);temporal(warn);version(warn);join_key(warn);format_gaia(warn) | AL74: https://thinkhazard.org/en/about | AM74: global_gfdrr_thinkhazard
A75: Agroclimatic indicators from 1951 to 2099 derived from climate projections | B75: Silver | C75: 96 | D75: climate_hazard | E75: healthy | F75: open | G75: grid_0.5deg | H75: Needs raster support | I75: 2 | K75: Curated | L75: 2099 | M75: registration | N75: 2026-10-28 | O75: pass | P75: pass | Q75: pass | R75: pass | S75: pass | T75: pass | U75: warn | V75: pass | W75: pass | X75: pass | Y75: pass | Z75: pass | AA75: warn | AB75: pass | AC75: pass | AD75: pass | AE75: pass | AF75: not_checked | AG75: pass | AH75: pass | AI75: n.a. | AJ75: n.a. | AK75: format_match(warn);recency(warn) | AL75: https://cds.climate.copernicus.eu/datasets/sis-agroclimatic-indicators?tab=overview | AM75: global_copernicus_agroclimatic_indicators
A76: EM-DAT: The International Disaster Database | B76: Silver | C76: 81 | D76: climate_hazard | E76: healthy | F76: non-commercial | G76: country | H76: Needs a count/distance step | I76: 2 | K76: Curated | L76: 2026 | M76: registration | N76: 2026-10-28 | O76: pass | P76: pass | Q76: pass | R76: pass | S76: pass | T76: pass | U76: pass | V76: warn | W76: warn | X76: pass | Y76: warn | Z76: pass | AA76: pass | AB76: not_checked | AC76: not_checked | AD76: warn | AE76: pass | AF76: not_checked | AG76: not_checked | AH76: not_checked | AI76: n.a. | AJ76: n.a. | AK76: machine_metadata(warn);persistent_id(warn);license(warn);unit(warn) | AL76: https://www.emdat.be/ | AM76: global_cred_emdat
A77: European Drought Observatory (EDO) and Global Drought Observatory (GDO) drought indicators | B77: Silver | C77: 86 | D77: climate_hazard | E77: degraded | F77: attribution | G77: grid_5km | H77: Needs raster support | I77: 2 | K77: Curated | L77: current | M77: open | N77: 2026-10-28 | O77: pass | P77: pass | Q77: pass | R77: pass | S77: pass | T77: pass | U77: pass | V77: fail | W77: warn | X77: pass | Y77: pass | Z77: not_checked | AA77: not_checked | AB77: not_checked | AC77: not_checked | AD77: not_checked | AE77: warn | AF77: warn | AG77: not_checked | AH77: not_checked | AI77: n.a. | AJ77: n.a. | AK77: machine_metadata;persistent_id(warn);coverage(warn);access(warn) | AL77: https://drought.emergency.copernicus.eu/tumbo/edo/download/ | AM77: eu_copernicus_edo_gdo_drought
A78: European Forest Fire Information System (EFFIS) burnt areas, active fires, fire danger forecast | B78: Silver | C78: 85 | D78: climate_hazard | E78: degraded | F78: open | G78: polygon | H78: Needs raster support | I78: 2 | K78: Curated | L78: 2026 | M78: open | N78: 2026-10-28 | O78: pass | P78: pass | Q78: pass | R78: pass | S78: pass | T78: fail | U78: n.a. | V78: fail | W78: warn | X78: pass | Y78: pass | Z78: warn | AA78: pass | AB78: pass | AC78: not_checked | AD78: warn | AE78: warn | AF78: pass | AG78: pass | AH78: pass | AI78: n.a. | AJ78: n.a. | AK78: access_url;machine_metadata;persistent_id(warn);temporal(warn);unit(warn);coverage(warn) | AL78: https://forest-fire.emergency.copernicus.eu/applications/data-and-services | AM78: eu_copernicus_effis
A79: FIRMS: Fire Information for Resource Management System active fire / thermal anomaly detections (MODIS, VIIRS) | B79: Silver | C79: 93 | D79: climate_hazard | E79: healthy | F79: open | G79: point (375 m VIIRS pixel; ~1 km MODIS pixel) | H79: Needs raster support | I79: 2 | K79: Curated | L79: 2026 | M79: registration | N79: 2026-10-28 | O79: pass | P79: pass | Q79: pass | R79: pass | S79: pass | T79: pass | U79: pass | V79: warn | W79: warn | X79: pass | Y79: pass | Z79: pass | AA79: pass | AB79: pass | AC79: pass | AD79: pass | AE79: pass | AF79: warn | AG79: pass | AH79: pass | AI79: n.a. | AJ79: n.a. | AK79: machine_metadata(warn);persistent_id(warn);access(warn) | AL79: https://firms.modaps.eosdis.nasa.gov/ | AM79: global_nasa_firms_active_fires
A80: GEM Global Earthquake Model: Global Seismic Hazard Map, Global Exposure Model, Global Seismic Risk Map (2018, 2023 versions) | B80: Silver | C80: 81 | D80: climate_hazard | E80: degraded | F80: non-commercial | G80: grid_0.01deg | H80: Needs raster support | I80: 2 | K80: Curated | L80: 2026 | M80: open | N80: 2026-10-28 | O80: pass | P80: pass | Q80: pass | R80: pass | S80: pass | T80: fail | U80: n.a. | V80: warn | W80: warn | X80: pass | Y80: warn | Z80: warn | AA80: pass | AB80: warn | AC80: pass | AD80: warn | AE80: pass | AF80: pass | AG80: pass | AH80: pass | AI80: n.a. | AJ80: n.a. | AK80: access_url;machine_metadata(warn);persistent_id(warn);license(warn);temporal(warn);cadence(warn);unit(warn) | AL80: https://www.globalquakemodel.org/products | AM80: global_gem_openquake_hazard_risk
A81: Low Elevation Coastal Zone (LECZ) Urban-Rural Population and Land Area Estimates, Version 3 | B81: Silver | C81: 92 | D81: climate_hazard | E81: healthy | F81: open | G81: grid_30arcsec (0.00083 deg, ~1 km) | H81: Needs raster support | I81: 2 | K81: Curated | L81: 2015 | M81: registration | N81: 2026-10-28 | O81: pass | P81: pass | Q81: pass | R81: pass | S81: pass | T81: pass | U81: warn | V81: pass | W81: pass | X81: pass | Y81: pass | Z81: pass | AA81: warn | AB81: warn | AC81: pass | AD81: pass | AE81: pass | AF81: warn | AG81: pass | AH81: pass | AI81: n.a. | AJ81: n.a. | AK81: format_match(warn);recency(warn);cadence(warn);access(warn) | AL81: https://www.earthdata.nasa.gov/data/catalog/esdis-ciesin-sedac-lecz-urplaev3-3.00 | AM81: global_sedac_lecz_v3
A82: MACA (Multivariate Adaptive Constructed Analogs) downscaled CMIP5 projections | B82: Silver | C82: 94 | D82: climate_hazard | E82: healthy | F82: open | G82: grid_4km (1/24 degree, METDATA); grid_6km (1/16 degree, LIVNEH) | H82: Needs raster support | I82: 2 | K82: Curated | L82: current | M82: open | N82: 2026-10-28 | O82: pass | P82: pass | Q82: pass | R82: pass | S82: pass | T82: pass | U82: warn | V82: warn | W82: warn | X82: pass | Y82: pass | Z82: warn | AA82: not_checked | AB82: not_checked | AC82: pass | AD82: pass | AE82: pass | AF82: pass | AG82: pass | AH82: pass | AI82: n.a. | AJ82: n.a. | AK82: format_match(warn);machine_metadata(warn);persistent_id(warn);temporal(warn) | AL82: https://www.climatologylab.org/maca.html | AM82: us_uidaho_maca
A83: MODIS/Terra+Aqua Burned Area Monthly L3 Global 500m SIN Grid V061 (MCD64A1) | B83: Silver | C83: 100 | D83: climate_hazard | E83: healthy | F83: open | G83: grid_500m (MODIS Sinusoidal Tiling System) | H83: Needs raster support | I83: 2 | K83: Curated | L83: 2026 | M83: registration | N83: 2026-10-28 | O83: pass | P83: pass | Q83: pass | R83: pass | S83: pass | T83: pass | U83: warn | V83: pass | W83: pass | X83: pass | Y83: pass | Z83: pass | AA83: pass | AB83: warn | AC83: pass | AD83: pass | AE83: pass | AF83: not_checked | AG83: pass | AH83: warn | AI83: n.a. | AJ83: n.a. | AK83: format_match(warn);cadence(warn);format_gaia(warn) | AL83: https://www.earthdata.nasa.gov/data/catalog/lpcloud-mcd64a1-061 | AM83: global_nasa_mcd64a1_burned_area
A84: National Seismic Hazard Model (NSHM) | B84: Silver | C84: 74 | D84: climate_hazard | E84: healthy | F84: unknown | G84: grid_0.02deg (stated for Hawaii 2021 only; other regions not stated) | H84: Needs raster support | I84: 2 | K84: Curated | L84: 2023 | M84: open | N84: 2026-10-28 | O84: pass | P84: pass | Q84: pass | R84: pass | S84: pass | T84: pass | U84: pass | V84: warn | W84: warn | X84: pass | Y84: warn | Z84: warn | AA84: pass | AB84: pass | AC84: pass | AD84: warn | AE84: pass | AF84: not_checked | AG84: warn | AH84: not_checked | AI84: n.a. | AJ84: n.a. | AK84: machine_metadata(warn);persistent_id(warn);license(warn);temporal(warn);unit(warn);join_key(warn) | AL84: https://www.usgs.gov/programs/earthquake-hazards/science/national-seismic-hazard-model | AM84: us_usgs_national_seismic_hazard_model
A85: OpenFEMA Disaster Declarations Summaries (v2) | B85: Silver | C85: 91 | D85: climate_hazard | E85: healthy | F85: attribution | G85: county | H85: Joins today | I85: 2 | K85: Curated | L85: 2026 | M85: open | N85: 2026-10-22 | O85: pass | P85: pass | Q85: pass | R85: pass | S85: pass | T85: pass | U85: pass | V85: warn | W85: warn | X85: pass | Y85: pass | Z85: pass | AA85: pass | AB85: pass | AC85: pass | AD85: warn | AE85: pass | AF85: pass | AG85: pass | AH85: pass | AI85: n.a. | AJ85: n.a. | AK85: machine_metadata(warn);persistent_id(warn);unit(warn) | AL85: https://www.fema.gov/openfema-data-page/disaster-declarations-summaries-v2 | AM85: us_fema_openfema_disaster_declarations
A86: U.S. Billion-Dollar Weather and Climate Disasters (Climate Central continuation) | B86: Silver | C86: 77 | D86: climate_hazard | E86: healthy | F86: non-commercial | G86: state | H86: Joins today | I86: 2 | K86: Curated | L86: 2026 | M86: restricted | N86: 2026-10-22 | O86: pass | P86: pass | Q86: pass | R86: pass | S86: pass | T86: pass | U86: pass | V86: warn | W86: warn | X86: pass | Y86: warn | Z86: pass | AA86: pass | AB86: warn | AC86: warn | AD86: pass | AE86: pass | AF86: fail | AG86: warn | AH86: fail | AI86: n.a. | AJ86: n.a. | AK86: access;format_gaia;machine_metadata(warn);persistent_id(warn);license(warn);cadence(warn);version(warn);join_key(warn) | AL86: https://www.climatecentral.org/billion-dollar-disasters | AM86: us_climatecentral_billion_dollar_disasters
A87: U.S. Drought Monitor (USDM) GIS Data | B87: Silver | C87: 84 | D87: climate_hazard | E87: degraded | F87: attribution | G87: grid_500m (gridded data); polygon (one polygon per DM class); county/state (Excel statistics) | H87: Needs raster support | I87: 2 | K87: Curated | L87: current | M87: open | N87: 2026-10-28 | O87: pass | P87: pass | Q87: pass | R87: pass | S87: pass | T87: pass | U87: pass | V87: fail | W87: warn | X87: pass | Y87: pass | Z87: warn | AA87: not_checked | AB87: not_checked | AC87: not_checked | AD87: warn | AE87: pass | AF87: pass | AG87: pass | AH87: pass | AI87: n.a. | AJ87: n.a. | AK87: machine_metadata;persistent_id(warn);temporal(warn);unit(warn) | AL87: https://droughtmonitor.unl.edu/DmData/GISData.aspx | AM87: us_ndmc_us_drought_monitor
A88: Longitudinal Tract Data Base (LTDB) | B88: Silver | C88: 80 | D88: demographics | E88: degraded | F88: non-commercial | G88: tract | H88: Joins today | I88: 3 | K88: Curated | L88: 2020 | M88: registration | N88: 2026-10-22 | O88: pass | P88: pass | Q88: pass | R88: pass | S88: pass | T88: pass | U88: warn | V88: fail | W88: warn | X88: pass | Y88: warn | Z88: pass | AA88: pass | AB88: warn | AC88: not_checked | AD88: pass | AE88: warn | AF88: warn | AG88: warn | AH88: warn | AI88: n.a. | AJ88: n.a. | AK88: machine_metadata;format_match(warn);persistent_id(warn);license(warn);cadence(warn);coverage(warn);access(warn);join_key(warn);format_gaia(warn) | AL88: https://s4.ad.brown.edu/projects/diversity/Researcher/LTDB.htm | AM88: us_brown_ltdb
A89: Our World in Data | B89: Silver | C89: 96 | D89: demographics | E89: healthy | F89: attribution | G89: country | H89: Not linkable as listed | I89: 3 | K89: Curated | L89: current | M89: open | N89: 2026-10-28 | O89: pass | P89: pass | Q89: pass | R89: pass | S89: pass | T89: pass | U89: pass | V89: warn | W89: warn | X89: pass | Y89: pass | Z89: not_checked | AA89: not_checked | AB89: warn | AC89: not_checked | AD89: not_checked | AE89: not_checked | AF89: pass | AG89: not_checked | AH89: warn | AI89: n.a. | AJ89: n.a. | AK89: machine_metadata(warn);persistent_id(warn);cadence(warn);format_gaia(warn) | AL89: https://ourworldindata.org/about | AM89: global_owid
A90: American Community Survey 1-Year Data | B90: Silver | C90: 86 | D90: demographics | E90: healthy | F90: attribution | G90: place and county with population 65,000+ (no tract/block group/ZCTA in 1-year data) | H90: Joins today | I90: 2 | K90: Curated | L90: 2024 | M90: unknown | N90: 2026-10-22 | O90: pass | P90: pass | Q90: pass | R90: pass | S90: pass | T90: pass | U90: pass | V90: warn | W90: warn | X90: pass | Y90: pass | Z90: pass | AA90: pass | AB90: pass | AC90: pass | AD90: warn | AE90: pass | AF90: pass | AG90: warn | AH90: warn | AI90: n.a. | AJ90: n.a. | AK90: machine_metadata(warn);persistent_id(warn);unit(warn);join_key(warn);format_gaia(warn) | AL90: https://www.census.gov/data/developers/data-sets/acs-1year.html | AM90: us_census_acs_1year
A91: Censo Nacional de Poblacion y Vivienda 2018 (CNPV) | B91: Silver | C91: 83 | D91: demographics | E91: healthy | F91: attribution | G91: admin2 (municipio) on landing page; manzana/MGN not mentioned | H91: Joins today | I91: 2 | K91: Curated | L91: 2018 | M91: unknown | N91: 2026-10-22 | O91: pass | P91: pass | Q91: pass | R91: pass | S91: pass | T91: pass | U91: warn | V91: warn | W91: warn | X91: pass | Y91: pass | Z91: pass | AA91: warn | AB91: not_checked | AC91: warn | AD91: warn | AE91: pass | AF91: pass | AG91: warn | AH91: warn | AI91: n.a. | AJ91: n.a. | AK91: format_match(warn);machine_metadata(warn);persistent_id(warn);recency(warn);version(warn);unit(warn);join_key(warn);format_gaia(warn) | AL91: https://www.dane.gov.co/index.php/estadisticas-por-tema/demografia-y-poblacion/censo-nacional-de-poblacion-y-vivenda-2018 | AM91: co_dane_cnpv_2018
A92: Census 2022 Small Area Population Statistics (SAPS) | B92: Silver | C92: 86 | D92: demographics | E92: healthy | F92: open | G92: polygon (Small Area, 18,919 units) | H92: Joins today | I92: 2 | K92: Curated | L92: 2022 | M92: open | N92: 2026-10-22 | O92: pass | P92: pass | Q92: pass | R92: pass | S92: pass | T92: pass | U92: warn | V92: warn | W92: warn | X92: pass | Y92: pass | Z92: pass | AA92: pass | AB92: warn | AC92: warn | AD92: warn | AE92: pass | AF92: pass | AG92: warn | AH92: warn | AI92: n.a. | AJ92: n.a. | AK92: format_match(warn);machine_metadata(warn);persistent_id(warn);cadence(warn);version(warn);unit(warn);join_key(warn);format_gaia(warn) | AL92: https://www.cso.ie/en/census/census2022/census2022smallareapopulationstatistics/ | AM92: ie_cso_census_2022_saps
A93: Degree of urbanisation statistics (cities, towns and suburbs, rural areas) | B93: Silver | C93: 95 | D93: demographics | E93: healthy | F93: unknown | G93: postcode_small_area | H93: Joins today | I93: 2 | K93: Curated | M93: unknown | N93: 2026-10-22 | O93: pass | P93: pass | Q93: pass | R93: pass | S93: pass | T93: n.a. | U93: n.a. | V93: warn | W93: warn | X93: pass | Y93: not_checked | Z93: not_checked | AA93: not_checked | AB93: not_checked | AC93: not_checked | AD93: not_checked | AE93: not_checked | AF93: pass | AG93: not_checked | AH93: not_checked | AI93: n.a. | AJ93: n.a. | AK93: machine_metadata(warn);persistent_id(warn) | AL93: https://ec.europa.eu/eurostat/web/degree-of-urbanisation/database | AM93: eu_eurostat_degree_of_urbanisation
A94: e-Stat Statistical GIS (jSTAT MAP; small area and regional mesh statistics; boundary data) | B94: Silver | C94: 83 | D94: demographics | E94: degraded | F94: attribution | G94: polygon (小地域 small area); regional mesh mentioned but mesh size not stated | H94: Needs raster support | I94: 2 | K94: Curated | L94: 2025 | M94: open | N94: 2026-10-28 | O94: pass | P94: pass | Q94: pass | R94: warn | S94: pass | T94: pass | U94: pass | V94: warn | W94: warn | X94: pass | Y94: pass | Z94: warn | AA94: pass | AB94: warn | AC94: not_checked | AD94: warn | AE94: warn | AF94: pass | AG94: pass | AH94: not_checked | AI94: n.a. | AJ94: n.a. | AK94: soft404(warn);machine_metadata(warn);persistent_id(warn);temporal(warn);cadence(warn);unit(warn);coverage(warn) | AL94: https://www.e-stat.go.jp/gis | AM94: jp_estat_jstat_map
A95: IPUMS NHGIS (National Historical Geographic Information System) | B95: Silver | C95: 82 | D95: demographics | E95: degraded | F95: registration | G95: block | H95: Joins today | I95: 2 | K95: Curated | L95: 2026 | M95: registration | N95: 2026-10-22 | O95: pass | P95: pass | Q95: pass | R95: pass | S95: pass | T95: pass | U95: pass | V95: fail | W95: warn | X95: pass | Y95: warn | Z95: pass | AA95: pass | AB95: warn | AC95: warn | AD95: pass | AE95: pass | AF95: warn | AG95: not_checked | AH95: not_checked | AI95: n.a. | AJ95: n.a. | AK95: machine_metadata;persistent_id(warn);license(warn);cadence(warn);version(warn);access(warn) | AL95: https://www.nhgis.org/ | AM95: us_ipums_nhgis
A96: Population grids (GEOSTAT 1 km grids and Census 2021 grid) | B96: Silver | C96: 91 | D96: demographics | E96: healthy | F96: open (Census 2021); non-commercial (GEOSTAT 2006/2011) | G96: grid_1km (Census 2021 and GEOSTAT); derived JRC 100 m population grid also linked | H96: Needs raster support | I96: 2 | K96: Curated | L96: 2021 | M96: open | N96: 2026-10-28 | O96: pass | P96: pass | Q96: pass | R96: pass | S96: pass | T96: n.a. | U96: n.a. | V96: warn | W96: warn | X96: pass | Y96: warn | Z96: pass | AA96: pass | AB96: warn | AC96: pass | AD96: pass | AE96: pass | AF96: pass | AG96: pass | AH96: pass | AI96: n.a. | AJ96: n.a. | AK96: machine_metadata(warn);persistent_id(warn);license(warn);cadence(warn) | AL96: https://ec.europa.eu/eurostat/web/gisco/geodata/population-distribution/population-grids | AM96: eu_eurostat_gisco_population_grids
A97: Recensement General de la Population et de l'Habitat 2024 (RGPH 2024) | B97: Silver | C97: 86 | D97: demographics | E97: healthy | F97: open | G97: admin3 (commune); urban/rural split | H97: Joins today | I97: 2 | K97: Curated | L97: 2024 | M97: open | N97: 2026-10-22 | O97: pass | P97: pass | Q97: pass | R97: pass | S97: pass | T97: pass | U97: pass | V97: warn | W97: warn | X97: pass | Y97: pass | Z97: pass | AA97: pass | AB97: warn | AC97: warn | AD97: warn | AE97: pass | AF97: pass | AG97: warn | AH97: warn | AI97: n.a. | AJ97: n.a. | AK97: machine_metadata(warn);persistent_id(warn);cadence(warn);version(warn);unit(warn);join_key(warn);format_gaia(warn) | AL97: https://www.hcp.ma/Population-legale-du-Royaume-du-Maroc-repartie-par-regions-provinces-et-prefectures-et-communes-selon-les-resultats-du_a3974.html | AM97: ma_hcp_rgph_2024
A98: Saudi Census 2022 | B98: Silver | C98: 90 | D98: demographics | E98: healthy | F98: unknown | G98: postcode_small_area | H98: Joins today | I98: 2 | K98: Curated | L98: 2022 | M98: open | N98: 2026-10-22 | O98: pass | P98: pass | Q98: pass | R98: pass | S98: pass | T98: warn | U98: n.a. | V98: warn | W98: warn | X98: pass | Y98: not_checked | Z98: warn | AA98: pass | AB98: not_checked | AC98: not_checked | AD98: not_checked | AE98: not_checked | AF98: not_checked | AG98: not_checked | AH98: not_checked | AI98: n.a. | AJ98: n.a. | AK98: access_url(warn);machine_metadata(warn);persistent_id(warn);temporal(warn) | AL98: https://www.stats.gov.sa/en/ | AM98: sa_gastat_census_2022
A99: 3D Elevation Program (3DEP) elevation products | B99: Silver | C99: 94 | D99: environment | E99: healthy | F99: open | G99: grid_1m | H99: Needs raster support | I99: 3 | K99: Curated | L99: 2026 | M99: open | N99: 2026-10-22 | O99: pass | P99: pass | Q99: pass | R99: pass | S99: pass | T99: pass | U99: pass | V99: warn | W99: warn | X99: pass | Y99: pass | Z99: warn | AA99: pass | AB99: warn | AC99: warn | AD99: pass | AE99: pass | AF99: pass | AG99: pass | AH99: pass | AI99: n.a. | AJ99: n.a. | AK99: machine_metadata(warn);persistent_id(warn);temporal(warn);cadence(warn);version(warn) | AL99: https://www.usgs.gov/3d-elevation-program | AM99: us_usgs_3dep
A100: AirNow API (real-time observations, forecasts, AQI) | B100: Silver | C100: 83 | D100: environment | E100: degraded | F100: registration | G100: point | H100: Needs a count/distance step | I100: 3 | K100: Curated | L100: 2026 | M100: registration | N100: 2026-10-22 | O100: pass | P100: pass | Q100: pass | R100: pass | S100: pass | T100: pass | U100: pass | V100: fail | W100: warn | X100: pass | Y100: warn | Z100: not_checked | AA100: pass | AB100: pass | AC100: not_checked | AD100: pass | AE100: pass | AF100: warn | AG100: pass | AH100: warn | AI100: n.a. | AJ100: n.a. | AK100: machine_metadata;persistent_id(warn);license(warn);access(warn);format_gaia(warn) | AL100: https://docs.airnowapi.org/ | AM100: us_epa_airnow_api
A101: AirQo air quality data (API, Nexus, Vertex) | B101: Silver | C101: 84 | D101: environment | E101: healthy | F101: registration | G101: point | H101: Needs a count/distance step | I101: 3 | K101: Curated | L101: 2026 | M101: registration | N101: 2026-10-22 | O101: pass | P101: pass | Q101: pass | R101: pass | S101: pass | T101: n.a. | U101: n.a. | V101: warn | W101: warn | X101: pass | Y101: warn | Z101: not_checked | AA101: pass | AB101: warn | AC101: not_checked | AD101: pass | AE101: warn | AF101: warn | AG101: not_checked | AH101: warn | AI101: n.a. | AJ101: n.a. | AK101: machine_metadata(warn);persistent_id(warn);license(warn);cadence(warn);coverage(warn);access(warn);format_gaia(warn) | AL101: https://airqo.net/ | AM101: ug_makerere_airqo
A102: Annual PM2.5 Concentrations for Countries and Urban Areas, v1 (1998 - 2016) | B102: Silver | C102: 88 | D102: environment | E102: healthy | F102: open | G102: urban area / country | H102: Joins today | I102: 3 | J102: global_pm25_concentration_1998_2016 | K102: Curated | L102: 2016 | M102: open | N102: 2026-10-28 | O102: pass | P102: pass | Q102: pass | R102: pass | S102: pass | T102: pass | U102: warn | V102: not_checked | W102: pass | X102: pass | Y102: pass | Z102: pass | AA102: warn | AB102: not_checked | AC102: not_checked | AD102: warn | AE102: not_checked | AF102: pass | AG102: not_checked | AH102: pass | AI102: pass | AJ102: fail | AK102: recipe_health;format_match(warn);recency(warn);unit(warn) | AL102: https://dataverse.harvard.edu/dataset.xhtml?persistentId=doi:10.7910/DVN/RHIFKL | AM102: global_sedac_pm25_countries_urban_1998_2016
...

Sheet Refined set
A1: Dataset | B1: Publisher | C1: Theme | D1: Coverage | E1: Finest unit | F1: Years | G1: Latest year | H1: License class | I1: Licence (confirmed) | J1: Access | K1: Format | L1: Gaia fit | M1: Health relevance (0-3) | N1: In gaiaCatalog | O1: Tier | P1: Score | Q1: Landing page | R1: id
A2: 2022 Social Vulnerability by US Census Block Group | B2: Harvard Dataverse deposit (derived from CDC/ATSDR SVI) | D2: US | E2: block_group | F2: title says 2022; file name says 2020; not reconciled | G2: 2022 | H2: open | I2: CC0 1.0 | J2: open_download | K2: tab | O2: Silver | Q2: https://doi.org/10.7910/dvn/arbhpk | R2: us_harvard_svi_percentiles_block_group
A3: Beachwatch swim sites with pollution forecasts and latest water quality, New South Wales | B3: NSW Beachwatch (published via publicdata.au / Zenodo) | D3: NSW swim sites (246 rows) | E3: point | F3: live feed, version 2026-10-29 | G3: 2026 | H3: open | I3: CC BY 4.0 | J3: open_download | K3: csv; parquet; json; xlsx | O3: Gold | Q3: https://doi.org/10.5281/zenodo.23113632 | R3: au_nsw_beachwatch_swim_sites_live
A4: Birthing Friendly Hospitals with Geocoded Addresses | B4: CMS Provider Data Catalog | E4: facility (point; geocoded) | F4: current snapshot; catalog 'modified' 2026-10-22, next update 2027-01-20 | H4: public_domain_us_federal | I4: not stated in catalog metadata (federal open data; unverified) | J4: open_download (CSV via DKAN API) | O4: Silver | Q4: https://data.cms.gov/provider-data/dataset/hbf-map | R4: us_cms_pdc_hbf_map
A5: Buprenorphine Prescribing Requirements and Limitations | B5: Center for Public Health Law Research (Temple University; LawAtlas) | D5: US (50 states + DC) | E5: state | F5: 2023-03-01 to 2024-09-01 | G5: 2024 | J5: registration | K5: not stated | O5: Silver | Q5: https://doi.org/10.60541/snt6-m904 | R5: us_lawatlas_buprenorphine_prescribing_laws
A6: Calculating Hazard Indices for PFAS in California's Drinking Water | B6: Mendeley Data (Geotracker-derived) | D6: California (Geotracker monitoring locations) | E6: point | F6: years not stated (published 2024-11-22) | H6: open | I6: CC BY 4.0 | J6: open_download ("Download All") | K6: xlsx | O6: Silver | Q6: https://doi.org/10.17632/hy28gb37tg | R6: us_mendeley_california_pfas_hazard_indices
A7: Compilation of riverine water quality data from the Great Barrier Reef catchment area, northeastern Australia: version 2.0 | B7: James Cook University (Great Barrier Reef catchments) | D7: Great Barrier Reef catchment (466 sites) | E7: point | F7: 1986-10-19 to 2023-02-08 | G7: 2023 | H7: open | I7: CC BY 4.0 (page: "will be licensed under") | J7: open_download ("Open: free access under license") | K7: xlsx; zip | O7: Silver | Q7: https://doi.org/10.25903/pase-na93 | R7: au_jcu_gbr_catchment_riverine_water_quality_v2
A8: Complications and Unplanned Hospital Visits - PPS-Exempt Cancer Hospital | B8: CMS Provider Data Catalog | E8: facility (11 PPS-exempt cancer hospitals) | F8: current snapshot; catalog 'modified' 2026-10-22, next update 2027-01-20 | H8: public_domain_us_federal | I8: not stated in catalog metadata (federal open data; unverified) | J8: open_download (CSV via DKAN API) | O8: Silver | Q8: https://data.cms.gov/provider-data/dataset/z8ax-x9j1 | R8: us_cms_pdc_z8ax_x9j1
A9: COVID-19 US State Policy Database | B9: Boston University School of Public Health (CUSP; hosted on openICPSR) | D9: US (50 states + DC) | E9: state | F9: 2/2020 to 6/2020 (time period); version V143 dated 2022-03-30 | G9: 2020 | J9: open_download (assumed: no login named) | K9: not stated (folder "COVID-19-US-State-Policy-Database-master"; data sources on a linked page) | O9: Silver | Q9: https://doi.org/10.3886/e119446 | R9: us_cusp_covid19_state_policy_database
A10: COVID-19: State Emergency Declarations & Mitigation Policies | B10: Center for Public Health Law Research (Temple University; LawAtlas) | D10: US (50 states + DC) | E10: state | F10: 2020-01-20 to 2020-07-01 | G10: 2020 | J10: registration | K10: not stated | O10: Silver | Q10: https://doi.org/10.60541/ethb-2t35 | R10: us_lawatlas_covid19_state_emergency_declarations
A11: Cyanobacterial HAB Monitoring using Satellite Imagery for the United States Great Lakes region created by the NOAA Harmful Algal Bloom Forecasting Branch (HAB-F) from 2000 to 2024 (NCEI Accession 0312614) | B11: NOAA NCEI | D11: US Great Lakes (Erie, Sandusky Bay, Saginaw Bay, Green Bay, Winnebago) | E11: raster | F11: 2000-06-01 to 2024-11-15 (July-October blooms) | G11: 2024 | H11: open | I11: CC0 1.0 Universal | J11: open_download (HTTPS) | K11: csv; geotiff | O11: Silver | Q11: https://doi.org/10.25921/wzk1-r208 | R11: us_noaa_ncei_greatlakes_cyano_hab_satellite
A12: Data and Materials for: Statewide Intensification of Harmful Algal Blooms Across California Lakes and Reservoirs | B12: Mendeley Data (paper supplement) | D12: California lakes and reservoirs | F12: years not stated (published 2026-03-16) | H12: open | I12: CC BY 4.0 | J12: open_download ("Download All") | K12: not listed on page (shapefiles in description) | O12: Silver | Q12: https://doi.org/10.17632/66dm3vs3g2 | R12: us_mendeley_california_lakes_hab_intensification
A13: Daytime surface urban heat island intensity across 6022 global cities in summer 2019 | B13: Zenodo deposit | D13: 6,022 cities worldwide | E13: point | F13: summer 2019 (single season) | G13: 2019 | H13: open | I13: CC BY 4.0 | J13: open_download | K13: xlsx with coordinates | O13: Gold | Q13: https://doi.org/10.5281/zenodo.17644686 | R13: global_zenodo_daytime_suhi_6022_cities_2019
A14: Electronic Cigarette Laws | B14: Center for Public Health Law Research (Temple University; LawAtlas) | D14: US (50 states + DC) | E14: state | F14: 2016-08-01 to 2017-08-01 | G14: 2017 | J14: registration | K14: not stated | O14: Silver | Q14: https://doi.org/10.60541/rq4m-pk67 | R14: us_lawatlas_e_cigarette_laws
A15: ERA5-Land weekly: Air temperature at 2 meter above surface, weekly time series for Europe at 1 km resolution (2016 - 2020) | B15: Zenodo deposit (OpenGeoHub) | D15: Europe (EPSG:3035) | E15: grid_1km | F15: 2016-01-01 to 2020-12-31, weekly | G15: 2020 | H15: open | I15: CC BY-SA 4.0 | J15: open_download | K15: geotiff | O15: Gold | Q15: https://doi.org/10.5281/zenodo.6559121 | R15: eu_zenodo_era5land_weekly_air_temperature_1km
A16: Experimental Harmful Algal Bloom (HAB) bulletin forecast products and associated satellite imagery from Lake Erie from 2008-09-04 to 2016-11-01 created by the NOAA National Centers for Coastal Ocean Science | B16: NOAA NCEI / NOS | D16: Lake Erie | E16: raster | F16: 2008-09-04 to 2016-11-01 | G16: 2016 | H16: open | I16: public domain (US Government work, 17 U.S.C. 105; federal rule applied) | J16: open_download (OneStop / NCEI browse; other options by contacting NCEI) | K16: geotiff; pdf | O16: Silver | Q16: https://doi.org/10.25921/q053-h813 | R16: us_noaa_ncei_lake_erie_hab_bulletin_experimental
A17: Global 0.05° daily mean land surface temperature product (2001-2023) | B17: Zenodo deposit | D17: global | E17: grid_0.05deg | F17: 2001-2023 in this record (1981-2000 is a separate record) | G17: 2023 | H17: open | I17: CC BY 4.0 | J17: open_download (per-year RAR archives, 29.3 GB) | K17: RAR archives; inner format not stated | O17: Gold | Q17: https://doi.org/10.5281/zenodo.15187724 | R17: global_zenodo_lst_005deg_daily_2001_2023
A18: Global Gridded Relative Deprivation Index (GRDI), Version 1 | B18: NASA SEDAC (CIESIN, Columbia University) | D18: global (30 arc-second pixels) | E18: grid_1km | F18: 2010-2020 | G18: 2020 | H18: open | I18: CC BY 4.0 | J18: open_download | K18: geotiff (zip) | O18: Gold | Q18: https://doi.org/10.7910/dvn/vosv99 | R18: global_ciesin_grdi_v1
A19: Global High Resolution Daily Urban Extreme Heat Exposure (UHE-Daily), 1983 - 2016 | B19: NASA SEDAC (CIESIN, Columbia University) | D19: global (>10,000 urban settlements) | E19: polygon | F19: 1983-01-01 to 2016-12-31, daily | G19: 2016 | H19: open | I19: "openly shared, without restriction" (EOSDIS Data Use and Citation Guidance) | J19: open_download (login not stated) | K19: shp; csv | O19: Silver | Q19: https://doi.org/10.7927/fq7g-ny13 | R19: global_sedac_uhe_daily_1983_2016
A20: Global Subnational Atlas of Poverty | B20: World Bank-derived panel (Harvard Dataverse deposit) | D20: global | E20: admin1 | F20: panel poverty rates; "version August 2022"; years not in the record metadata | H20: open | I20: CC0 1.0 | J20: open_download | K20: xlsx | O20: Silver | Q20: https://doi.org/10.7910/dvn/mlhfaf | R20: global_harvard_gsap_poverty_panel
A21: Good Samaritan Overdose Prevention Laws | B21: PDAPS | E21: state (50 states + DC code; no local) | F21: 2007-2023; effective dates: yes: per-state 'effective' and 'through' dates | I21: not stated on page; full pin citations behind paid subscription ($29/month) | J21: free account (web view); download not tested | O21: Silver | Q21: https://pdaps.org/datasets/good-samaritan-overdose-laws-1501695153 | R21: us_pdaps_good_samaritan_overdose_laws_1501695153
A22: GridEX: A Dataset for Assessing the Area-wide Extreme Heat and Cold (EHE/ECE) Exposure in the United States: 2008-2022 | B22: Harvard Dataverse deposit (GridEX; derived from NOAA ISD) | D22: United States | E22: tract | F22: 2008-2022 | G22: 2022 | H22: open | I22: CC0 1.0 | J22: open_download | K22: csv; rds; geotiff | O22: Gold | Q22: https://doi.org/10.7910/dvn/djgkdj | R22: us_gridex_extreme_heat_cold_events
A23: HadISDH.extremes: gridded global monthly land surface wet bulb and dry bulb temperature extremes index data version 1.0.0.2022f | B23: Met Office Hadley Centre / CEDA | D23: near-global land surface | E23: grid_5deg | F23: 1973-2022, monthly | G23: 2022 | H23: open | I23: Open Government Licence v3.0 | J23: open_download (web download; OPeNDAP) | K23: netcdf | O23: Silver | Q23: https://doi.org/10.5285/2d1613955e1b4cd1b156e5f3edbd7e66 | R23: gb_ceda_hadisdh_extremes
A24: Health Impact Assessment (HIA) Bills | B24: LawAtlas | E24: state (+DC/territories; 51 jurisdictions) | F24: 2012-01-01 to 2016-12-31; effective dates: yes: Valid From / Updated Through on page; per-law effective dates in the download (not checked) | I24: not stated on page; 'Data Licensing' link target 404 under /data-licensing | J24: free account required to download data/codebook | O24: Silver | Q24: https://lawatlas.org/datasets/hia-bills | R24: us_lawatlas_hia_bills
A25: Home Health Care - Zip Codes | B25: CMS Provider Data Catalog | E25: ZIP (agency service areas) | F25: current snapshot; catalog 'modified' 2026-10-22, next update 2027-01-20 | H25: public_domain_us_federal | I25: not stated in catalog metadata (federal open data; unverified) | J25: open_download (CSV via DKAN API) | O25: Silver | Q25: https://data.cms.gov/provider-data/dataset/m5eg-upu5 | R25: us_cms_pdc_m5eg_upu5
A26: Hospice - Zip Data | B26: CMS Provider Data Catalog | E26: ZIP (hospice service ZIPs) | F26: current snapshot; catalog 'modified' 2026-10-22, next update 2027-01-20 | H26: public_domain_us_federal | I26: not stated in catalog metadata (federal open data; unverified) | J26: open_download (CSV via DKAN API) | O26: Silver | Q26: https://data.cms.gov/provider-data/dataset/95rg-2usp | R26: us_cms_pdc_95rg_2usp
A27: Inpatient Rehabilitation Facility - General Information | B27: CMS Provider Data Catalog | E27: facility (address, ZIP) | F27: current snapshot; catalog 'modified' 2026-10-22, next update 2027-01-20 | H27: public_domain_us_federal | I27: not stated in catalog metadata (federal open data; unverified) | J27: open_download (CSV via DKAN API) | O27: Silver | Q27: https://data.cms.gov/provider-data/dataset/7t8x-u3ir | R27: us_cms_pdc_7t8x_u3ir
A28: Legal Landscape of Gabapentin Drug Scheduling and Required Prescription Drug Monitoring | B28: Center for Public Health Law Research (Temple University; LawAtlas) | D28: US (50 states + DC) | E28: state | F28: 2016-01-01 to 2024-12-31 | G28: 2024 | J28: registration | K28: not stated | O28: Silver | Q28: https://doi.org/10.60541/fe0h-sx30 | R28: us_lawatlas_gabapentin_scheduling_pdmp_laws
A29: Local Eviction Laws | B29: LawAtlas | E29: city (30 cities) | F29: 2021-01-01 (single date); effective dates: yes: Valid From / Updated Through on page; per-law effective dates in the download (not checked) | I29: not stated on page; 'Data Licensing' link target 404 under /data-licensing | J29: free account required to download data/codebook | O29: Silver | Q29: https://lawatlas.org/datasets/local-eviction-laws | R29: us_lawatlas_local_eviction_laws
A30: Long-Term Care Hospital - General Information | B30: CMS Provider Data Catalog | E30: facility (address, ZIP) | F30: current snapshot; catalog 'modified' 2026-10-22, next update 2027-01-20 | H30: public_domain_us_federal | I30: not stated in catalog metadata (federal open data; unverified) | J30: open_download (CSV via DKAN API) | O30: Silver | Q30: https://data.cms.gov/provider-data/dataset/azum-44iv | R30: us_cms_pdc_azum_44iv
A31: MODIS/Terra Land Surface Temperature/Emissivity Daily L3 Global 1km SIN Grid V061 | B31: NASA LP DAAC | D31: global (sinusoidal tiles) | E31: raster | F31: 2000-02-24 to present, daily | G31: 2026 | H31: open | I31: "openly shared, without restriction" (EOSDIS Data Use and Citation Guidance) | J31: open_download (login not stated; cloud-enabled) | K31: HDF-EOS2 (.hdf) | O31: Silver | Q31: https://doi.org/10.5067/modis/mod11a1.061 | R31: global_nasa_mod11a1_v061
A32: Naloxone Overdose Prevention Laws | B32: PDAPS | E32: state (50 states + DC code; no local) | F32: 2001-2022; effective dates: yes: per-state 'effective' and 'through' dates | I32: not stated on page; full pin citations behind paid subscription ($29/month) | J32: free account (web view); download not tested | O32: Silver | Q32: https://pdaps.org/datasets/laws-regulating-administration-of-naloxone-1501695139 | R32: us_pdaps_laws_regulating_administration_of_naloxone_1501695
A33: National Multidimensional Poverty Index | B33: NITI Aayog (via Climateverse India) | D33: India (state and district) | E33: admin2 | F33: 2015-2023 | G33: 2023 | H33: open | I33: CC0 1.0 | J33: record lists only codebook.json/codebook.md; data files not listed | K33: codebook only (json; md) | O33: Silver | Q33: https://doi.org/10.71646/ljsccn | R33: in_climateverse_national_mpi_state_district
A34: National Poverty Line - Subnational Poverty | B34: The World Bank | D34: world (national poverty lines) | E34: admin1 | F34: 1992-2016, annual | G34: 2016 | H34: open | I34: CC BY 4.0 | J34: open_download (via Databank; CSV/Excel zip) | K34: csv; xlsx (zip) | O34: Gold | Q34: https://doi.org/10.57966/tk74-ep75 | R34: global_worldbank_national_poverty_line_subnational
A35: Neighborhood Deprivation Index for year 2010, using the 2010 census geographic boundaries | B35: CEHI Data Hub | D35: USA (all states) | E35: tract | F35: 2010 (single year) | G35: 2010 | J35: "Access Restriction: Not available"; login not stated | K35: csv | O35: Silver | Q35: https://doi.org/10.25614/ndi_2010_trt_allstates | R35: us_cehi_ndi_2010_tract
A36: NOAA nClimGrid-Daily Version 1 – Daily gridded temperature and precipitation for the Contiguous United States since 1951 | B36: NOAA NCEI | D36: contiguous US | E36: grid_5km | F36: 1951-01-01 to present, daily | G36: 2026 | H36: open | I36: public domain (US Government work, 17 U.S.C. 105; federal rule applied) | J36: open_download (direct, THREDDS, AWS S3) | K36: netcdf; csv | O36: Gold | Q36: https://doi.org/10.25921/c4gt-r169 | R36: us_noaa_nclimgrid_daily
A37: Poverty Mapping Project: Global Subnational Infant Mortality Rates | B37: CIESIN (Columbia University), Poverty Mapping Project | D37: global (country list in record) | E37: polygon | F37: 2000 (single year) | G37: 2000 | H37: open | I37: CC BY 4.0 | J37: open_download | K37: shp; grid; xls; tabular zip | O37: Silver | Q37: https://doi.org/10.7910/dvn/wtnahq | R37: global_ciesin_povmap_subnational_infant_mortality
A38: Poverty Mapping Project: Global Subnational Prevalence of Child Malnutrition | B38: CIESIN (Columbia University), Poverty Mapping Project | D38: global (country list in record) | E38: polygon | F38: 1990-2002 (most recent subnational year per country) | G38: 2002 | H38: open | I38: CC BY 4.0 | J38: open_download | K38: shp; grid; tabular zip | O38: Silver | Q38: https://doi.org/10.7910/dvn/0ljjoj | R38: global_ciesin_povmap_subnational_child_malnutrition
A39: Poverty Mapping Project: Small Area Estimates of Poverty and Inequality | B39: CIESIN (Columbia University), Poverty Mapping Project | D39: about twenty countries (record text) | E39: polygon | F39: 1990-2002 | G39: 2002 | H39: open | I39: CC BY 4.0 | J39: open_download | K39: shp; csv/tabular zip; centroid zip | O39: Silver | Q39: https://doi.org/10.7910/dvn/rkrw8q | R39: global_ciesin_povmap_small_area_poverty_inequality
A40: Prescription Drug Monitoring Program Laws: Reporting, Mandates & Access | B40: LawAtlas | E40: state (+DC/territories; 51 jurisdictions) | F40: 2014-01-01 to 2023-12-31; effective dates: yes: Valid From / Updated Through on page; per-law effective dates in the download (not checked) | I40: not stated on page; 'Data Licensing' link target 404 under /data-licensing | J40: free account required to download data/codebook | O40: Silver | Q40: https://lawatlas.org/datasets/prescription-drug-monitoring-program-laws-reporting-mandates-access-2014-2023 | R40: us_lawatlas_prescription_drug_monitoring_program_laws_reportin
A41: Prescription Drug Monitoring Program Laws: Reporting, Mandates & Access, 2014-2019 | B41: PDAPS | E41: state (50 states + DC code; no local) | F41: 2014-2019; effective dates: yes: per-state 'effective' and 'through' dates | I41: not stated on page; full pin citations behind paid subscription ($29/month) | J41: free account (web view); download not tested | O41: Silver | Q41: https://pdaps.org/datasets/pdmp-mandates | R41: us_pdaps_pdmp_mandates
A42: Prescription Drug Monitoring Program Laws: Reporting, Mandates & Access, 2014-2023 | B42: Center for Public Health Law Research (Temple University; LawAtlas) | D42: US (50 states + DC) | E42: state | F42: 2014-01-01 to 2023-12-31 (updated through) | G42: 2023 | J42: registration | K42: not stated | O42: Silver | Q42: https://doi.org/10.60541/235t-fj52 | R42: us_lawatlas_pdmp_laws_2014_2023
A43: Small-area Deprivation Measure for Brazil: Data Documentation | B43: University of Glasgow (research data) | D43: Brazil (310,120 census sectors; 303,218 scored) | E43: small_area | F43: based on the 2010 Brazilian Population Census | G43: 2010 | H43: open | I43: CC BY 4.0 | J43: open_download ("Anyone") | K43: csv (108 MB); pdf documentation | O43: Gold | Q43: https://doi.org/10.5525/gla.researchdata.980 | R43: br_glasgow_small_area_deprivation_2010
A44: State HIV Criminalization Laws | B44: LawAtlas | E44: state (+DC/territories; 52 jurisdictions) | F44: 2023-08-31 to 2024-12-31; effective dates: yes: Valid From / Updated Through on page; per-law effective dates in the download (not checked) | I44: not stated on page; 'Data Licensing' link target 404 under /data-licensing | J44: free account required to download data/codebook | O44: Silver | Q44: https://lawatlas.org/datasets/state-hiv-criminalization-laws | R44: us_lawatlas_state_hiv_criminalization_laws
A45: State HIV Laboratory Reporting Laws | B45: LawAtlas | E45: state (+DC/territories; 53 jurisdictions) | F45: 2023-11-30 to 2025-04-01; effective dates: yes: Valid From / Updated Through on page; per-law effective dates in the download (not checked) | I45: not stated on page; 'Data Licensing' link target 404 under /data-licensing | J45: free account required to download data/codebook | O45: Silver | Q45: https://lawatlas.org/datasets/state-laboratory-reporting-laws | R45: us_lawatlas_state_laboratory_reporting_laws
A46: State HIV/STI Minors' Consent Laws | B46: LawAtlas | E46: state (+DC/territories; 52 jurisdictions) | F46: 2022-05-31 to 2024-12-31; effective dates: yes: Valid From / Updated Through on page; per-law effective dates in the download (not checked) | I46: not stated on page; 'Data Licensing' link target 404 under /data-licensing | J46: free account required to download data/codebook | O46: Silver | Q46: https://lawatlas.org/datasets/state-minors-consent-laws | R46: us_lawatlas_state_minors_consent_laws
A47: State Laws Limiting Prescriptions for Opioid Analgesics | B47: PDAPS | E47: state (50 states + DC code; no local) | F47: 2014-2019; effective dates: yes: per-state 'effective' and 'through' dates | I47: not stated on page; full pin citations behind paid subscription ($29/month) | J47: free account (web view); download not tested | O47: Silver | Q47: https://pdaps.org/datasets/opioid-analgesics-prescribing-limits | R47: us_pdaps_opioid_analgesics_prescribing_limits
A48: State Minimum Wage Laws | B48: LawAtlas | E48: state (+DC/territories; 25 jurisdictions) | F48: 2010-01-01 to 2023-04-15; effective dates: yes: Valid From / Updated Through on page; per-law effective dates in the download (not checked) | I48: not stated on page; 'Data Licensing' link target 404 under /data-licensing | J48: free account required to download data/codebook | O48: Silver | Q48: https://lawatlas.org/datasets/state-minimum-wage-laws | R48: us_lawatlas_state_minimum_wage_laws
A49: State Perinatal HIV Testing Laws | B49: LawAtlas | E49: state (+DC/territories; 52 jurisdictions) | F49: 2019-01-01 to 2025-04-01; effective dates: yes: Valid From / Updated Through on page; per-law effective dates in the download (not checked) | I49: not stated on page; 'Data Licensing' link target 404 under /data-licensing | J49: free account required to download data/codebook | O49: Silver | Q49: https://lawatlas.org/datasets/state-perinatal-hiv-testing-laws | R49: us_lawatlas_state_perinatal_hiv_testing_laws
A50: State Syringe Access Laws | B50: Center for Public Health Law Research (Temple University; LawAtlas) | D50: US (50 states + DC) | E50: state | F50: 2010-01-01 to 2024-06-01 | G50: 2024 | J50: registration | K50: not stated | O50: Silver | Q50: https://doi.org/10.60541/kshg-k144 | R50: us_lawatlas_state_syringe_access_laws
A51: Statutory and Constitutional Right to Abortion | B51: Center for Public Health Law Research (Temple University; LawAtlas) | D51: US (50 states + DC) | E51: state | F51: 2018-12-01 to 2022-11-01 | G51: 2022 | J51: registration | K51: not stated | O51: Silver | Q51: https://doi.org/10.60541/26gc-yv35 | R51: us_lawatlas_right_to_abortion_laws
A52: Syringe Services Programs Laws | B52: PDAPS | E52: state (50 states + DC code; no local) | F52: 2019-2021; effective dates: yes: per-state 'effective' and 'through' dates | I52: not stated on page; full pin citations behind paid subscription ($29/month) | J52: free account (web view); download not tested | O52: Silver | Q52: https://pdaps.org/datasets/syringe-services-programs-laws | R52: us_pdaps_syringe_services_programs_laws
A53: Tobacco Pricing Strategies | B53: Center for Public Health Law Research (Temple University; LawAtlas) | D53: US (50 states + DC) | E53: state | F53: 2019-09-01 (single date) | G53: 2019 | J53: registration | K53: not stated | O53: Silver | Q53: https://doi.org/10.60541/tq0g-2c27 | R53: us_lawatlas_tobacco_pricing_strategies
A54: Veterans Health Administration Provider Level Data | B54: CMS Provider Data Catalog | E54: facility/provider (VA; quality measures) | F54: current snapshot; catalog 'modified' 2026-10-22, next update 2027-01-20 | H54: public_domain_us_federal | I54: not stated in catalog metadata (federal open data; unverified) | J54: open_download (CSV via DKAN API) | O54: Silver | Q54: https://data.cms.gov/provider-data/dataset/uyx4-5s7f | R54: us_cms_pdc_uyx4_5s7f
A55: Yearly Occupational Heat Exposure by Census Tract, County, State, and Nationwide in the Contiguous US, 2010-2019 | B55: Zenodo deposit | D55: contiguous US (no AK, HI) | E55: tract | F55: 2010-2019, yearly | G55: 2019 | H55: open | I55: CC BY 4.0 | J55: open_download | K55: zip (contents not stated) | O55: Gold | Q55: https://doi.org/10.5281/zenodo.15199025 | R55: us_zenodo_occupational_heat_exposure_tract
A56: EPA AirData: AQS site listing (aqs_sites.zip) and monitor listing (aqs_monitors.zip) | B56: US EPA | C56: air quality | D56: US | E56: point | F56: current listing (updated twice a year) | H56: public_domain_us_federal | J56: open_download | K56: csv (zip) | L56: Joins today | M56: 3 | O56: Silver | P56: 86 | Q56: https://aqs.epa.gov/aqsweb/airdata/download_files.html | R56: us_epa_aqs_sites_monitors
A57: Cartographic Boundary Files | B57: U.S. Census Bureau | C57: boundaries | D57: US nation-based and state-based files (state FIPS 01-78, national file 99); Puerto Rico referenced (FIPS 72 subbarrios) | E57: block_group | F57: 1990; 2000; 2010; 2013-2018 on this page; 2019 and later on the new Cartographic Boundary File page (description page lists entity-description PDFs for each year 2013-2025) | G57: 2025 | H57: public_domain_us_federal | J57: open_download | K57: shp; kml | L57: Joins today | M57: 3 | O57: Gold | P57: 98 | Q57: https://www.census.gov/geographies/mapping-files/time-series/geo/carto-boundary-file.html | R57: us_census_cartographic_boundary
A58: 2021 Census Boundary Files | B58: Statistics Canada | C58: boundaries | D58: Canada (layers from provinces/territories down to dissemination blocks; not stated in words) | E58: block | F58: 2021 Census (single vintage); temporal coverage '2021-01-01 to undefined'; published 2022-02-01, record modified 2024-02-15 | G58: 2021 | H58: open | I58: Open Government Licence - Canada | J58: open_download | K58: shp; gdb (FGDB); gml; esri rest; wms; zip (relationship file); pdf/html (reference guides) | L58: Joins today | M58: 1 | O58: Silver | P58: 93 | Q58: https://open.canada.ca/data/dataset/ef70dc3b-1069-4037-9bce-61f47e628a1d | R58: ca_statcan_census_boundary_files_2021
A59: Australian Statistical Geography Standard (ASGS) Edition 3 digital boundary files | B59: Australian Bureau of Statistics (ABS) | C59: boundaries | D59: Geographic Australia (bounding box N -8, S -45, W 96, E 169; Other Territories coded 9) | E59: block | F59: Edition 3, July 2021 - June 2026 (Main Structure released 20/07/2021; Non ABS Structures 6 Oct 2021; SUA 5 Oct 2022; Remoteness 21 Mar 2023; LGA 2025 files updated 21/07/2026) | G59: 2025 | H59: open | I59: CC BY 4.0 (Creative Commons Attribution 4.0 International) | J59: open_download | K59: gpkg; shp (zip archives, GDA2020 and GDA94 sets, with ISO 19115 XML metadata) | L59: Joins today | M59: 1 | O59: Silver | P59: 91 | Q59: https://www.abs.gov.au/statistics/standards/australian-statistical-geography-standard-asgs-edition-3/jul2021-jun2026/access-and-downloads/digital-boundary-files | R59: au_abs_asgs_boundaries
A60: Boundary-Line | B60: Ordnance Survey | C60: boundaries | D60: Great Britain | E60: postcode_small_area | F60: current product, updated twice a year; no vintage year stated (historic county boundaries 'from as far back as the late 19th Century') | G60: 2026 | H60: unknown | J60: open_download | K60: shp; gpkg; gml; tab (MapInfo); vector tiles | L60: Joins today | M60: 1 | O60: Silver | P60: 92 | Q60: https://www.ordnancesurvey.co.uk/products/boundary-line | R60: gb_os_boundary_line
A61: Cartografia digitalizada de secciones censales | B61: Instituto Nacional de Estadistica (INE) | C61: boundaries | D61: ES (national files; callejero per province incl. Ceuta and Melilla) | E61: polygon (seccion censal; small statistical area) | F61: annual vintages 2001, 2003-2025 (2002 absent) | G61: 2025 | H61: open | I61: CC BY-SA 4.0 (footer text: 'Este sitio web y su contenido estan bajo licencia CC BY-SA 4.0'); footer link points to CC BY 4.0 | J61: open_download | K61: shp; WMS; WFS; OGC API Features | L61: Joins today | M61: 1 | O61: Gold | P61: 98 | Q61: https://www.ine.es/ss/Satellite?L=es_ES&c=Page&cid=1259952026632&p=1259952026632&pagename=ProductosYServicios%2FPYSLayout | R61: es_ine_secciones_censales
A62: Census code lists: 2020 Census county FIPS codes | B62: U.S. Census Bureau | C62: boundaries | D62: county table coverage not explicit; companion state table: states, DC, Puerto Rico and Insular Areas | E62: county | F62: 2020 (also a 2010 vintage tab) | G62: 2020 | H62: public_domain_us_federal | J62: open_download | K62: txt (state file link is .txt; county file format not shown on the extracted page) | L62: Joins today | M62: 1 | N62: us_2020_census_county_fips | O62: Gold | P62: 98 | Q62: https://www.census.gov/library/reference/code-lists.html | R62: us_census_county_fips_codes
A63: Census Geocoder (Geocoding Services API) | B63: U.S. Census Bureau | C63: boundaries | D63: United States, Puerto Rico and the U.S. Island Areas | E63: point | F63: ongoing ('Current' benchmark always exists; benchmarks Current / ACS#### / Census####) | G63: 2026 | H63: public_domain_us_federal | J63: api | K63: json/jsonp (single record); csv (batch output); batch input csv/txt/dat/xls/xlsx | L63: Needs a count/distance step | M63: 1 | O63: Silver | P63: 91 | Q63: https://geocoding.geo.census.gov/geocoder/ | R63: us_census_geocoder
A64: Demografiska statistikomraden (DeSO) | B64: Statistiska centralbyran (SCB) | C64: boundaries | D64: Sweden (nationwide) | E64: polygon (DeSO small statistical area; county and municipality as attributes) | F64: DeSO 2018 and DeSO 2025 versions; DeSO 2025 boundaries valid from 2025-01-01; all statistics published in 2025 use DeSO 2025 | G64: 2025 | H64: open | I64: CC0 (Statistics Sweden open data terms page, linked from the DeSO page as the usage terms for open geodata) | J64: open_download | K64: gpkg (via WFS GetFeature); wms; wfs; xlsx (historical changes 2018-2025, DeSO-RegSO connection table) | L64: Joins today | M64: 1 | O64: Gold | P64: 98 | Q64: https://www.scb.se/en/services/open-data-api/open-geodata/open-data-for-deso--demographic-statistical-areas/ | R64: se_scb_deso
A65: Frontier and Remote Area (FAR) Codes | B65: U.S. Department of Agriculture | C65: boundaries | D65: US: 2010 and 2020 cover ZIP Codes and tracts in the 50 states and DC; 2000 covers contiguous US ZIP Codes only | E65: tract (ZIP Code and census tract tables); a grid_90m raster version of each 2020 FAR level is offered via the ERS Geospatial Resources page | F65: 2000, 2010 and 2020 vintages; 2020 vintage released March 2026 (page updated 3/13/2026) | G65: 2020 | H65: public_domain_us_federal | J65: open_download | K65: xlsx; xls; zip; pdf (landing page); shapefile and grid for 2020 via ERS Geospatial Resources (page not read) | L65: Needs raster support | M65: 1 | O65: Silver | P65: 84 | Q65: http://www.ers.usda.gov/data-products/frontier-and-remote-area-codes | R65: us_usda_ers_far_codes
A66: GADM (Database of Global Administrative Areas) | B66: GADM | C66: boundaries | D66: global (by country, or the whole world as one download) | E66: postcode_small_area | G66: 2026 | H66: non-commercial | I66: custom terms: free for academic and other non-commercial use; redistribution or commercial use not allowed without prior permission | J66: open_download | K66: gpkg; shp; geojson; kmz (some zipped); R via the geodata package (no rds file listed) | L66: Joins today | M66: 1 | O66: Silver | P66: 75 | Q66: https://gadm.org/data.html | R66: global_gadm_boundaries
A67: geoBoundaries (Global Database of Political Administrative Boundaries) | B67: William & Mary geoLab | C67: boundaries | D67: global (over 200 entities including all UN member states; about 1 million boundaries) | E67: admin5 (ADM0-ADM5) | F67: boundaries tracked since 2016; archived releases 1.3.3 (Aug 2018) to 5.0.0 (Dec 19, 2022); a 'current' release served by the API without a version number | G67: 2022 | H67: open | I67: CC BY 4.0 (gbOpen release); gbHumanitarian (UN OCHA mirror) may be less open; gbAuthoritative (UN SALB mirror) not for commercial use | J67: api; open_download | K67: geojson; topojson; simplified geojson; aggregate zip; shapefile mentioned in the API introduction | L67: Joins today | M67: 1 | O67: Silver | P67: 85 | Q67: https://www.geoboundaries.org/ | R67: global_geoboundaries
A68: Geographic Relationship Files (incl. 2010-2020 tract/block comparability) | B68: U.S. Census Bureau | C68: boundaries | D68: partly: 2024 files are 'for the state of Connecticut only'; coverage of the 2000-2020 files not readable (tab content not rendered) | E68: block (2020 Census Block Relationship Files and 2010 Census Block Relationship Files listed in the record-layout index); 2024 files are CD/SLD to county | F68: tabs for 2000, 2010, 2020, 2022, 2023, 2024; page last revised November 21, 2024; only the 2024 tab (ACS24 Connecticut files) was readable | G68: 2024 | H68: public_domain_us_federal | J68: open_download | K68: txt (2024 files, each under 1 MB, on www2.census.gov); delimiter not stated | L68: Joins today | M68: 1 | O68: Gold | P68: 93 | Q68: https://www.census.gov/geographies/reference-files/time-series/geo/relationship-files.html | R68: us_census_relationship_files
A69: GeoNames geographical database | B69: GeoNames (unxos gmbh) | C69: boundaries | D69: global (allCountries.zip combines all countries; per-country files for each ISO code plus no-country) | E69: point | F69: ongoing (daily database extract; modifications-<date>.txt and deletes-<date>.txt change files); no start year stated | G69: 2026 | H69: open | I69: CC BY 4.0 | J69: open_download | K69: tab-delimited txt (utf8) with lat/lon; REST web services (API) | L69: Needs a count/distance step | M69: 1 | O69: Silver | P69: 92 | Q69: https://www.geonames.org/export/ | R69: global_geonames
A70: GeoNames postal codes | B70: GeoNames (unxos gmbh) | C70: boundaries | D70: about 120 countries; partial codes only for CL, CN, IE, MT, AR, BR; CA/NL/UK full codes in separate *_full.csv.zip files | E70: point | F70: daily dumps | G70: current | H70: open | I70: CC BY 4.0 | J70: open_download | K70: tab-delimited txt (utf8) with lat/lon | L70: Needs a count/distance step | M70: 1 | O70: Silver | P70: 95 | Q70: https://www.geonames.org/export/ | R70: global_geonames_postal_codes
A71: Global Administrative Unit Layers (GAUL) | B71: Food and Agriculture Organization of the United Nations | C71: boundaries | D71: global (place keyword World; bbox -180/180, -90/90) | E71: admin2 | F71: 2024 edition (temporal extent 2024-01-01 to 2024-12-31); published 2024-12-19, last updated 2025-07-29 | G71: 2024 | H71: open | I71: CC BY 4.0 (catalog record; separate Terms of Use PDF must be read) | J71: open_download | K71: shp; csv (codelist); WMS | L71: Joins today | M71: 1 | O71: Gold | P71: 93 | Q71: https://www.fao.org/hih-geospatial-platform/news/detail/now-available--the-global-administrative-unit-layers-(gaul)-dataset---2024-edition/en | R71: global_fao_gaul
A72: Local administrative units (LAU) - GISCO geodata | B72: Eurostat | C72: boundaries | D72: EU;EFTA;candidate countries | E72: admin3 | F72: 2011-2024 annual (years 2011 through 2024 in the download selector) | G72: 2024 | H72: non-commercial | I72: custom terms: GISCO download rules (must be accepted); non-exclusive, non-transferable right to use; not for commercial purposes (contact EuroGeographics for commercial use); source acknowledged: '(c) EuroGeographics for the administrative boundaries' | J72: open_download | K72: gpkg; shp; topojson; geojson; pbf; svg | L72: Joins today | M72: 1 | O72: Silver | P72: 84 | Q72: https://ec.europa.eu/eurostat/web/gisco/geodata/statistical-units/local-administrative-units | R72: eu_eurostat_gisco_lau
A73: NCHS Urban-Rural Classification Scheme for Counties | B73: Centers for Disease Control and Prevention | C73: boundaries | D73: US, 3,144 counties and county equivalents (incl. Connecticut planning regions); territories excluded | E73: county | F73: scheme vintages 1990, 2006, 2013, 2023; 2023 scheme (2022 population estimates) re-released September 2026 | G73: 2023 | H73: public_domain_us_federal | J73: open_download | K73: csv; sas7bdat; xlsx (2013); pdf (docs) | L73: Joins today | M73: 1 | O73: Gold | P73: 93 | Q73: https://www.cdc.gov/nchs/data_access/urban_rural.htm | R73: us_cdc_nchs_urban_rural
A74: OpenAddresses | B74: OpenAddresses | C74: boundaries | D74: global ('data from the whole world'; per-source) | E74: address | H74: attribution | I74: per-source open licences; 'Most sources only require attribution' | J74: open_download | K74: csv;geojson | L74: Needs a count/distance step | M74: 1 | O74: Silver | P74: 97 | Q74: https://openaddresses.io/ | R74: global_openaddresses
A75: Postal codes point dataset and postal code to NUTS correspondence (Tercet) | B75: Eurostat | C75: boundaries | D75: EU, EFTA and candidate countries | E75: point | F75: editions 2020 and 2024 | G75: 2024 | H75: open | I75: CC BY-SA 4.0 (required acknowledgement: '(c) European Union - GISCO, 2024, postal code point dataset, Licence CC-BY-SA 4.0') | J75: open_download | K75: gpkg; shp; csv | L75: Needs a count/distance step | M75: 1 | O75: Gold | P75: 98 | Q75: https://ec.europa.eu/eurostat/web/gisco/geodata/administrative-units/postal-codes | R75: eu_eurostat_gisco_postal_codes
A76: Qualified Opportunity Zones (designated census tracts) | B76: U.S. Department of the Treasury | C76: boundaries | D76: US states (each State nominated eligible tracts) and Puerto Rico; DC/territories not explicitly listed | E76: tract | F76: 2018 designations (list updated 2018-12-14; 'these designations are final'); new designation cycle opened 2026-07-01 | G76: 2018 | H76: public_domain_us_federal | J76: open_download | K76: xlsx; shp (zip); xlsb; web map (CIMS); pdf | L76: Joins today | M76: 1 | O76: Gold | P76: 92 | Q76: https://www.cdfifund.gov/opportunity-zones | R76: us_treasury_opportunity_zones
A77: Radios censales (cartografia censal) - Censo 2022 / 2010 | B77: Instituto Nacional de Estadistica y Censos (INDEC) | C77: boundaries | D77: not stated; hosted on Buenos Aires province portal, publisher INDEC | E77: polygon (radio censal, census enumeration area) | F77: 2010 and 2022 census cartography (resources for both censuses) | G77: 2022 | H77: open | I77: CC BY-SA 4.0 (INDEC site footer, all site material unless marked); CC BY 4.0 (GBA open-data catalog dataset page) | J77: open_download | K77: csv; shp; geojson; kml; pdf (definitions) | L77: Joins today | M77: 1 | O77: Silver | P77: 89 | Q77: https://www.indec.gob.ar/indec/web/Institucional-Indec-Codgeo | R77: ar_indec_radios_censales
A78: Rural-Urban Commuting Area Codes (RUCA) | B78: U.S. Department of Agriculture | C78: boundaries | D78: US and its territories (Puerto Rico added 2010, other territories 2020) | E78: tract | F78: 1990, 2000, 2010, 2020 tract versions (not directly comparable); ZIP version 2010 and 2020 (2020 ZIP file uses June 2024 ZIP boundaries) | G78: 2020 | H78: public_domain_us_federal | J78: open_download | K78: xlsx; csv; xls (older vintages); pdf (classification examples) | L78: Joins today | M78: 1 | O78: Gold | P78: 91 | Q78: http://www.ers.usda.gov/data-products/rural-urban-commuting-area-codes | R78: us_usda_ers_ruca
A79: Rural-Urban Continuum Codes (RUCC) | B79: U.S. Department of Agriculture | C79: boundaries | D79: US (3,144 counties/equivalents in 50 states + DC) plus 89 county equivalents in PR, American Samoa, Guam, Northern Mariana Islands, US Virgin Islands (3,235 total, 2023) | E79: county | F79: 1974, 1983, 1993, 2003, 2013, 2023 (updated each decade since 1983) | G79: 2023 | H79: public_domain_us_federal | J79: open_download | K79: xlsx; csv (2023); xls (older vintages) | L79: Joins today | M79: 1 | O79: Gold | P79: 91 | Q79: http://www.ers.usda.gov/data-products/rural-urban-continuum-codes | R79: us_usda_ers_rucc
A80: Second Administrative Level Boundaries (SALB) | B80: United Nations | C80: boundaries | D80: aims at all UN Member States; data listing shows 197 Member States, but every visible row shows 'Geospatial Datasets: None' | E80: admin2 | F80: through time (historical tables) | H80: unknown | I80: UN copyright ('Copyright of the SALB Data (including codes, historical tables, and geospatial data) is vested in the United Nations'); Terms of Contribution and Terms of Use referenced under Methodology, not read | J80: open_download (historical XLSX tables for some countries only; no geospatial download seen) | K80: xlsx (historical change tables) | L80: Unknown | M80: 1 | O80: Silver | P80: 71 | Q80: https://salb.un.org/en | R80: global_un_salb
A81: Stats NZ Geographic Data Service (boundaries) | B81: Stats NZ | C81: boundaries | D81: New Zealand (including oceanic areas) | E81: polygon (SA2; plus grid_250m population grid); meshblock/SA1 layers not seen | F81: current boundary vintages 2025 and 2026 listed (SA2 2026 as at 1 January 2026); series since 2018 not shown | G81: 2026 | H81: open | I81: CC BY 4.0 (Creative Commons Attribution 4.0 International; commercial use allowed, attribution required) | J81: open_download (Koordinates export; login prompts present, requirement not stated) | K81: not named on pages read (Koordinates export 'in a specific file format and projection') | L81: Joins today | M81: 1 | O81: Silver | P81: 81 | Q81: https://datafinder.stats.govt.nz/ | R81: nz_statsnz_geographic_data_service
A82: Tanzania 2022 Population and Housing Census boundaries (regions, districts; Magu District) | B82: Tanzania National Bureau of Statistics | C82: boundaries | D82: Tanzania | E82: admin2 (region and district confirmed; ward, village/mtaa and EA levels described as planned in text carried over from the 2012 release) | F82: 2022 Census (page header 'Tanzania, 2020 - 2022'; reference ID TZA-NBS-PHC-2020-ShapeFilesv01; geodatabase dated 2024) | G82: 2022 | H82: registration | I82: custom terms of use (statistical and scientific research purposes only; no redistribution without written agreement; no re-identification; citation required; agreement implied by continuing to data retrieval) | J82: registration (terms must be accepted before retrieval; Register/Login links; direct ZIP links listed under related materials) | K82: shp (described as shapefile feature class); geodatabase package .mpkx in ZIP; PDF manual | L82: Unknown | M82: 1 | N82: tz_2022_nbs;tz_2022_nbs_magu_district | O82: Silver | P82: 74 | Q82: https://microdata.nbs.go.tz/index.php/catalog/49/related-materials | R82: tz_nbs_2022_census_boundaries
A83: The National Map (TNM) base layers | B83: USGS | C83: boundaries | D83: United States and its territories | E83: grid_ | F83: continuous | G83: current | H83: public_domain_us_federal | J83: open_download | K83: gdb; shp; geotiff; geopdf; web services; S3 | L83: Needs raster support | M83: 1 | O83: Silver | P83: 96 | Q83: https://www.usgs.gov/programs/national-geospatial-program/national-map | R83: us_usgs_national_map
A84: TIGER/Line Shapefiles | B84: U.S. Census Bureau | C84: boundaries | D84: US; PR; island areas | E84: block | F84: 1992-2026 vintages (shapefile 2007 to present; TIGER/Line ASCII 2006 and earlier; Census 2000 in both) | G84: 2026 | H84: public_domain_us_federal | J84: open_download | K84: shp (2007-present); TIGER/Line ASCII (2006 and earlier) | L84: Joins today | M84: 1 | N84: fl_2019_tl_tract;fl_2020_tl_tract;fl_2021_tl_tract;fl_2022_tl_cousub;fl_2022_tl_tract;fl_2023_tl_tract;fl_2024_tl_tract;fl_2025_tl_tract;us_2019_prisecroads_tl;us_2019_tract_tl | O84: Silver | P84: 97 | Q84: https://www.census.gov/geographies/mapping-files/time-series/geo/tiger-line-file.html | R84: us_census_tiger_line
A85: TIGER/Line Shapefiles - Counties | B85: U.S. Census Bureau | C85: boundaries | D85: US;PR;island areas | E85: county | F85: 1992-2026 (yearly vintages listed; 2026 boundaries as of January 1, 2026) | G85: 2026 | H85: public_domain_us_federal | J85: open_download | K85: shp (2007-present); TIGER/Line ASCII (2006 and earlier) | L85: Joins today | M85: 1 | N85: us_2019_county_tl;us_2020_county_tl;us_2022_county_tl;us_2023_county_tl | O85: Silver | P85: 97 | Q85: https://www.census.gov/geographies/mapping-files/time-series/geo/tiger-line-file.html | R85: us_census_tiger_line_county
A86: U.S. Gazetteer Files | B86: U.S. Census Bureau | C86: boundaries | D86: 50 states, DC and Puerto Rico; Island Areas not included (some school-district and legislative files cover fewer states) | E86: tract | F86: 1990, 2000, 2010, 2012-2026 (yearly vintages listed) | G86: 2026 | H86: public_domain_us_federal | J86: open_download | K86: pipe-delimited txt (zip), with GEOID and lat/lon | L86: Joins today | M86: 1 | O86: Gold | P86: 98 | Q86: https://www.census.gov/geographies/reference-files/time-series/geo/gazetteer-files.html | R86: us_census_gazetteer
A87: Urban and Rural Classification (2020 Census Urban Areas) | B87: U.S. Census Bureau | C87: boundaries | D87: U.S., Puerto Rico and Island Areas (block-level file: U.S. and Puerto Rico only) | E87: block | F87: 2010 and 2020 Census classifications (2000 and 1990 referenced); latest 2020 | G87: 2020 | H87: public_domain_us_federal | J87: open_download | K87: xlsx; xls; txt (block file with GEOID); shp (zip); geodatabase | L87: Joins today | M87: 1 | O87: Gold | P87: 98 | Q87: https://www.census.gov/programs-surveys/geography/guidance/geo-areas/urban-rural.html | R87: us_census_urban_rural
A88: Urban Influence Codes (UIC) | B88: U.S. Department of Agriculture | C88: boundaries | D88: 3,235 counties and county-equivalents in the 50 states, DC, Puerto Rico, American Samoa, Guam, Northern Mariana Islands and U.S. Virgin Islands | E88: county | F88: 1993, 2003, 2013, 2024 versions (2003 Puerto Rico file separate); latest 2024 | G88: 2024 | H88: public_domain_us_federal | J88: open_download | K88: xlsx; csv (2024); xls (2013, 2003, 1993) | L88: Joins today | M88: 1 | O88: Gold | P88: 91 | Q88: http://www.ers.usda.gov/data-products/urban-influence-codes | R88: us_usda_ers_uic
A89: Who's On First | B89: Who's On First (Geocode Earth; formerly Mapzen) | C89: boundaries | D89: global ('all the places in the world'; 219 countries, 26M records, 21M venues) | E89: point | H89: attribution | I89: per-source open licences (CC BY 3.0/4.0, CC0 1.0, Open Government Licence v2/v3, MPL 2.0, other government open-data licences); 'Crediting Who's On First is recommended and linking back to the License is required' | J89: open_download | K89: geojson; sqlite; bundled slices | L89: Joins today | M89: 1 | O89: Silver | P89: 87 | Q89: https://whosonfirst.org/ | R89: global_whos_on_first
A90: ZIP Code Tabulation Areas (ZCTAs) | B90: U.S. Census Bureau | C90: boundaries | D90: US (50 states, DC, PR); Island Areas excluded | E90: zcta | F90: Gazetteer vintages 1990, 2000, 2010, 2012-2026 (yearly); ZCTA file based on 2020 Census blocks | G90: 2026 | H90: public_domain_us_federal | J90: open_download | K90: pipe-delimited txt (zip) | L90: Joins today | M90: 1 | N90: mdc_2020_zcta;us_2020_zcta | O90: Gold | P90: 98 | Q90: https://www.census.gov/geographies/reference-files/time-series/geo/gazetteer-files.html | R90: us_census_zcta
A91: EnviroAtlas Community Data (block-group metrics for selected communities) | B91: US EPA | C91: built_environment | D91: US, 32 communities (e.g. Austin TX, Baltimore MD, Chicago IL, Los Angeles CA, New York NY, Phoenix AZ, Philadelphia PA, Washington DC) | E91: block_group | F91: Data years not stated; community releases dated Oct2019, Apr2020 (most communities), May2021 (Los Angeles), Mar2023 (San Diego, Tacoma); community spreadsheet dated 10/2/2023 | G91: 2023 | H91: public_domain_us_federal | J91: open_download | K91: gdb; csv; shp; geotiff; xlsx (download lists) | L91: Joins today | M91: 3 | O91: Silver | P91: 94 | Q91: https://www.epa.gov/enviroatlas/data-download | R91: us_epa_enviroatlas_community
A92: Indicators of Broadband Need map | B92: U.S. Department of Commerce | C92: built_environment | D92: US ('across the country'; tribal communities mentioned) | E92: block | F92: Release date June 17, 2021 only; source data years not stated | G92: 2021 | H92: public_domain_us_federal | J92: web map viewer only (no download or API described) | K92: web map (Esri Living Atlas layers) | L92: Joins today | M92: 3 | O92: Silver | P92: 86 | Q92: https://broadbandusa.ntia.gov/node/7522 | R92: us_ntia_indicators_broadband_need
A93: National Walkability Index | B93: EPA | C93: built_environment | D93: US ('every Census 2019 block group in the U.S.'); keywords include Puerto Rico and American Samoa; bounding box -180 to 180, 2.97 to 90 | E93: block_group | F93: DCAT temporal 2019-01-01 to open-ended (9999-01-01); issued and modified 2021-05-13; block groups from Census 2019; 2021 user guide | G93: 2021 | H93: open | I93: CC0 1.0 (https://creativecommons.org/publicdomain/zero/1.0/) | J93: open_download | K93: zip (contents not stated); csv; ArcGIS REST MapServer; html | L93: Joins today | M93: 3 | O93: Gold | P93: 95 | Q93: https://catalog.data.gov/dataset/walkability-index | R93: us_epa_national_walkability_index
A94: Overture Maps Foundation data releases | B94: Overture Maps Foundation | C94: built_environment | D94: global | E94: point | F94: Dated releases through at least 2026 (example path release/2026-10-21.0; STAC catalog 'always points to the latest release'); start year not stated | G94: 2026 | H94: open | I94: ODbL (base, buildings, divisions, transportation themes); places: per provider, mostly CDLA Permissive 2.0 (Foursquare Apache 2.0, AllThePlaces CC0 1.0); addresses: per-country permissive open licences (mostly CC BY 4.0, CC0, public domain) | J94: open_download | K94: geoparquet; geojson (export); pmtiles | L94: Needs a count/distance step | M94: 3 | O94: Silver | P94: 93 | Q94: https://docs.overturemaps.org/getting-data/ | R94: global_overture_maps
A95: Smart Location Database (SLD) | B95: EPA | C95: built_environment | D95: US (every census block group in the United States) | E95: block_group | F95: 2019 Census block group boundaries; V3 released Jan 2021 (data years of inputs not stated on the record) | G95: 2021 | H95: open | I95: CC0 1.0 (License field links to https://creativecommons.org/publicdomain/zero/1.0/) | J95: open_download | K95: zip (contents not described); csv; ArcGIS MapServer REST | L95: Joins today | M95: 3 | O95: Silver | P95: 96 | Q95: https://catalog.data.gov/dataset/smart-location-database | R95: us_epa_smart_location_database
A96: VIIRS/NPP Lunar BRDF-Adjusted Nighttime Lights Yearly L3 Global 15 arc second (VNP46A4) | B96: NASA | C96: built_environment | D96: global | E96: grid_15arcsec | F96: annual from 2012-01-01; end date not stated (availability chart did not load) | G96: 2023 | H96: public_domain_us_federal | J96: registration | K96: HDF5 (HDF-EOS5, .h5) | L96: Needs raster support | M96: 3 | N96: egom_2012_viirs_vnp46a4;egom_2013_viirs_vnp46a4;egom_2014_viirs_vnp46a4;egom_2015_viirs_vnp46a4;egom_2016_viirs_vnp46a4;egom_2017_viirs_vnp46a4;egom_2018_viirs_vnp46a4;egom_2019_viirs_vnp46a4;egom_2020_viirs_vnp46a4;egom_2021_viirs_vnp46a4;egom_2022_viirs_vnp46a4;egom_2023_viirs_vnp46a4;egom_2024_viirs_vnp46a4;mdc_2012_viirs_vnp46a4;mdc_2013_viirs_vnp46a4;mdc_2014_viirs_vnp46a4;mdc_2015_viirs_vnp46a4;mdc_2016_viirs_vnp46a4;mdc_2017_viirs_vnp46a4;mdc_2018_viirs_vnp46a4;mdc_2019_viirs_vnp46a4;mdc_2020_viirs_vnp46a4;mdc_2023_viirs_vnp46a4 | O96: Silver | P96: 87 | Q96: https://ladsweb.modaps.eosdis.nasa.gov/missions-and-measurements/products/VNP46A4/ | R96: global_nasa_viirs_vnp46a4
A97: Annual National Land Cover Database (Annual NLCD) | B97: USGS | C97: built_environment | D97: US (conterminous United States) | E97: grid_30m | F97: 1985-2025 annual | G97: 2025 | H97: open | I97: public domain; CC0 1.0 Universal (no use constraints) | J97: open_download | K97: raster (format not named); WMS | L97: Needs raster support | M97: 2 | N97: mdc_2021_nlcd_impervious_surfaces;mdc_2021_nlcd_land_cover | O97: Silver | P97: 89 | Q97: https://www.mrlc.gov/data | R97: us_usgs_nlcd_annual
A98: C-CAP Regional Land Cover and Change | B98: NOAA | C98: built_environment | D98: US coasts (coastal states) incl. Hawaii and Puerto Rico | E98: grid_30m | F98: 1975-2021 (epochs 1975, 1985, 1992, 1996, 2001, 2006, 2010, 2016, 2021; HI 1992/2001/2005; PR 2010) | G98: 2021 | H98: public_domain_us_federal | J98: open_download | K98: raster (format not named); shp (mapping boundary); xlsx (change data); ArcGIS ImageServer | L98: Needs raster support | M98: 2 | O98: Gold | P98: 93 | Q98: https://coast.noaa.gov/digitalcoast/data/ccapregional.html | R98: us_noaa_ccap_land_cover
A99: County Business Patterns | B99: U.S. Census Bureau | C99: built_environment | D99: US (U.S., state, county, metro/micro areas, CSA, congressional district, ZIP Code); Puerto Rico and Island Areas also covered | E99: zip | F99: 1986-2023 annual (datasets 'from 1986 to the current reference year'; tables on data.census.gov from 2012); Latest Data: 2023 | G99: 2023 | H99: public_domain_us_federal | J99: open_download | K99: csv | L99: Joins today | M99: 2 | O99: Gold | P99: 93 | Q99: https://www.census.gov/programs-surveys/cbp.html | R99: us_census_cbp
A100: Derived map of global electricity transmission and distribution lines (Global Electrification Database) | B100: World Bank | C100: built_environment | D100: global | E100: line | H100: open | I100: CC BY 4.0 | J100: open_download | K100: gpkg; tif; ArcGIS Feature Service | L100: Needs raster support | M100: 2 | O100: Silver | P100: 92 | Q100: https://datacatalog.worldbank.org/search/dataset/0038055/Global-Electrification-Database-from-Tracking-SDG7-The-Energy-Progress-Report | R100: global_worldbank_global_electrification_grid_map
...

Sheet Browser queue
A1: Domain | B1: Dataset | C1: Reason | D1: What to confirm | E1: Shortlist | F1: Landing page | G1: Archive copy | H1: id
A2: admin.ch | B2: STATPOP - Population and households, hectare grid (GEOSTAT) | C2: fetcher got a challenge/empty page | D2: page loads and names this dataset; not retired or discontinued; licence / terms; years covered and latest year; finest spatial unit (listed: grid_100m); access route; download formats | F2: https://www.bfs.admin.ch/bfs/en/home/services/geostat/swiss-federal-statistics-geodata/population-buildings-dwellings-persons/population-housholds-from-2010.html | G2: https://web.archive.org/web/20260520075218/https://www.bfs.admin.ch/bfs/en/home/services/geostat/swiss-federal-statistics-geodata/population-buildings-dwellings-persons/population-housholds-from-2010.html | H2: ch_bfs_statpop_hectare
A3: arcgis.com | B3: WFIGS Interagency Fire Perimeters (current and full history) | C3: fetcher got a challenge/empty page | D3: page loads and names this dataset; not retired or discontinued; licence / terms; years covered and latest year; finest spatial unit (listed: polygon); access route; download formats | E3: yes | F3: https://data-nifc.opendata.arcgis.com/ | G3: https://web.archive.org/web/20261002064241/https://data-nifc.opendata.arcgis.com/ | H3: us_nifc_wfigs_fire_perimeters
A4: arcgis.com | B4: 2015 Miami-Dade County DEM (10ft, 30ft, 100ft) | C4: fetcher got a challenge/empty page | D4: page loads and names this dataset; not retired or discontinued; licence / terms; years covered and latest year; finest spatial unit (listed: grid_); access route; download formats | F4: https://gis-mdc.opendata.arcgis.com/documents/MDC::2015-miami-dade-county-dem-10ft/about | G4: https://web.archive.org/web/20260122142655/https://gis-mdc.opendata.arcgis.com/documents/MDC::2015-miami-dade-county-dem-10ft/about | H4: us_mdc_2015_dem
A5: arcgis.com | B5: City of Miami Comission Districts | C5: fetcher got a challenge/empty page | D5: page loads and names this dataset; not retired or discontinued; licence / terms; years covered and latest year; finest spatial unit (listed: unknown); access route; download formats | F5: https://datahub-miamigis.opendata.arcgis.com/datasets/1ff4f95b49e142ee8d4e93bb33a9f42d_0/explore | H5: us_com_comission_districts
A6: arcgis.com | B6: HUD eGIS Open Data (HUD-eGIS Storefront) | C6: fetcher got a challenge/empty page | D6: page loads and names this dataset; not retired or discontinued; licence / terms; years covered and latest year; finest spatial unit (listed: point); access route; download formats | F6: https://hudgis-hud.opendata.arcgis.com/ | G6: https://web.archive.org/web/20261017065844/https://hudgis-hud.opendata.arcgis.com/ | H6: us_hud_egis_open_data
A7: arcgis.com | B7: Miami-Dade Bodies of Water | C7: fetcher got a challenge/empty page | D7: page loads and names this dataset; not retired or discontinued; licence / terms; years covered and latest year; finest spatial unit (listed: unknown); access route; download formats | F7: https://gis-mdc.opendata.arcgis.com/datasets/MDC::water-p/about | G7: https://web.archive.org/web/20260122123145/https://gis-mdc.opendata.arcgis.com/datasets/MDC::water-p/about | H7: us_mdc_water_polygons
A8: arcgis.com | B8: Miami-Dade Brownfield Sites | C8: fetcher got a challenge/empty page | D8: page loads and names this dataset; not retired or discontinued; licence / terms; years covered and latest year; finest spatial unit (listed: unknown); access route; download formats | F8: https://gis-mdc.opendata.arcgis.com/datasets/MDC::brownfield/about | G8: https://web.archive.org/web/20260215163426/https://gis-mdc.opendata.arcgis.com/datasets/MDC::brownfield/about | H8: gaia_mdc_brownfield_site
A9: arcgis.com | B9: Miami-Dade Community Health Centers | C9: fetcher got a challenge/empty page | D9: page loads and names this dataset; not retired or discontinued; licence / terms; years covered and latest year; finest spatial unit (listed: unknown); access route; download formats | F9: https://gis-mdc.opendata.arcgis.com/datasets/MDC::commercial-property/about | G9: https://web.archive.org/web/20260215165215/https://gis-mdc.opendata.arcgis.com/datasets/MDC::commercial-property/about | H9: us_mdc_community_health_centers
A10: arcgis.com | B10: Miami-Dade Community Redevelopment Areas | C10: fetcher got a challenge/empty page | D10: page loads and names this dataset; not retired or discontinued; licence / terms; years covered and latest year; finest spatial unit (listed: unknown); access route; download formats | F10: https://gis-mdc.opendata.arcgis.com/datasets/MDC::community-redevelopment-area/about | G10: https://web.archive.org/web/20260122125148/https://gis-mdc.opendata.arcgis.com/datasets/MDC::community-redevelopment-area/about | H10: us_mdc_community_redevelopment_agency
A11: arcgis.com | B11: Miami-Dade County Comission Districts | C11: fetcher got a challenge/empty page | D11: page loads and names this dataset; not retired or discontinued; licence / terms; years covered and latest year; finest spatial unit (listed: unknown); access route; download formats | F11: https://gis-mdc.opendata.arcgis.com/datasets/21f56c05380e477ea3008fd527ddafe4_0/explore | H11: us_mdc_comission_districts
A12: arcgis.com | B12: Miami-Dade County Municipal Park Boundaries | C12: fetcher got a challenge/empty page | D12: page loads and names this dataset; not retired or discontinued; licence / terms; years covered and latest year; finest spatial unit (listed: unknown); access route; download formats | F12: https://gis-mdc.opendata.arcgis.com/datasets/MDC::municipal-park-boundary/about | G12: https://web.archive.org/web/20260509194903/https://gis-mdc.opendata.arcgis.com/datasets/MDC::municipal-park-boundary/about | H12: us_mdc_municipal_park_boundaries
A13: arcgis.com | B13: Miami-Dade County Park Boundaries | C13: fetcher got a challenge/empty page | D13: page loads and names this dataset; not retired or discontinued; licence / terms; years covered and latest year; finest spatial unit (listed: unknown); access route; download formats | F13: https://gis-mdc.opendata.arcgis.com/datasets/MDC::county-park-boundary-view/about | G13: https://web.archive.org/web/20260122133747/https://gis-mdc.opendata.arcgis.com/datasets/MDC::county-park-boundary-view/about | H13: us_mdc_county_park_boundaries
A14: arcgis.com | B14: Miami-Dade County Unincorporated Zone District Specifications | C14: fetcher got a challenge/empty page | D14: page loads and names this dataset; not retired or discontinued; licence / terms; years covered and latest year; finest spatial unit (listed: unknown); access route; download formats | F14: https://gis-mdc.opendata.arcgis.com/datasets/276ee4451b604600b8fcd8e870bd524a_0/explore | H14: us_mdc_unincorporated_zone_desc
A15: arcgis.com | B15: Miami-Dade Federally Qualified Health Centers | C15: fetcher got a challenge/empty page | D15: page loads and names this dataset; not retired or discontinued; licence / terms; years covered and latest year; finest spatial unit (listed: unknown); access route; download formats | F15: https://gis-mdc.opendata.arcgis.com/datasets/MDC::federally-qualified-health-center/about | G15: https://web.archive.org/web/20260415064110/https://gis-mdc.opendata.arcgis.com/datasets/MDC::federally-qualified-health-center/about | H15: us_mdc_federally_qualified_health_centers
A16: arcgis.com | B16: Miami-Dade Hospitals | C16: fetcher got a challenge/empty page | D16: page loads and names this dataset; not retired or discontinued; licence / terms; years covered and latest year; finest spatial unit (listed: unknown); access route; download formats | F16: https://gis-mdc.opendata.arcgis.com/datasets/MDC::hospital/about | G16: https://web.archive.org/web/20260422110213/https://gis-mdc.opendata.arcgis.com/datasets/MDC::hospital/about | H16: us_mdc_hospitals
A17: arcgis.com | B17: Miami-Dade Qualified Opportunity Zones | C17: fetcher got a challenge/empty page | D17: page loads and names this dataset; not retired or discontinued; licence / terms; years covered and latest year; finest spatial unit (listed: unknown); access route; download formats | F17: https://gis-mdc.opendata.arcgis.com/datasets/MDC::qualified-opportunity-zones/about | G17: https://web.archive.org/web/20260122142303/https://gis-mdc.opendata.arcgis.com/datasets/MDC::qualified-opportunity-zones/about | H17: us_mdc_qualified_opportunity_zones
A18: arcgis.com | B18: Miami-Dade Superfund Sites | C18: fetcher got a challenge/empty page | D18: page loads and names this dataset; not retired or discontinued; licence / terms; years covered and latest year; finest spatial unit (listed: unknown); access route; download formats | F18: https://gis-mdc.opendata.arcgis.com/datasets/MDC::super-fund-site/about | G18: https://web.archive.org/web/20260122141750/https://gis-mdc.opendata.arcgis.com/datasets/MDC::super-fund-site/about | H18: us_mdc_superfund_site
A19: arcgis.com | B19: Public Housing Developments | C19: fetcher got a challenge/empty page | D19: page loads and names this dataset; not retired or discontinued; licence / terms; years covered and latest year; finest spatial unit (listed: point); access route; download formats | F19: https://hudgis-hud.opendata.arcgis.com/datasets/HUD::public-housing-developments-1/about | G19: https://web.archive.org/web/20260412154854/https://hudgis-hud.opendata.arcgis.com/datasets/HUD::public-housing-developments-1/about | H19: us_hud_public_housing_developments
A20: bbs.gov.bd | B20: Population and Housing Census 2022 (Bangladesh) | C20: certificate: tls_invalid | D20: browser accepts the certificate (tls_invalid); page loads and names this dataset; not retired or discontinued; licence / terms; years covered and latest year; finest spatial unit (listed: admin2); access route; download formats | E20: yes | F20: https://bbs.gov.bd/ | G20: https://web.archive.org/web/20261017141429/https://bbs.gov.bd/ | H20: bd_bbs_census_2022
A21: bogota.gov.co | B21: Estratos Socioeconómicos de Bogotá Según Manzanas | C21: fetcher got a challenge/empty page | D21: page loads and names this dataset; not retired or discontinued; licence / terms; years covered and latest year; finest spatial unit (listed: unknown); access route; download formats | F21: https://datosabiertos.bogota.gov.co/dataset/estratificacion-para-bogota | G21: https://web.archive.org/web/20250717124908/https://datosabiertos.bogota.gov.co/dataset/estratificacion-para-bogota | H21: gaia_bogota_2019_estratos_manzana_dane
A22: bps.go.id | B22: Potensi Desa (Podes) 2024 - village potential statistics | C22: blocked_bot (401/403/202 challenge) | D22: page loads and names this dataset; not retired or discontinued; licence / terms; years covered and latest year; finest spatial unit (listed: unknown); access route; download formats | F22: https://www.bps.go.id/en/publication/2024/12/10/2f5217e2d6a695a0830290a7/statistik-potensi-desa-indonesia-2024.html | G22: https://web.archive.org/web/20260423232955/https://www.bps.go.id/en/publication/2024/12/10/2f5217e2d6a695a0830290a7/statistik-potensi-desa-indonesia-2024.html | H22: id_bps_podes_2024
A23: bts.gov | B23: National Transportation Atlas Database (NTAD) | C23: fetcher got a challenge/empty page | D23: page loads and names this dataset; not retired or discontinued; licence / terms; years covered and latest year; finest spatial unit (listed: point); access route; download formats | F23: https://geodata.bts.gov/ | G23: https://web.archive.org/web/20261017131355/https://geodata.bts.gov/ | H23: us_bts_ntad
A24: censusindia.gov.in | B24: Census of India 2011 - Primary Census Abstract (village/town-wise) | C24: certificate: tls_incomplete_chain | D24: browser accepts the certificate (tls_incomplete_chain); page loads and names this dataset; not retired or discontinued; licence / terms; years covered and latest year; finest spatial unit (listed: postcode_small_area); access route; download formats | E24: yes | F24: https://censusindia.gov.in/census.website/data/census-tables | G24: https://web.archive.org/web/20261009012447/https://censusindia.gov.in/census.website/data/census-tables | H24: in_orgi_census_2011_pca
A25: cloudtostreet.ai | B25: Global Flood Database (Cloud to Street / Tellman et al. 2021): satellite-observed flood extents for 913 events, 2000-2018 | C25: fetcher got a challenge/empty page | D25: page loads and names this dataset; not retired or discontinued; licence / terms; years covered and latest year; finest spatial unit (listed: grid_250m); access route; download formats | F25: https://global-flood-database.cloudtostreet.ai/ | G25: https://web.archive.org/web/20260925102615/https://global-flood-database.cloudtostreet.ai/ | H25: global_cloudtostreet_global_flood_database
A26: cms.gov | B26: Provider of Services (POS) File - Hospital and Non-Hospital Facilities | C26: fetcher got a challenge/empty page | D26: page loads and names this dataset; not retired or discontinued; licence / terms; years covered and latest year; finest spatial unit (listed: point); access route; download formats | F26: https://data.cms.gov/provider-characteristics/hospitals-and-other-facilities/provider-of-services-file-hospital-non-hospital-facilities | G26: https://web.archive.org/web/20261016094400/https://data.cms.gov/provider-characteristics/hospitals-and-other-facilities/provider-of-services-file-hospital-non-hospital-facilities | H26: us_cms_provider_of_services
A27: columbia.edu | B27: Global Human Modification of Terrestrial Systems (Kennedy et al.), v1 | C27: timeout | D27: page loads and names this dataset; not retired or discontinued; licence / terms; years covered and latest year; finest spatial unit (listed: grid_1km); access route; download formats | F27: https://sedac.ciesin.columbia.edu/data/set/lulc-human-modification-terrestrial-systems | G27: https://web.archive.org/web/20250510143011/https://sedac.ciesin.columbia.edu/data/set/lulc-human-modification-terrestrial-systems | H27: global_sedac_human_modification
A28: copernicus.eu | B28: Urban Atlas (Functional Urban Areas land use/land cover) | C28: fetcher got a challenge/empty page | D28: page loads and names this dataset; not retired or discontinued; licence / terms; years covered and latest year; finest spatial unit (listed: postcode_small_area); access route; download formats | E28: yes | F28: https://land.copernicus.eu/en/products/urban-atlas | G28: https://web.archive.org/web/20260930191838/https://land.copernicus.eu/en/products/urban-atlas | H28: eu_copernicus_urban_atlas
A29: copernicus.eu | B29: European Flood Awareness System (EFAS) river discharge forecasts and historical simulations | C29: fetcher got a challenge/empty page | D29: page loads and names this dataset; not retired or discontinued; licence / terms; years covered and latest year; finest spatial unit (listed: grid_1.67km); access route; download formats | F29: https://european-flood.emergency.copernicus.eu/en/about-efas | H29: eu_copernicus_efas
A30: copernicus.eu | B30: Global Flood Awareness System (GloFAS) river discharge forecasts and historical reanalysis | C30: fetcher got a challenge/empty page | D30: page loads and names this dataset; not retired or discontinued; licence / terms; years covered and latest year; finest spatial unit (listed: grid_0.05deg); access route; download formats | F30: https://global-flood.emergency.copernicus.eu/ | G30: https://web.archive.org/web/20261008152401/https://global-flood.emergency.copernicus.eu/ | H30: global_copernicus_glofas
A31: dane.gov.co | B31: Marco Geoestadistico Nacional (MGN) 2018 | C31: fetcher got a challenge/empty page | D31: page loads and names this dataset; not retired or discontinued; licence / terms; years covered and latest year; finest spatial unit (listed: block); access route; download formats | F31: https://geoportal.dane.gov.co/ | G31: https://web.archive.org/web/20261017055007/https://geoportal.dane.gov.co/ | H31: co_dane_mgn
A32: digital.nhs.uk | B32: ODS GP and GP practice related data (epraccur) | C32: blocked_bot (401/403/202 challenge) | D32: page loads and names this dataset; not retired or discontinued; licence / terms; years covered and latest year; finest spatial unit (listed: point); access route; download formats | F32: https://digital.nhs.uk/services/organisation-data-service/export-data-files/csv-downloads/gp-and-gp-practice-related-data | G32: https://web.archive.org/web/20261014114155/https://digital.nhs.uk/services/organisation-data-service/export-data-files/csv-downloads/gp-and-gp-practice-related-data | H32: gb_nhs_ods_gp_practices
A33: dot.gov | B33: National Transit Database (NTD) | C33: blocked_bot (401/403/202 challenge) | D33: page loads and names this dataset; not retired or discontinued; licence / terms; years covered and latest year; finest spatial unit (listed: unknown); access route; download formats | F33: https://transit.dot.gov/ntd | G33: https://web.archive.org/web/20261017184426/https://transit.dot.gov/ntd | H33: us_fta_national_transit_database
A34: dwd.de | B34: GPCC Global Precipitation Climatology Centre gridded precipitation (Full Data Monthly/Daily, Monitoring, First Guess, Climatology, Drought Index) | C34: blocked_robots | D34: page loads and names this dataset; not retired or discontinued; licence / terms; years covered and latest year; finest spatial unit (listed: grid_0.25deg); access route; download formats | F34: https://www.dwd.de/EN/ourservices/gpcc/gpcc.html | G34: https://web.archive.org/web/20261016191117/https://www.dwd.de/EN/ourservices/gpcc/gpcc.html | H34: global_dwd_gpcc
A35: eia.gov | B35: U.S. Energy Atlas (EIA energy infrastructure map layers) | C35: fetcher got a challenge/empty page | D35: page loads and names this dataset; not retired or discontinued; licence / terms; years covered and latest year; finest spatial unit (listed: point); access route; download formats | F35: https://atlas.eia.gov/ | G35: https://web.archive.org/web/20261017014449/https://atlas.eia.gov/ | H35: us_eia_energy_atlas
A36: energydata.info | B36: Africa Infrastructure Country Diagnostic (AICD) spatial database | C36: blocked_bot (401/403/202 challenge) | D36: page loads and names this dataset; not retired or discontinued; licence / terms; years covered and latest year; finest spatial unit (listed: point); access route; download formats | F36: https://energydata.info/dataset?tags=AICD | H36: global_worldbank_aicd_spatial
A37: epa.gov | B37: RCRAInfo Public Data Export (hazardous waste handlers, Biennial Report) | C37: fetcher got a challenge/empty page | D37: page loads and names this dataset; not retired or discontinued; licence / terms; years covered and latest year; finest spatial unit (listed: point); access route; download formats | F37: https://rcrapublic.epa.gov/rcra-public-export | G37: https://web.archive.org/web/20251213070317/https://rcrapublic.epa.gov/rcra-public-export | H37: us_epa_rcrainfo_public_export
A38: europa.eu | B38: ECDC Surveillance Atlas of Infectious Diseases | C38: fetcher got a challenge/empty page | D38: page loads and names this dataset; not retired or discontinued; licence / terms; years covered and latest year; finest spatial unit (listed: country); access route; download formats | F38: https://atlas.ecdc.europa.eu/public/index.aspx | G38: https://web.archive.org/web/20261016044806/https://atlas.ecdc.europa.eu/public/index.aspx | H38: eu_ecdc_surveillance_atlas
A39: europa.eu | B39: JRC Global River Flood Hazard Maps (return periods 10-500 yr) | C39: fetcher got a challenge/empty page | D39: page loads and names this dataset; not retired or discontinued; licence / terms; years covered and latest year; finest spatial unit (listed: grid_30arcsec); access route; download formats | F39: https://data.jrc.ec.europa.eu/collection/id-0054 | G39: https://web.archive.org/web/20261012010118/https://data.jrc.ec.europa.eu/collection/id-0054 | H39: global_jrc_global_flood_hazard_maps
A40: europa.eu | B40: World Atlas of Desertification (WAD) third edition and geoportal datasets (land degradation, SDG 15.3.1) | C40: blocked_bot (401/403/202 challenge) | D40: page loads and names this dataset; not retired or discontinued; licence / terms; years covered and latest year; finest spatial unit (listed: grid_1km); access route; download formats | F40: https://wad.jrc.ec.europa.eu/ | G40: https://web.archive.org/web/20260927003709/https://wad.jrc.ec.europa.eu/ | H40: global_jrc_world_atlas_desertification
A41: fao.org | B41: FAOSTAT | C41: fetcher got a challenge/empty page | D41: page loads and names this dataset; not retired or discontinued; licence / terms; years covered and latest year; finest spatial unit (listed: country); access route; download formats | F41: https://www.fao.org/faostat/en/ | G41: https://web.archive.org/web/20261018112009/https://www.fao.org/faostat/en/ | H41: global_fao_faostat
A42: fao.org | B42: Global Agro-Ecological Zones (GAEZ v4) | C42: fetcher got a challenge/empty page | D42: page loads and names this dataset; not retired or discontinued; licence / terms; years covered and latest year; finest spatial unit (listed: grid_); access route; download formats | F42: https://gaez.fao.org/ | G42: https://web.archive.org/web/20261008151552/https://gaez.fao.org/ | H42: global_fao_gaez
A43: fao.org | B43: Hand-in-Hand Geospatial Platform | C43: fetcher got a challenge/empty page | D43: page loads and names this dataset; not retired or discontinued; licence / terms; years covered and latest year; finest spatial unit (listed: grid_); access route; download formats | F43: https://data.apps.fao.org/ | G43: https://web.archive.org/web/20261016174729/https://data.apps.fao.org/ | H43: global_fao_hih_geospatial_platform
A44: fao.org | B44: WaPOR (Water Productivity through Open access of Remotely sensed derived data) | C44: fetcher got a challenge/empty page | D44: page loads and names this dataset; not retired or discontinued; licence / terms; years covered and latest year; finest spatial unit (listed: grid_300m); access route; download formats | F44: https://data.apps.fao.org/wapor/ | G44: https://web.archive.org/web/20261004162231/https://data.apps.fao.org/wapor/ | H44: global_fao_wapor
A45: fcc.gov | B45: FCC Broadband Data Collection / National Broadband Map | C45: blocked_bot (401/403/202 challenge) | D45: page loads and names this dataset; not retired or discontinued; licence / terms; years covered and latest year; finest spatial unit (listed: point); access route; download formats | F45: https://broadbandmap.fcc.gov/ | G45: https://web.archive.org/web/20261017122816/https://broadbandmap.fcc.gov/ | H45: us_fcc_broadband_data_collection
A46: fgov.be | B46: Statistical sectors (secteurs statistiques / statistische sectoren) | C46: fetcher got a challenge/empty page | D46: page loads and names this dataset; not retired or discontinued; licence / terms; years covered and latest year; finest spatial unit (listed: postcode_small_area); access route; download formats | F46: https://statbel.fgov.be/en/open-data/statistical-sectors-2023 | G46: https://web.archive.org/web/20241114170127/https://statbel.fgov.be/en/open-data/statistical-sectors-2023 | H46: be_statbel_statistical_sectors
A47: figshare.com | B47: Global surface NO2 concentrations 1990-2020 (Anenberg, Mohegh, Larkin et al.) | C47: blocked_bot (401/403/202 challenge) | D47: page loads and names this dataset; not retired or discontinued; licence / terms; years covered and latest year; finest spatial unit (listed: grid_1km); access route; download formats | F47: https://figshare.com/articles/dataset/Global_surface_NO2_concentrations_1990-2020/12968114/4 | G47: https://web.archive.org/web/20251219123741/https://figshare.com/articles/dataset/Global_surface_NO2_concentrations_1990-2020/12968114/4 | H47: global_anenberg_surface_no2
A48: firststreet.org | B48: First Street climate risk models (Flood Factor, Fire Factor, Heat Factor, Wind Factor, Air Factor) | C48: fetcher got a challenge/empty page | D48: page loads and names this dataset; not retired or discontinued; licence / terms; years covered and latest year; finest spatial unit (listed: point); access route; download formats | F48: https://firststreet.org/ | G48: https://web.archive.org/web/20261012215820/https://firststreet.org/ | H48: us_firststreet_risk_factors
... A54: gob.pe | B54: Catastro Minero Huayhuash (INGEMMET) | C54: certificate: tls_incomplete_chain | D54: browser accepts the certificate (tls_incomplete_chain); page loads and names this dataset; not retired or discontinued; licence / terms; years covered and latest year; finest spatial unit (listed: unknown); access route; download formats | F54: https://geocatmin.ingemmet.gob.pe/arcgis/rest/services/SERV_CATASTRO_MINERO_WGS84/MapServer/0 | G54: https://web.archive.org/web/20250528032053/https://geocatmin.ingemmet.gob.pe/arcgis/rest/services/SERV_CATASTRO_MINERO_WGS84/MapServer/0 | H54: pe_catastrominero_ingemmet
A55: gob.pe | B55: Catastro Rural and Comunidades Campesinas (MIDAGRI) | C55: certificate: tls_incomplete_chain | D55: browser accepts the certificate (tls_incomplete_chain); page loads and names this dataset; not retired or discontinued; licence / terms; years covered and latest year; finest spatial unit (listed: unknown); access route; download formats | F55: https://georural.midagri.gob.pe/geoservicios/rest/services/public/Catastro_Rural/MapServer/0 | H55: pe_midagri_catastro_rural
A56: gob.pe | B56: Centros Poblados (capital distrital, capital provincial, centros poblados, dispersos) (IDEP/IGN/INEI) | C56: timeout | D56: page loads and names this dataset; not retired or discontinued; licence / terms; years covered and latest year; finest spatial unit (listed: unknown); access route; download formats | F56: https://www.idep.gob.pe/geoportal/rest/services/DATOS_GEOESPACIALES/CENTROS_POBLADOS/FeatureServer/2 | G56: https://web.archive.org/web/20250627040223/https://www.idep.gob.pe/geoportal/rest/services/DATOS_GEOESPACIALES/CENTROS_POBLADOS/FeatureServer/2 | H56: pe_idep_centros_poblados
A57: gob.pe | B57: Glaciares Huayhuash (ANA) | C57: timeout | D57: page loads and names this dataset; not retired or discontinued; licence / terms; years covered and latest year; finest spatial unit (listed: unknown); access route; download formats | F57: https://geosnirh.ana.gob.pe/server/rest/services/P%C3%BAblico/Glaciares/MapServer | G57: https://web.archive.org/web/20250614185443/https://geosnirh.ana.gob.pe/server/rest/services/P%C3%BAblico/Glaciares/MapServer | H57: pe_glaciares_ana
A58: gob.pe | B58: Inventario Bofedales Huayhuash 2023 (INAIGEM) | C58: fetcher got a challenge/empty page | D58: page loads and names this dataset; not retired or discontinued; licence / terms; years covered and latest year; finest spatial unit (listed: unknown); access route; download formats | F58: https://datacochageoespacial.inaigem.gob.pe/geonetwork/srv/spa/catalog.search#/metadata/0b17e18e-2622-4158-9cc5-a31a587743df | H58: pe_2023_bofedales_inaigem
A59: gob.pe | B59: Lagos y Lagunas Huayhuash (ANA) | C59: timeout | D59: page loads and names this dataset; not retired or discontinued; licence / terms; years covered and latest year; finest spatial unit (listed: unknown); access route; download formats | F59: https://geosnirh.ana.gob.pe/server/rest/services/P%C3%BAblico/Lagunas/MapServer/36 | G59: https://web.archive.org/web/20250712095632/https://geosnirh.ana.gob.pe/server/rest/services/P%C3%BAblico/Lagunas/MapServer/36 | H59: pe_lagunas_ana
A60: gob.pe | B60: Limites Departamental, Provincial y Distrital (MINAM geoservidor) | C60: fetcher got a challenge/empty page | D60: page loads and names this dataset; not retired or discontinued; licence / terms; years covered and latest year; finest spatial unit (listed: unknown); access route; download formats | F60: https://geoservidorperu.minam.gob.pe/arcgis/rest/services/ServicioBase/MapServer/14 | G60: https://web.archive.org/web/20220818064902/https://geoservidorperu.minam.gob.pe/arcgis/rest/services/ServicioBase/MapServer/14 | H60: pe_minam_limites_administrativos
A61: gob.pe | B61: Ríos Huayhuash | C61: timeout | D61: page loads and names this dataset; not retired or discontinued; licence / terms; years covered and latest year; finest spatial unit (listed: unknown); access route; download formats | F61: https://geosnirh.ana.gob.pe/server/rest/services/P%C3%BAblico/Rios/MapServer/37 | G61: https://web.archive.org/web/20250715095938/https://geosnirh.ana.gob.pe/server/rest/services/P%C3%BAblico/Rios/MapServer/37 | H61: gaia_hh_rios_ana
A62: grid3.org | B62: GRID3 settlement extents (v3, 52 sub-Saharan African countries) and GRID3 health facilities, boundaries, population datasets | C62: fetcher got a challenge/empty page | D62: page loads and names this dataset; not retired or discontinued; licence / terms; years covered and latest year; finest spatial unit (listed: point); access route; download formats | F62: https://data.grid3.org/ | G62: https://web.archive.org/web/20261017073704/https://data.grid3.org/ | H62: af_grid3_settlement_extents
A63: harvard.edu | B63: CIESIN subcollection (rescued SEDAC datasets) on Harvard Dataverse, CAFE collection | C63: blocked_bot (401/403/202 challenge) | D63: page loads and names this dataset; not retired or discontinued; licence / terms; years covered and latest year; finest spatial unit (listed: unknown); access route; download formats | F63: https://dataverse.harvard.edu/dataverse/ciesin | G63: https://web.archive.org/web/20260519125200/https://dataverse.harvard.edu/dataverse/ciesin | H63: global_ciesin_harvard_dataverse_sedac_collection
A64: harvard.edu | B64: Harvard Dataverse (listing) | C64: blocked_bot (401/403/202 challenge) | D64: page loads and names this dataset; not retired or discontinued; licence / terms; years covered and latest year; finest spatial unit (listed: unknown); access route; download formats | F64: https://dataverse.harvard.edu/ | G64: https://web.archive.org/web/20261016002746/https://dataverse.harvard.edu/ | H64: us_harvard_dataverse
A65: healthdata.org | B65: GBD 2021 Air Pollution Exposure Estimates 1990-2021 (ambient PM2.5, ozone, household air pollution) | C65: fetcher got a challenge/empty page | D65: page loads and names this dataset; not retired or discontinued; licence / terms; years covered and latest year; finest spatial unit (listed: grid_0.1deg); access route; download formats | F65: https://ghdx.healthdata.org/record/ihme-data/gbd-2021-air-pollution-exposure-estimates-1990-2021 | G65: https://web.archive.org/web/20260327205246/https://ghdx.healthdata.org/record/ihme-data/gbd-2021-air-pollution-exposure-estimates-1990-2021 | H65: global_ihme_gbd_air_pollution_exposure
A66: heat.gov | B66: NIHHIS heat.gov | C66: blocked_bot (401/403/202 challenge) | D66: page loads and names this dataset; not retired or discontinued; licence / terms; years covered and latest year; finest spatial unit (listed: unknown); access route; download formats | F66: https://www.heat.gov/ | G66: https://web.archive.org/web/20261017075152/https://www.heat.gov/ | H66: us_noaa_nihhis_heat_gov
A67: hhearprogram.org | B67: Human Health Exposure Analysis Resource (HHEAR, formerly CHEAR) | C67: timeout | D67: page loads and names this dataset; not retired or discontinued; licence / terms; years covered and latest year; finest spatial unit (listed: unknown); access route; download formats | F67: https://hhearprogram.org/ | G67: https://web.archive.org/web/20260323022914/https://hhearprogram.org/ | H67: us_niehs_hhear
A68: huduser.gov | B68: HUD Aggregated USPS Administrative Data on Address Vacancies | C68: blocked_bot (401/403/202 challenge) | D68: page loads and names this dataset; not retired or discontinued; licence / terms; years covered and latest year; finest spatial unit (listed: tract); access route; download formats | E68: yes | F68: https://www.huduser.gov/portal/datasets/usps.html | G68: https://web.archive.org/web/20261015235729/https://www.huduser.gov/portal/datasets/usps.html | H68: us_hud_usps_vacancy
A69: huduser.gov | B69: Picture of Subsidized Households | C69: blocked_bot (401/403/202 challenge) | D69: page loads and names this dataset; not retired or discontinued; licence / terms; years covered and latest year; finest spatial unit (listed: tract); access route; download formats | E69: yes | F69: https://www.huduser.gov/portal/datasets/assthsg.html | G69: https://web.archive.org/web/20261017030107/https://www.huduser.gov/portal/datasets/assthsg.html | H69: us_hud_picture_of_subsidized_households
A70: huduser.gov | B70: HUD-USPS ZIP Code Crosswalk Files | C70: blocked_bot (401/403/202 challenge) | D70: page loads and names this dataset; not retired or discontinued; licence / terms; years covered and latest year; finest spatial unit (listed: tract); access route; download formats | F70: https://www.huduser.gov/portal/datasets/usps_crosswalk.html | G70: https://web.archive.org/web/20261014184547/https://www.huduser.gov/portal/datasets/usps_crosswalk.html | H70: us_hud_usps_zip_crosswalk
A71: huduser.gov | B71: Low-Income Housing Tax Credit (LIHTC) Database | C71: blocked_bot (401/403/202 challenge) | D71: page loads and names this dataset; not retired or discontinued; licence / terms; years covered and latest year; finest spatial unit (listed: point); access route; download formats | F71: https://www.huduser.gov/portal/datasets/lihtc.html | G71: https://web.archive.org/web/20261016061218/https://www.huduser.gov/portal/datasets/lihtc.html | H71: us_hud_lihtc
A72: huduser.gov | B72: Qualified Census Tracts (QCT) and Difficult Development Areas (DDA) | C72: blocked_bot (401/403/202 challenge) | D72: page loads and names this dataset; not retired or discontinued; licence / terms; years covered and latest year; finest spatial unit (listed: tract); access route; download formats | F72: https://www.huduser.gov/portal/datasets/qct.html | G72: https://web.archive.org/web/20261014184545/https://www.huduser.gov/portal/datasets/qct.html | H72: us_hud_qct_dda
A73: humdata.org | B73: COX'S Bazar District - Teknaf and Ukhia Upazila Para and Ward Locations | C73: blocked_bot (401/403/202 challenge) | D73: page loads and names this dataset; not retired or discontinued; licence / terms; years covered and latest year; finest spatial unit (listed: admin2); access route; download formats | E73: yes | F73: https://data.humdata.org/dataset/cox-s-bazar-district-teknaf-and-ukhia-upazila-para-and-ward-locations | G73: https://web.archive.org/web/20221212215339/https://data.humdata.org/dataset/cox-s-bazar-district-teknaf-and-ukhia-upazila-para-and-ward-locations | H73: hdx_cox_s_bazar_district_teknaf_and_ukhia_upazila_para_and
A74: humdata.org | B74: Kenya - Household income statistics in Bomet county | C74: blocked_bot (401/403/202 challenge) | D74: page loads and names this dataset; not retired or discontinued; licence / terms; years covered and latest year; finest spatial unit (listed: county); access route; download formats | E74: yes | F74: https://data.humdata.org/dataset/kenya-household-income-statistics-in-bomet-county | G74: https://web.archive.org/web/20220926125504/https://data.humdata.org/dataset/kenya-household-income-statistics-in-bomet-county | H74: hdx_kenya_household_income_statistics_in_bomet_county
A75: humdata.org | B75: Brazil: Epidemiological and hospital indicators on covid-19 in Ouro Preto | C75: blocked_bot (401/403/202 challenge) | D75: page loads and names this dataset; not retired or discontinued; licence / terms; years covered and latest year; finest spatial unit (listed: point); access route; download formats | F75: https://data.humdata.org/dataset/brazil-epidemiological-and-hospital-indicators-on-covid-19-in-ouro-preto | G75: https://web.archive.org/web/20260306020404/https://data.humdata.org/dataset/brazil-epidemiological-and-hospital-indicators-on-covid-19-in-ouro-preto | H75: hdx_brazil_epidemiological_and_hospital_indicators_on_covid
A76: humdata.org | B76: Colombia: Health Facilities | C76: blocked_bot (401/403/202 challenge) | D76: page loads and names this dataset; not retired or discontinued; licence / terms; years covered and latest year; finest spatial unit (listed: point); access route; download formats | F76: https://data.humdata.org/dataset/colombia-health-facilities-2021 | G76: https://web.archive.org/web/20260204173039/https://data.humdata.org/dataset/colombia-health-facilities-2021 | H76: hdx_colombia_health_facilities
A77: humdata.org | B77: Ethiopia - Health Facilities | C77: blocked_bot (401/403/202 challenge) | D77: page loads and names this dataset; not retired or discontinued; licence / terms; years covered and latest year; finest spatial unit (listed: point); access route; download formats | F77: https://data.humdata.org/dataset/ethiopian-health-facilities | G77: https://web.archive.org/web/20260311165304/https://data.humdata.org/dataset/ethiopian-health-facilities | H77: hdx_ethiopia_health_facilities
A78: humdata.org | B78: Ethiopia - Market Centers | C78: blocked_bot (401/403/202 challenge) | D78: page loads and names this dataset; not retired or discontinued; licence / terms; years covered and latest year; finest spatial unit (listed: point); access route; download formats | F78: https://data.humdata.org/dataset/ethiopia-market-centers | G78: https://web.archive.org/web/20260311165446/https://data.humdata.org/dataset/ethiopia-market-centers | H78: hdx_ethiopia_market_centers
A79: humdata.org | B79: Food Market Locations | C79: blocked_bot (401/403/202 challenge) | D79: page loads and names this dataset; not retired or discontinued; licence / terms; years covered and latest year; finest spatial unit (listed: point); access route; download formats | F79: https://data.humdata.org/dataset/food-market-locations | H79: hdx_food_market_locations
A80: humdata.org | B80: Global: Reported number of pregnant women presenting at antenatal clinics (ANC) who were tested for HIV or already knew their HIV positive status | C80: blocked_bot (401/403/202 challenge) | D80: page loads and names this dataset; not retired or discontinued; licence / terms; years covered and latest year; finest spatial unit (listed: point); access route; download formats | F80: https://data.humdata.org/dataset/unicef-hva-pmtct-stat-num | G80: https://web.archive.org/web/20250418044437/https://data.humdata.org/dataset/unicef-hva-pmtct-stat-num | H80: hdx_global_reported_number_of_pregnant_women_presenting_at
A81: humdata.org | B81: Health Facilities of Ghana | C81: blocked_bot (401/403/202 challenge) | D81: page loads and names this dataset; not retired or discontinued; licence / terms; years covered and latest year; finest spatial unit (listed: point); access route; download formats | F81: https://data.humdata.org/dataset/hotosm_gha_health_facilities | G81: https://web.archive.org/web/20260212074044/https://data.humdata.org/dataset/hotosm_gha_health_facilities | H81: hdx_health_facilities_of_ghana
A82: humdata.org | B82: Health Facilities of India | C82: blocked_bot (401/403/202 challenge) | D82: page loads and names this dataset; not retired or discontinued; licence / terms; years covered and latest year; finest spatial unit (listed: point); access route; download formats | F82: https://data.humdata.org/dataset/hotosm_ind_health_facilities | H82: hdx_health_facilities_of_india
A83: humdata.org | B83: Health Facilities of Indonesia | C83: blocked_bot (401/403/202 challenge) | D83: page loads and names this dataset; not retired or discontinued; licence / terms; years covered and latest year; finest spatial unit (listed: point); access route; download formats | F83: https://data.humdata.org/dataset/hotosm_idn_health_facilities | G83: https://web.archive.org/web/20260131010112/https://data.humdata.org/dataset/hotosm_idn_health_facilities | H83: hdx_health_facilities_of_indonesia
A84: humdata.org | B84: Health Facilities of Kenya | C84: blocked_bot (401/403/202 challenge) | D84: page loads and names this dataset; not retired or discontinued; licence / terms; years covered and latest year; finest spatial unit (listed: point); access route; download formats | F84: https://data.humdata.org/dataset/hotosm_ken_health_facilities | G84: https://web.archive.org/web/20260120051822/https://data.humdata.org/dataset/hotosm_ken_health_facilities | H84: hdx_health_facilities_of_kenya
A85: humdata.org | B85: Health Facilities of Philippines | C85: blocked_bot (401/403/202 challenge) | D85: page loads and names this dataset; not retired or discontinued; licence / terms; years covered and latest year; finest spatial unit (listed: point); access route; download formats | F85: https://data.humdata.org/dataset/hotosm_phl_health_facilities | G85: https://web.archive.org/web/20260224064145/https://data.humdata.org/dataset/hotosm_phl_health_facilities | H85: hdx_health_facilities_of_philippines
A86: humdata.org | B86: Hospitals of Nepal | C86: blocked_bot (401/403/202 challenge) | D86: page loads and names this dataset; not retired or discontinued; licence / terms; years covered and latest year; finest spatial unit (listed: point); access route; download formats | F86: https://data.humdata.org/dataset/osgeonepal_npl_hospitals | G86: https://web.archive.org/web/20260411071142/https://data.humdata.org/dataset/osgeonepal_npl_hospitals | H86: hdx_hospitals_of_nepal
A87: humdata.org | B87: Nigeria: Health facilities | C87: blocked_bot (401/403/202 challenge) | D87: page loads and names this dataset; not retired or discontinued; licence / terms; years covered and latest year; finest spatial unit (listed: point); access route; download formats | F87: https://data.humdata.org/dataset/nigeria-health-facilities | G87: https://web.archive.org/web/20260210235610/https://data.humdata.org/dataset/nigeria-health-facilities | H87: hdx_nigeria_health_facilities
A88: humdata.org | B88: Nigeria: Hospitals and Clinics with registration status and Location | C88: blocked_bot (401/403/202 challenge) | D88: page loads and names this dataset; not retired or discontinued; licence / terms; years covered and latest year; finest spatial unit (listed: point); access route; download formats | F88: https://data.humdata.org/dataset/nigeria-hospitals-and-clinics-with-registration-status-and-location | G88: https://web.archive.org/web/20260210235810/https://data.humdata.org/dataset/nigeria-hospitals-and-clinics-with-registration-status-and-location | H88: hdx_nigeria_hospitals_and_clinics_with_registration_status
A89: humdata.org | B89: Public Hospitals in Myanmar | C89: blocked_bot (401/403/202 challenge) | D89: page loads and names this dataset; not retired or discontinued; licence / terms; years covered and latest year; finest spatial unit (listed: point); access route; download formats | F89: https://data.humdata.org/dataset/mimu-geonode-public-hospitals-in-myanmar | G89: https://web.archive.org/web/20260928130304/https://data.humdata.org/dataset/mimu-geonode-public-hospitals-in-myanmar | H89: hdx_public_hospitals_in_myanmar
A90: humdata.org | B90: Somalia - Health Facilities | C90: blocked_bot (401/403/202 challenge) | D90: page loads and names this dataset; not retired or discontinued; licence / terms; years covered and latest year; finest spatial unit (listed: point); access route; download formats | F90: https://data.humdata.org/dataset/somalia-health-facilities-data | G90: https://web.archive.org/web/20260227134533/https://data.humdata.org/dataset/somalia-health-facilities-data | H90: hdx_somalia_health_facilities
A91: humdata.org | B91: Sudan: Prevalence of diseases in outpatient clinics per state | C91: blocked_bot (401/403/202 challenge) | D91: page loads and names this dataset; not retired or discontinued; licence / terms; years covered and latest year; finest spatial unit (listed: point); access route; download formats | F91: https://data.humdata.org/dataset/sudan-prevalence-of-diseases-in-outpatient-clinics-per-state | G91: https://web.archive.org/web/20260205051302/https://data.humdata.org/dataset/sudan-prevalence-of-diseases-in-outpatient-clinics-per-state | H91: hdx_sudan_prevalence_of_diseases_in_outpatient_clinics_per
A92: humdata.org | B92: Tanzania: Market Price Survey for Essential Commodities | C92: blocked_bot (401/403/202 challenge) | D92: page loads and names this dataset; not retired or discontinued; licence / terms; years covered and latest year; finest spatial unit (listed: point); access route; download formats | F92: https://data.humdata.org/dataset/united-republic-of-tanzania-rapid-assessment-survey-of-market-prices | G92: https://web.archive.org/web/20260707004352/https://data.humdata.org/dataset/united-republic-of-tanzania-rapid-assessment-survey-of-market-prices | H92: hdx_tanzania_market_price_survey_for_essential_commodities
A93: humdata.org | B93: Ugandan Regional and General Hospitals | C93: blocked_bot (401/403/202 challenge) | D93: page loads and names this dataset; not retired or discontinued; licence / terms; years covered and latest year; finest spatial unit (listed: point); access route; download formats | F93: https://data.humdata.org/dataset/ugandan-regional-and-general-hospitals | G93: https://web.archive.org/web/20220512170932/https://data.humdata.org/dataset/ugandan-regional-and-general-hospitals | H93: hdx_ugandan_regional_and_general_hospitals
A94: humdata.org | B94: Venezuela - Earthquake Hazardous Facilities | C94: blocked_bot (401/403/202 challenge) | D94: page loads and names this dataset; not retired or discontinued; licence / terms; years covered and latest year; finest spatial unit (listed: point); access route; download formats | F94: https://data.humdata.org/dataset/venezuela-earthquake-hazardous-facilities | G94: https://web.archive.org/web/20260630155543/https://data.humdata.org/dataset/venezuela-earthquake-hazardous-facilities | H94: hdx_venezuela_earthquake_hazardous_facilities
A95: ibge.gov.br | B95: Censo Demografico 2022 - Agregados por setores censitarios | C95: blocked_bot (401/403/202 challenge) | D95: page loads and names this dataset; not retired or discontinued; licence / terms; years covered and latest year; finest spatial unit (listed: postcode_small_area); access route; download formats | E95: yes | F95: https://www.ibge.gov.br/estatisticas/sociais/populacao/22827-censo-demografico-2022.html | G95: https://web.archive.org/web/20261010164327/https://www.ibge.gov.br/estatisticas/sociais/populacao/22827-censo-demografico-2022.html | H95: br_ibge_censo_2022_setores
A96: ibge.gov.br | B96: Malhas territoriais (malha de setores censitarios, municipios, UF) | C96: blocked_bot (401/403/202 challenge) | D96: page loads and names this dataset; not retired or discontinued; licence / terms; years covered and latest year; finest spatial unit (listed: postcode_small_area); access route; download formats | F96: https://www.ibge.gov.br/geociencias/organizacao-do-territorio/malhas-territoriais/15774-malhas.html | G96: https://web.archive.org/web/20261004030554/https://www.ibge.gov.br/geociencias/organizacao-do-territorio/malhas-territoriais/15774-malhas.html | H96: br_ibge_malhas_territoriais
A97: inegi.org.mx | B97: Censo de Poblacion y Vivienda 2020 - Principales resultados por AGEB y manzana urbana | C97: fetcher got a challenge/empty page | D97: page loads and names this dataset; not retired or discontinued; licence / terms; years covered and latest year; finest spatial unit (listed: block); access route; download formats | E97: yes | F97: https://www.inegi.org.mx/programas/ccpv/2020/ | G97: https://web.archive.org/web/20261016202149/https://www.inegi.org.mx/programas/ccpv/2020/ | H97: mx_inegi_censo_2020_ageb_manzana
A98: inegi.org.mx | B98: Marco Geoestadistico | C98: fetcher got a challenge/empty page | D98: page loads and names this dataset; not retired or discontinued; licence / terms; years covered and latest year; finest spatial unit (listed: block); access route; download formats | F98: https://www.inegi.org.mx/temas/mg/ | G98: https://web.archive.org/web/20261015013331/https://www.inegi.org.mx/temas/mg/ | H98: mx_inegi_marco_geoestadistico
A99: istat.it | B99: Basi territoriali e variabili censuarie (sezioni di censimento) | C99: certificate: tls_handshake_failure | D99: browser accepts the certificate (tls_handshake_failure); page loads and names this dataset; not retired or discontinued; licence / terms; years covered and latest year; finest spatial unit (listed: unknown); access route; download formats | F99: https://www.istat.it/notizia/basi-territoriali-e-variabili-censuarie/ | G99: https://web.archive.org/web/20261007020256/https://www.istat.it/notizia/basi-territoriali-e-variabili-censuarie/ | H99: it_istat_basi_territoriali
A100: istat.it | B100: Indice di vulnerabilita sociale e materiale (IVSM) | C100: certificate: tls_handshake_failure | D100: browser accepts the certificate (tls_handshake_failure); page loads and names this dataset; not retired or discontinued; licence / terms; years covered and latest year; finest spatial unit (listed: unknown); access route; download formats | F100: https://www.istat.it/produzione-editoriale/le-misure-della-vulnerabilita-unapplicazione-a-diversi-ambiti-territoriali | G100: https://web.archive.org/web/20250407093526/https://www.istat.it/produzione-editoriale/le-misure-della-vulnerabilita-unapplicazione-a-diversi-ambiti-territoriali | H100: it_istat_ivsm
A101: knbs.or.ke | B101: 2019 Kenya Population and Housing Census (KPHC) results | C101: certificate: tls_incomplete_chain | D101: browser accepts the certificate (tls_incomplete_chain); page loads and names this dataset; not retired or discontinued; licence / terms; years covered and latest year; finest spatial unit (listed: postcode_small_area); access route; download formats | E101: yes | F101: https://www.knbs.or.ke/2019-kenya-population-and-housing-census-results/ | G101: https://web.archive.org/web/20261002090407/https://www.knbs.or.ke/2019-kenya-population-and-housing-census-results/ | H101: ke_knbs_census_2019
A102: malariaatlas.org | B102: Malaria Atlas Project (MAP) global rasters: Pf parasite rate, incidence, ITN coverage, accessibility to cities and healthcare travel time (Weiss et al.) | C102: fetcher got a challenge/empty page | D102: page loads and names this dataset; not retired or discontinued; licence / terms; years covered and latest year; finest spatial unit (listed: grid_5km); access route; download formats | F102: https://data.malariaatlas.org/ | G102: https://web.archive.org/web/20261009094156/https://data.malariaatlas.org/ | H102: global_malaria_atlas_project_rasters
A103: mdpi.com | B103: SAANS satellite-derived 1 km ambient PM2.5 for India (2000-2019) | C103: blocked_bot (401/403/202 challenge) | D103: page loads and names this dataset; not retired or discontinued; licence / terms; years covered and latest year; finest spatial unit (listed: grid_1km); access route; download formats | F103: https://www.mdpi.com/2072-4292/12/23/3872 | G103: https://web.archive.org/web/20260630043239/https://www.mdpi.com/2072-4292/12/23/3872 | H103: in_iitd_saans_pm25
A104: meta.com | B104: High Resolution Population Density Maps and Demographic Estimates (HRSL), Meta Data for Good with CIESIN | C104: fetcher got a challenge/empty page | D104: page loads and names this dataset; not retired or discontinued; licence / terms; years covered and latest year; finest spatial unit (listed: grid_30m); access route; download formats | F104: https://ai.meta.com/ai-for-good/datasets/high-resolution-population-density-maps/ | G104: https://web.archive.org/web/20260927092337/https://ai.meta.com/ai-for-good/datasets/high-resolution-population-density-maps/ | H104: global_meta_hrsl_population
A105: nasa.gov | B105: MERRA-2 tavg1_2d_aer_Nx: 2d, 1-Hourly, Time-averaged, Single-Level, Assimilation, Aerosol Diagnostics V5.12.4 (M2T1NXAER) | C105: fetcher got a challenge/empty page | D105: page loads and names this dataset; not retired or discontinued; licence / terms; years covered and latest year; finest spatial unit (listed: grid_0.5deg); access route; download formats | F105: https://disc.gsfc.nasa.gov/datasets/M2T1NXAER_5.12.4/summary | G105: https://web.archive.org/web/20260918043440/https://disc.gsfc.nasa.gov/datasets/M2T1NXAER_5.12.4/summary | H105: global_nasa_merra2_m2t1nxaer
...

Sheet Duplicates resolved
